Workbook
Name _01_: Approvers!$J$3:$J$19
Name AM110000_: Approvers!$J$20:$J$21
Name COSTCENTER: Approvers!$C$2:$C$208
Name CP110000_: Approvers!$J$22:$J$24
Name CT110000_: Approvers!$J$25:$J$27
Name DEPARTMENT: Approvers!$B$2:$B$109
Name DIVISION: Approvers!$A$2:$A$28
Name GM110000_: Approvers!$J$28:$J$33
Name GM210000_: Approvers!$J$34:$J$36
Name GM410000_: Approvers!$J$37:$J$39
Name GM510000_: Approvers!$J$40:$J$48
Name GM610000_: Approvers!$J$49:$J$49
Name GM710000_: Approvers!$J$50:$J$53
Name GM810000_: Approvers!$J$54:$J$56
Name GM910000_: Approvers!$J$57:$J$60
Name HS110000_: Approvers!$J$61:$J$84
Name HS210000_: Approvers!$J$85:$J$131
Name HS310000_: Approvers!$J$132:$J$134
Name HS810000_: Approvers!$J$135:$J$142
Name IA110000_: Approvers!$J$143
Name MULTI___BU: Approvers!$J$2
Name SH110000_: Approvers!$J$144:$J$159
Name SH110001_: Approvers!$J$157:$J$159
Name SH112000_: Approvers!$J$160:$J$161
Name SH113000_: Approvers!$J$162:$J$164
Name SH210000_: Approvers!$J$165:$J$169
Name SH310000_: Approvers!$J$170:$J$171
Name SH410000_: Approvers!$J$172:$J$189
Name SH510000_: Approvers!$J$190:$J$198
Name SH810000_: Approvers!$J$199:$J$203
Name SH910000_: Approvers!$J$204:$J$207

Sheet Dynamics Enum Cache

Sheet Bid Tab (F&B Ops and CatMan) 10
G2: BID TABULATION TEMPLATE - DETAILED | L2: SUPPLIER TYPE | M2: PROCUREMENT METHOD | O2: AWARD METHOD | AV2: Document Code | AX2: SCD-PSP-PRT-FO-004
G3: BID CATEGORY: | AV3: Revision Number | AX3: 06
G4: REQUESTING DIVISION: | AV4: Effective Date | AX4: 45474
G5: COST CENTER / NAME:
G6: SRF REFERENCE #: | AJ6: PRICE COMPARISON
G7: RINGI REFERENCE #: | AJ7: BIDDERS
AJ8: 1 | AP8: 2 | AV8: 3 | BB8: 4 | BH8: 5 | BN8: 6
A9: # | B9: REDROCK ITEM CODE <Input "NEW" for New Items> | C9: ITEM NAME AND DESCRIPTION | D9: ESTIMATED QTY | E9: UOM | F9: BASELINE- CURRENT | J9: MARKET PRICING | M9: RECOMMENDED AWARD | P9: BID ANALYSIS | AB9: PROCUREMENT SAVINGS | AG9: PRICE DIFF VS CURRENT SPEND | AJ9: VENDOR 1 | AP9: VENDOR 2 | AV9: VENDOR 3 | BB9: VENDOR 4 | BH9: VENDOR 5 | BN9: VENDOR 6 | BT9: VENDOR 7 | BZ9: VENDOR 8 | CF9: VENDOR 9 | CL9: VENDOR 10
D10: +/- 10-15% Variance | F10: SUPPLIER | G10: LAST SYSTEM PRICE | H10: LAST SYSTEM UPLOAD DATE | I10: EXTENDED COST | J10: SRP | K10: REFERENCE | L10: DIFF % SRP | M10: SUPPLIER | N10: UNIT COST | O10: EXTENDED COST | P10: INITIAL LOWEST COMPLIANT BID | Q10: VENDOR CHECK - CURRENT | R10: # OF BIDDERS | S10: AWARDED TO LOWEST | T10: AVE. BID | U10: AVE. BID % VS SYSTEM PRICE | V10: AWARDED TO LOWEST COMPLIANT | W10: LOWEST COMPLIANT VENDOR | X10: RECOMMENDED AMOUNT | Y10: AWARDED TO RECOMMENDED | Z10: LOWEST COMPLIANT BID | AA10: TOTAL LOWEST COMPLIANT / RECOMMENDED BID | AB10: UNIT COST SAVINGS REFERENCE | AC10: GROSS AMOUNT | AD10: UNIT SAVINGS | AE10: TOTAL SAVINGS | AF10: PRICE BENCHMARK | AG10: UNIT PRICE DIFF CURRENT | AH10: EXTENDED PRICE DIFF CURRENT | AI10: PRICE DIFF % CURRENT | AJ10: Initial Bid | AK10: Negotiated Bid | AL10: Extended Cost | AM10: % Variance from System Price | AN10: Remarks | AO10: Compliant | AP10: Initial Bid | AQ10: Negotiated Bid | AR10: Extended Cost | AS10: % Variance from System Price | AT10: Remarks | AU10: Compliant | AV10: Initial Bid | AW10: Negotiated Bid | AX10: Extended Cost | AY10: % Variance from System Price | AZ10: Remarks | BA10: Compliant | BB10: Initial Bid | BC10: Negotiated Bid | BD10: Extended Cost | BE10: % Variance from System Price | BF10: Remarks | BG10: Compliant | BH10: Initial Bid | BI10: Negotiated Bid | BJ10: Extended Cost | BK10: % Variance from System Price | BL10: Remarks | BM10: Compliant | BN10: Initial Bid | BO10: Negotiated Bid | BP10: Extended Cost | BQ10: % Variance from System Price | BR10: Remarks | BS10: Compliant | BT10: Initial Bid | BU10: Negotiated Bid | BV10: Extended Cost | BW10: % Variance from System Price | BX10: Remarks | BY10: Compliant | BZ10: Initial Bid | CA10: Negotiated Bid | CB10: Extended Cost | CC10: % Variance from System Price | CD10: Remarks | CE10: Compliant | CF10: Initial Bid | CG10: Negotiated Bid | CH10: Extended Cost | CI10: % Variance from System Price | CJ10: Remarks | CK10: Compliant | CL10: Initial Bid | CM10: Negotiated Bid | CN10: Extended Cost | CO10: % Variance from System Price | CP10: Remarks | CQ10: Compliant
A11: 1 | I11: =G11*D11 -> 0 | L11: =IFERROR((J11-N11)/J11,0) -> 0 | M11: =IF(N11>0,IF(N11=AK11,$AJ$9,IF(N11=AQ11,$AP$9,IF(N11=AW11,$AV$9,IF(N11=BC11,$BB$9,IF(N11=BI11,$BH$9,IF(N11=BO11,$BN$9,IF(N11=BU11,$BT$9,IF(N11=CA11,$BZ$9,IF(N11=CG11,$CF$9,IF(N11=CM11,$CL$9,"")))))))))),"") | N11: =IF(X11>0,X11,Z11) -> 0 | O11: =IFERROR(N11*D11,"") -> 0 | P11: =MIN(IF($AO11=Reference!$A$10,100000000,AJ11),IF($AU11=Reference!$A$10,100000000,AP11),IF($BA11=Reference!$A$10,100000000,AV11),IF($BG11=Reference!$A$10,100000000,BB11),IF($BM11=Reference!$A$10,100000000,BH11),IF($BS11=Reference!$A$10,100000000,BN11),IF($BY11=Reference!$A$10,100000000,BT11),IF($CE11=Reference!$A$10,100000000,BZ11),IF($CK11=Reference!$A$10,100000000,CF11),IF($CQ11=Reference!$A$10,100000000,CL11)) -> 0 | Q11: =W11=F11 -> FALSE | R11: =COUNT(BC11,AK11,AQ11,AW11,BI11,BO11,BU11,CA11,CG11,CM11) -> 0 | S11: =MIN(AK11,AQ11,AW11,BC11,BI11,BO11,BU11,CA11,CG11,CM11)=N11 -> TRUE | T11: =IFERROR(AVERAGE(AK11,AQ11,AW11,BC11,BI11,BO11,BU11,CA11,CG11,CM11),"") | U11: =IFERROR(((G11-T11)/G11),"") | V11: =$Z11=$N11 -> TRUE | W11: =IF(Z11=AK11,$AJ$9,IF(Z11=AQ11,$AP$9,IF(Z11=AW11,$AV$9,IF(Z11=BC11,$BB$9,IF(Z11=BI11,$BH$9,IF(Z11=BO11,$BN$9,IF(Z11=BU11,$BT$9,IF(Z11=CA11,$BZ$9,IF(Z11=CG11,$CF$9,IF(Z11=CM11,$CL$9)))))))))) -> VENDOR 1 | X11: =IF(AO11=Reference!$A$8,'Bid Tab (F&B Ops and CatMan) 10'!AK11,IF('Bid Tab (F&B Ops and CatMan) 10'!AU11=Reference!$A$8,'Bid Tab (F&B Ops and CatMan) 10'!AQ11,IF('Bid Tab (F&B Ops and CatMan) 10'!BA11=Reference!$A$8,'Bid Tab (F&B Ops and CatMan) 10'!AW11,IF('Bid Tab (F&B Ops and CatMan) 10'!BG11=Reference!$A$8,'Bid Tab (F&B Ops and CatMan) 10'!BC11,IF('Bid Tab (F&B Ops and CatMan) 10'!BM11=Reference!$A$8,'Bid Tab (F&B Ops and CatMan) 10'!BI11,IF('Bid Tab (F&B Ops and CatMan) 10'!BS11=Reference!$A$8,'Bid Tab (F&B Ops and CatMan) 10'!BO11,IF('Bid Tab (F&B Ops and CatMan) 10'!BY11=Reference!$A$8,'Bid Tab (F&B Ops and CatMan) 10'!BU11,IF('Bid Tab (F&B Ops and CatMan) 10'!CE11=Reference!$A$8,'Bid Tab (F&B Ops and CatMan) 10'!CA11,IF('Bid Tab (F&B Ops and CatMan) 10'!CK11=Reference!$A$8,'Bid Tab (F&B Ops and CatMan) 10'!CG11,IF('Bid Tab (F&B Ops and CatMan) 10'!CQ11=Reference!$A$8,'Bid Tab (F&B Ops and CatMan) 10'!CM11,0)))))))))) -> 0 | Y11: =IFERROR(IF(Reference!$A$8=HLOOKUP(Reference!$A$8,'Bid Tab (F&B Ops and CatMan) 10'!AJ11:CQ11,1,0),TRUE,FALSE),FALSE) -> FALSE | Z11: =MIN(IF(AO11=Reference!$A$10,100000000,AK11),IF(AU11=Reference!$A$10,100000000,AQ11),IF(BA11=Reference!$A$10,100000000,AW11),IF(BG11=Reference!$A$10,100000000,BC11),IF(BM11=Reference!$A$10,100000000,BI11),IF(BS11=Reference!$A$10,100000000,BO11),IF(BY11=Reference!$A$10,100000000,BU11),IF(CE11=Reference!$A$10,100000000,CA11),IF(CK11=Reference!$A$10,100000000,CG11),IF(CQ11=Reference!$A$10,100000000,CM11)) -> 0 | AA11: =IF(X11>0,X11*D11,Z11*D11) -> 0 | AB11: =IF(Reference!A18>0,Reference!A18,MAX(IF(TODAY()-H11<365,IF(G11>=N11,G11,P11),P11),G11)) -> 0 | AC11: =IF(AE11>0,AB11*$D11,O11) -> 0 | AD11: =IF(N11>$AB11,0,(($AB11-N11))) -> 0 | AE11: =IF(N11>$AB11,0,(($AB11-N11)*$D11)) -> 0 | AF11: =IF(AND((AD11=0),(F11=M11),(G11=N11),(TODAY()-H11<365)),"PRICE EXTENSION",IF(AND(G11=AB11,G11>0),"LAST SYSTEM PRICE",IF(AB11>0,"INITIAL LOWEST BID"," "))) | AG11: =IF(G11>0,G11-Z11,0) -> 0 | AH11: =AG11*D11 -> 0 | AI11: =IFERROR((G11-Z11)/G11,0) -> 0 | AL11: =IFERROR(AK11*$D11,0) -> 0 | AM11: =IFERROR(($G11-AK11)/$G11,0) -> 0 | AR11: =IFERROR(AQ11*$D11,0) -> 0 | AS11: =IFERROR(($G11-AQ11)/$G11,0) -> 0 | AX11: =IFERROR(AW11*$D11,0) -> 0 | AY11: =IFERROR(($G11-AW11)/$G11,0) -> 0 | BD11: N | BE11: =IFERROR(($G11-BC11)/$G11,0) -> 0 | BJ11: =IFERROR(BI11*$D11,0) -> 0 | BK11: =IFERROR(($G11-BI11)/$G11,0) -> 0 | BP11: =IFERROR(BO11*$D11,0) -> 0 | BQ11: =IFERROR(($G11-BO11)/$G11,0) -> 0 | BV11: =IFERROR(BU11*$D11,0) -> 0 | BW11: =IFERROR(($G11-BU11)/$G11,0) -> 0 | CB11: =IFERROR(CA11*$D11,0) -> 0 | CC11: =IFERROR(($G11-CA11)/$G11,0) -> 0 | CH11: =IFERROR(CG11*$D11,0) -> 0 | CI11: =IFERROR(($G11-CG11)/$G11,0) -> 0 | CN11: =IFERROR(CM11*$D11,0) -> 0 | CO11: =IFERROR(($G11-CM11)/$G11,0) -> 0
A12: 2 | I12: =G12*D12 -> 0 | L12: =IFERROR((J12-N12)/J12,0) -> 0 | M12: =IF(N12>0,IF(N12=AK12,$AJ$9,IF(N12=AQ12,$AP$9,IF(N12=AW12,$AV$9,IF(N12=BC12,$BB$9,IF(N12=BI12,$BH$9,IF(N12=BO12,$BN$9,IF(N12=BU12,$BT$9,IF(N12=CA12,$BZ$9,IF(N12=CG12,$CF$9,IF(N12=CM12,$CL$9,"")))))))))),"") | N12: =IF(X12>0,X12,Z12) -> 0 | O12: =IFERROR(N12*D12,"") -> 0 | P12: =MIN(IF($AO12=Reference!$A$10,100000000,AJ12),IF($AU12=Reference!$A$10,100000000,AP12),IF($BA12=Reference!$A$10,100000000,AV12),IF($BG12=Reference!$A$10,100000000,BB12),IF($BM12=Reference!$A$10,100000000,BH12),IF($BS12=Reference!$A$10,100000000,BN12),IF($BY12=Reference!$A$10,100000000,BT12),IF($CE12=Reference!$A$10,100000000,BZ12),IF($CK12=Reference!$A$10,100000000,CF12),IF($CQ12=Reference!$A$10,100000000,CL12)) -> 0 | Q12: =W12=F12 -> FALSE | R12: =COUNT(BC12,AK12,AQ12,AW12,BI12,BO12,BU12,CA12,CG12,CM12) -> 0 | S12: =MIN(AK12,AQ12,AW12,BC12,BI12,BO12,BU12,CA12,CG12,CM12)=N12 -> TRUE | T12: =IFERROR(AVERAGE(AK12,AQ12,AW12,BC12,BI12,BO12,BU12,CA12,CG12,CM12),"") | U12: =IFERROR(((G12-T12)/G12),"") | V12: =$Z12=$N12 -> TRUE | W12: =IF(Z12=AK12,$AJ$9,IF(Z12=AQ12,$AP$9,IF(Z12=AW12,$AV$9,IF(Z12=BC12,$BB$9,IF(Z12=BI12,$BH$9,IF(Z12=BO12,$BN$9,IF(Z12=BU12,$BT$9,IF(Z12=CA12,$BZ$9,IF(Z12=CG12,$CF$9,IF(Z12=CM12,$CL$9,"")))))))))) -> VENDOR 1 | X12: =IF(AO12=Reference!$A$8,'Bid Tab (F&B Ops and CatMan) 10'!AK12,IF('Bid Tab (F&B Ops and CatMan) 10'!AU12=Reference!$A$8,'Bid Tab (F&B Ops and CatMan) 10'!AQ12,IF('Bid Tab (F&B Ops and CatMan) 10'!BA12=Reference!$A$8,'Bid Tab (F&B Ops and CatMan) 10'!AW12,IF('Bid Tab (F&B Ops and CatMan) 10'!BG12=Reference!$A$8,'Bid Tab (F&B Ops and CatMan) 10'!BC12,IF('Bid Tab (F&B Ops and CatMan) 10'!BM12=Reference!$A$8,'Bid Tab (F&B Ops and CatMan) 10'!BI12,IF('Bid Tab (F&B Ops and CatMan) 10'!BS12=Reference!$A$8,'Bid Tab (F&B Ops and CatMan) 10'!BO12,IF('Bid Tab (F&B Ops and CatMan) 10'!BY12=Reference!$A$8,'Bid Tab (F&B Ops and CatMan) 10'!BU12,IF('Bid Tab (F&B Ops and CatMan) 10'!CE12=Reference!$A$8,'Bid Tab (F&B Ops and CatMan) 10'!CA12,IF('Bid Tab (F&B Ops and CatMan) 10'!CK12=Reference!$A$8,'Bid Tab (F&B Ops and CatMan) 10'!CG12,IF('Bid Tab (F&B Ops and CatMan) 10'!CQ12=Reference!$A$8,'Bid Tab (F&B Ops and CatMan) 10'!CM12,0)))))))))) -> 0 | Y12: =IFERROR(IF(Reference!$A$8=HLOOKUP(Reference!$A$8,'Bid Tab (F&B Ops and CatMan) 10'!AJ12:CQ12,1,0),TRUE,FALSE),FALSE) -> FALSE | Z12: =MIN(IF(AO12=Reference!$A$10,100000000,AK12),IF(AU12=Reference!$A$10,100000000,AQ12),IF(BA12=Reference!$A$10,100000000,AW12),IF(BG12=Reference!$A$10,100000000,BC12),IF(BM12=Reference!$A$10,100000000,BI12),IF(BS12=Reference!$A$10,100000000,BO12),IF(BY12=Reference!$A$10,100000000,BU12),IF(CE12=Reference!$A$10,100000000,CA12),IF(CK12=Reference!$A$10,100000000,CG12),IF(CQ12=Reference!$A$10,100000000,CM12)) -> 0 | AA12: =IF(X12>0,X12*D12,Z12*D12) -> 0 | AB12: =IF(Reference!A19>0,Reference!A19,MAX(IF(TODAY()-H12<365,IF(G12>=N12,G12,P12),P12),G12)) -> 0 | AC12: =IF(AE12>0,AB12*$D12,O12) -> 0 | AD12: =IF(N12>$AB12,0,(($AB12-N12))) -> 0 | AE12: =IF(N12>$AB12,0,(($AB12-N12)*$D12)) -> 0 | AF12: =IF(AND((AD12=0),(F12=M12),(G12=N12),(TODAY()-H12<365)),"PRICE EXTENSION",IF(AND(G12=AB12,G12>0),"LAST SYSTEM PRICE",IF(AB12>0,"INITIAL LOWEST BID"," "))) | AG12: =IF(G12>0,G12-Z12,0) -> 0 | AH12: =AG12*D12 -> 0 | AI12: =IFERROR((G12-Z12)/G12,0) -> 0 | AL12: =IFERROR(AK12*$D12,0) -> 0 | AM12: =IFERROR(($G12-AK12)/$G12,0) -> 0 | AR12: =IFERROR(AQ12*$D12,0) -> 0 | AS12: =IFERROR(($G12-AQ12)/$G12,0) -> 0 | AX12: =IFERROR(AW12*$D12,0) -> 0 | AY12: =IFERROR(($G12-AW12)/$G12,0) -> 0 | BD12: =IFERROR(BC12*$D12,0) -> 0 | BE12: =IFERROR(($G12-BC12)/$G12,0) -> 0 | BJ12: =IFERROR(BI12*$D12,0) -> 0 | BK12: =IFERROR(($G12-BI12)/$G12,0) -> 0 | BP12: =IFERROR(BO12*$D12,0) -> 0 | BQ12: =IFERROR(($G12-BO12)/$G12,0) -> 0 | BV12: =IFERROR(BU12*$D12,0) -> 0 | BW12: =IFERROR(($G12-BU12)/$G12,0) -> 0 | CB12: =IFERROR(CA12*$D12,0) -> 0 | CC12: =IFERROR(($G12-CA12)/$G12,0) -> 0 | CH12: =IFERROR(CG12*$D12,0) -> 0 | CI12: =IFERROR(($G12-CG12)/$G12,0) -> 0 | CN12: =IFERROR(CM12*$D12,0) -> 0 | CO12: =IFERROR(($G12-CM12)/$G12,0) -> 0
A13: 3 | I13: =G13*D13 -> 0 | L13: =IFERROR((J13-N13)/J13,0) -> 0 | M13: =IF(N13>0,IF(N13=AK13,$AJ$9,IF(N13=AQ13,$AP$9,IF(N13=AW13,$AV$9,IF(N13=BC13,$BB$9,IF(N13=BI13,$BH$9,IF(N13=BO13,$BN$9,IF(N13=BU13,$BT$9,IF(N13=CA13,$BZ$9,IF(N13=CG13,$CF$9,IF(N13=CM13,$CL$9,"")))))))))),"") | N13: =IF(X13>0,X13,Z13) -> 0 | O13: =IFERROR(N13*D13,"") -> 0 | P13: =MIN(IF($AO13=Reference!$A$10,100000000,AJ13),IF($AU13=Reference!$A$10,100000000,AP13),IF($BA13=Reference!$A$10,100000000,AV13),IF($BG13=Reference!$A$10,100000000,BB13),IF($BM13=Reference!$A$10,100000000,BH13),IF($BS13=Reference!$A$10,100000000,BN13),IF($BY13=Reference!$A$10,100000000,BT13),IF($CE13=Reference!$A$10,100000000,BZ13),IF($CK13=Reference!$A$10,100000000,CF13),IF($CQ13=Reference!$A$10,100000000,CL13)) -> 0 | Q13: =W13=F13 -> FALSE | R13: =COUNT(BC13,AK13,AQ13,AW13,BI13,BO13,BU13,CA13,CG13,CM13) -> 0 | S13: =MIN(AK13,AQ13,AW13,BC13,BI13,BO13,BU13,CA13,CG13,CM13)=N13 -> TRUE | T13: =IFERROR(AVERAGE(AK13,AQ13,AW13,BC13,BI13,BO13,BU13,CA13,CG13,CM13),"") | U13: =IFERROR(((G13-T13)/G13),"") | V13: =$Z13=$N13 -> TRUE | W13: =IF(Z13=AK13,$AJ$9,IF(Z13=AQ13,$AP$9,IF(Z13=AW13,$AV$9,IF(Z13=BC13,$BB$9,IF(Z13=BI13,$BH$9,IF(Z13=BO13,$BN$9,IF(Z13=BU13,$BT$9,IF(Z13=CA13,$BZ$9,IF(Z13=CG13,$CF$9,IF(Z13=CM13,$CL$9,"")))))))))) -> VENDOR 1 | X13: =IF(AO13=Reference!$A$8,'Bid Tab (F&B Ops and CatMan) 10'!AK13,IF('Bid Tab (F&B Ops and CatMan) 10'!AU13=Reference!$A$8,'Bid Tab (F&B Ops and CatMan) 10'!AQ13,IF('Bid Tab (F&B Ops and CatMan) 10'!BA13=Reference!$A$8,'Bid Tab (F&B Ops and CatMan) 10'!AW13,IF('Bid Tab (F&B Ops and CatMan) 10'!BG13=Reference!$A$8,'Bid Tab (F&B Ops and CatMan) 10'!BC13,IF('Bid Tab (F&B Ops and CatMan) 10'!BM13=Reference!$A$8,'Bid Tab (F&B Ops and CatMan) 10'!BI13,IF('Bid Tab (F&B Ops and CatMan) 10'!BS13=Reference!$A$8,'Bid Tab (F&B Ops and CatMan) 10'!BO13,IF('Bid Tab (F&B Ops and CatMan) 10'!BY13=Reference!$A$8,'Bid Tab (F&B Ops and CatMan) 10'!BU13,IF('Bid Tab (F&B Ops and CatMan) 10'!CE13=Reference!$A$8,'Bid Tab (F&B Ops and CatMan) 10'!CA13,IF('Bid Tab (F&B Ops and CatMan) 10'!CK13=Reference!$A$8,'Bid Tab (F&B Ops and CatMan) 10'!CG13,IF('Bid Tab (F&B Ops and CatMan) 10'!CQ13=Reference!$A$8,'Bid Tab (F&B Ops and CatMan) 10'!CM13,0)))))))))) -> 0 | Y13: =IFERROR(IF(Reference!$A$8=HLOOKUP(Reference!$A$8,'Bid Tab (F&B Ops and CatMan) 10'!AJ13:CQ13,1,0),TRUE,FALSE),FALSE) -> FALSE | Z13: =MIN(IF(AO13=Reference!$A$10,100000000,AK13),IF(AU13=Reference!$A$10,100000000,AQ13),IF(BA13=Reference!$A$10,100000000,AW13),IF(BG13=Reference!$A$10,100000000,BC13),IF(BM13=Reference!$A$10,100000000,BI13),IF(BS13=Reference!$A$10,100000000,BO13),IF(BY13=Reference!$A$10,100000000,BU13),IF(CE13=Reference!$A$10,100000000,CA13),IF(CK13=Reference!$A$10,100000000,CG13),IF(CQ13=Reference!$A$10,100000000,CM13)) -> 0 | AA13: =IF(X13>0,X13*D13,Z13*D13) -> 0 | AB13: =IF(Reference!A20>0,Reference!A20,MAX(IF(TODAY()-H13<365,IF(G13>=N13,G13,P13),P13),G13)) -> 0 | AC13: =IF(AE13>0,AB13*$D13,O13) -> 0 | AD13: =IF(N13>$AB13,0,(($AB13-N13))) -> 0 | AE13: =IF(N13>$AB13,0,(($AB13-N13)*$D13)) -> 0 | AF13: =IF(AND((AD13=0),(F13=M13),(G13=N13),(TODAY()-H13<365)),"PRICE EXTENSION",IF(AND(G13=AB13,G13>0),"LAST SYSTEM PRICE",IF(AB13>0,"INITIAL LOWEST BID"," "))) | AG13: =IF(G13>0,G13-Z13,0) -> 0 | AH13: =AG13*D13 -> 0 | AI13: =IFERROR((G13-Z13)/G13,0) -> 0 | AL13: =IFERROR(AK13*$D13,0) -> 0 | AM13: =IFERROR(($G13-AK13)/$G13,0) -> 0 | AR13: =IFERROR(AQ13*$D13,0) -> 0 | AS13: =IFERROR(($G13-AQ13)/$G13,0) -> 0 | AX13: =IFERROR(AW13*$D13,0) -> 0 | AY13: =IFERROR(($G13-AW13)/$G13,0) -> 0 | BD13: =IFERROR(BC13*$D13,0) -> 0 | BE13: =IFERROR(($G13-BC13)/$G13,0) -> 0 | BJ13: =IFERROR(BI13*$D13,0) -> 0 | BK13: =IFERROR(($G13-BI13)/$G13,0) -> 0 | BP13: =IFERROR(BO13*$D13,0) -> 0 | BQ13: =IFERROR(($G13-BO13)/$G13,0) -> 0 | BV13: =IFERROR(BU13*$D13,0) -> 0 | BW13: =IFERROR(($G13-BU13)/$G13,0) -> 0 | CB13: =IFERROR(CA13*$D13,0) -> 0 | CC13: =IFERROR(($G13-CA13)/$G13,0) -> 0 | CH13: =IFERROR(CG13*$D13,0) -> 0 | CI13: =IFERROR(($G13-CG13)/$G13,0) -> 0 | CN13: =IFERROR(CM13*$D13,0) -> 0 | CO13: =IFERROR(($G13-CM13)/$G13,0) -> 0
A14: 4 | I14: =G14*D14 -> 0 | L14: =IFERROR((J14-N14)/J14,0) -> 0 | M14: =IF(N14>0,IF(N14=AK14,$AJ$9,IF(N14=AQ14,$AP$9,IF(N14=AW14,$AV$9,IF(N14=BC14,$BB$9,IF(N14=BI14,$BH$9,IF(N14=BO14,$BN$9,IF(N14=BU14,$BT$9,IF(N14=CA14,$BZ$9,IF(N14=CG14,$CF$9,IF(N14=CM14,$CL$9,"")))))))))),"") | N14: =IF(X14>0,X14,Z14) -> 0 | O14: =IFERROR(N14*D14,"") -> 0 | P14: =MIN(IF($AO14=Reference!$A$10,100000000,AJ14),IF($AU14=Reference!$A$10,100000000,AP14),IF($BA14=Reference!$A$10,100000000,AV14),IF($BG14=Reference!$A$10,100000000,BB14),IF($BM14=Reference!$A$10,100000000,BH14),IF($BS14=Reference!$A$10,100000000,BN14),IF($BY14=Reference!$A$10,100000000,BT14),IF($CE14=Reference!$A$10,100000000,BZ14),IF($CK14=Reference!$A$10,100000000,CF14),IF($CQ14=Reference!$A$10,100000000,CL14)) -> 0 | Q14: =W14=F14 -> FALSE | R14: =COUNT(BC14,AK14,AQ14,AW14,BI14,BO14,BU14,CA14,CG14,CM14) -> 0 | S14: =MIN(AK14,AQ14,AW14,BC14,BI14,BO14,BU14,CA14,CG14,CM14)=N14 -> TRUE | T14: =IFERROR(AVERAGE(AK14,AQ14,AW14,BC14,BI14,BO14,BU14,CA14,CG14,CM14),"") | U14: =IFERROR(((G14-T14)/G14),"") | V14: =$Z14=$N14 -> TRUE | W14: =IF(Z14=AK14,$AJ$9,IF(Z14=AQ14,$AP$9,IF(Z14=AW14,$AV$9,IF(Z14=BC14,$BB$9,IF(Z14=BI14,$BH$9,IF(Z14=BO14,$BN$9,IF(Z14=BU14,$BT$9,IF(Z14=CA14,$BZ$9,IF(Z14=CG14,$CF$9,IF(Z14=CM14,$CL$9,"")))))))))) -> VENDOR 1 | X14: =IF(AO14=Reference!$A$8,'Bid Tab (F&B Ops and CatMan) 10'!AK14,IF('Bid Tab (F&B Ops and CatMan) 10'!AU14=Reference!$A$8,'Bid Tab (F&B Ops and CatMan) 10'!AQ14,IF('Bid Tab (F&B Ops and CatMan) 10'!BA14=Reference!$A$8,'Bid Tab (F&B Ops and CatMan) 10'!AW14,IF('Bid Tab (F&B Ops and CatMan) 10'!BG14=Reference!$A$8,'Bid Tab (F&B Ops and CatMan) 10'!BC14,IF('Bid Tab (F&B Ops and CatMan) 10'!BM14=Reference!$A$8,'Bid Tab (F&B Ops and CatMan) 10'!BI14,IF('Bid Tab (F&B Ops and CatMan) 10'!BS14=Reference!$A$8,'Bid Tab (F&B Ops and CatMan) 10'!BO14,IF('Bid Tab (F&B Ops and CatMan) 10'!BY14=Reference!$A$8,'Bid Tab (F&B Ops and CatMan) 10'!BU14,IF('Bid Tab (F&B Ops and CatMan) 10'!CE14=Reference!$A$8,'Bid Tab (F&B Ops and CatMan) 10'!CA14,IF('Bid Tab (F&B Ops and CatMan) 10'!CK14=Reference!$A$8,'Bid Tab (F&B Ops and CatMan) 10'!CG14,IF('Bid Tab (F&B Ops and CatMan) 10'!CQ14=Reference!$A$8,'Bid Tab (F&B Ops and CatMan) 10'!CM14,0)))))))))) -> 0 | Y14: =IFERROR(IF(Reference!$A$8=HLOOKUP(Reference!$A$8,'Bid Tab (F&B Ops and CatMan) 10'!AJ14:CQ14,1,0),TRUE,FALSE),FALSE) -> FALSE | Z14: =MIN(IF(AO14=Reference!$A$10,100000000,AK14),IF(AU14=Reference!$A$10,100000000,AQ14),IF(BA14=Reference!$A$10,100000000,AW14),IF(BG14=Reference!$A$10,100000000,BC14),IF(BM14=Reference!$A$10,100000000,BI14),IF(BS14=Reference!$A$10,100000000,BO14),IF(BY14=Reference!$A$10,100000000,BU14),IF(CE14=Reference!$A$10,100000000,CA14),IF(CK14=Reference!$A$10,100000000,CG14),IF(CQ14=Reference!$A$10,100000000,CM14)) -> 0 | AA14: =IF(X14>0,X14*D14,Z14*D14) -> 0 | AB14: =IF(Reference!A21>0,Reference!A21,MAX(IF(TODAY()-H14<365,IF(G14>=N14,G14,P14),P14),G14)) -> 0 | AC14: =IF(AE14>0,AB14*$D14,O14) -> 0 | AD14: =IF(N14>$AB14,0,(($AB14-N14))) -> 0 | AE14: =IF(N14>$AB14,0,(($AB14-N14)*$D14)) -> 0 | AF14: =IF(AND((AD14=0),(F14=M14),(G14=N14),(TODAY()-H14<365)),"PRICE EXTENSION",IF(AND(G14=AB14,G14>0),"LAST SYSTEM PRICE",IF(AB14>0,"INITIAL LOWEST BID"," "))) | AG14: =IF(G14>0,G14-Z14,0) -> 0 | AH14: =AG14*D14 -> 0 | AI14: =IFERROR((G14-Z14)/G14,0) -> 0 | AL14: =IFERROR(AK14*$D14,0) -> 0 | AM14: =IFERROR(($G14-AK14)/$G14,0) -> 0 | AR14: =IFERROR(AQ14*$D14,0) -> 0 | AS14: =IFERROR(($G14-AQ14)/$G14,0) -> 0 | AX14: =IFERROR(AW14*$D14,0) -> 0 | AY14: =IFERROR(($G14-AW14)/$G14,0) -> 0 | BD14: =IFERROR(BC14*$D14,0) -> 0 | BE14: =IFERROR(($G14-BC14)/$G14,0) -> 0 | BJ14: =IFERROR(BI14*$D14,0) -> 0 | BK14: =IFERROR(($G14-BI14)/$G14,0) -> 0 | BP14: =IFERROR(BO14*$D14,0) -> 0 | BQ14: =IFERROR(($G14-BO14)/$G14,0) -> 0 | BV14: =IFERROR(BU14*$D14,0) -> 0 | BW14: =IFERROR(($G14-BU14)/$G14,0) -> 0 | CB14: =IFERROR(CA14*$D14,0) -> 0 | CC14: =IFERROR(($G14-CA14)/$G14,0) -> 0 | CH14: =IFERROR(CG14*$D14,0) -> 0 | CI14: =IFERROR(($G14-CG14)/$G14,0) -> 0 | CN14: =IFERROR(CM14*$D14,0) -> 0 | CO14: =IFERROR(($G14-CM14)/$G14,0) -> 0
A15: 5 | I15: =G15*D15 -> 0 | L15: =IFERROR((J15-N15)/J15,0) -> 0 | M15: =IF(N15>0,IF(N15=AK15,$AJ$9,IF(N15=AQ15,$AP$9,IF(N15=AW15,$AV$9,IF(N15=BC15,$BB$9,IF(N15=BI15,$BH$9,IF(N15=BO15,$BN$9,IF(N15=BU15,$BT$9,IF(N15=CA15,$BZ$9,IF(N15=CG15,$CF$9,IF(N15=CM15,$CL$9,"")))))))))),"") | N15: =IF(X15>0,X15,Z15) -> 0 | O15: =IFERROR(N15*D15,"") -> 0 | P15: =MIN(IF($AO15=Reference!$A$10,100000000,AJ15),IF($AU15=Reference!$A$10,100000000,AP15),IF($BA15=Reference!$A$10,100000000,AV15),IF($BG15=Reference!$A$10,100000000,BB15),IF($BM15=Reference!$A$10,100000000,BH15),IF($BS15=Reference!$A$10,100000000,BN15),IF($BY15=Reference!$A$10,100000000,BT15),IF($CE15=Reference!$A$10,100000000,BZ15),IF($CK15=Reference!$A$10,100000000,CF15),IF($CQ15=Reference!$A$10,100000000,CL15)) -> 0 | Q15: =W15=F15 -> FALSE | R15: =COUNT(BC15,AK15,AQ15,AW15,BI15,BO15,BU15,CA15,CG15,CM15) -> 0 | S15: =MIN(AK15,AQ15,AW15,BC15,BI15,BO15,BU15,CA15,CG15,CM15)=N15 -> TRUE | T15: =IFERROR(AVERAGE(AK15,AQ15,AW15,BC15,BI15,BO15,BU15,CA15,CG15,CM15),"") | U15: =IFERROR(((G15-T15)/G15),"") | V15: =$Z15=$N15 -> TRUE | W15: =IF(Z15=AK15,$AJ$9,IF(Z15=AQ15,$AP$9,IF(Z15=AW15,$AV$9,IF(Z15=BC15,$BB$9,IF(Z15=BI15,$BH$9,IF(Z15=BO15,$BN$9,IF(Z15=BU15,$BT$9,IF(Z15=CA15,$BZ$9,IF(Z15=CG15,$CF$9,IF(Z15=CM15,$CL$9,"")))))))))) -> VENDOR 1 | X15: =IF(AO15=Reference!$A$8,'Bid Tab (F&B Ops and CatMan) 10'!AK15,IF('Bid Tab (F&B Ops and CatMan) 10'!AU15=Reference!$A$8,'Bid Tab (F&B Ops and CatMan) 10'!AQ15,IF('Bid Tab (F&B Ops and CatMan) 10'!BA15=Reference!$A$8,'Bid Tab (F&B Ops and CatMan) 10'!AW15,IF('Bid Tab (F&B Ops and CatMan) 10'!BG15=Reference!$A$8,'Bid Tab (F&B Ops and CatMan) 10'!BC15,IF('Bid Tab (F&B Ops and CatMan) 10'!BM15=Reference!$A$8,'Bid Tab (F&B Ops and CatMan) 10'!BI15,IF('Bid Tab (F&B Ops and CatMan) 10'!BS15=Reference!$A$8,'Bid Tab (F&B Ops and CatMan) 10'!BO15,IF('Bid Tab (F&B Ops and CatMan) 10'!BY15=Reference!$A$8,'Bid Tab (F&B Ops and CatMan) 10'!BU15,IF('Bid Tab (F&B Ops and CatMan) 10'!CE15=Reference!$A$8,'Bid Tab (F&B Ops and CatMan) 10'!CA15,IF('Bid Tab (F&B Ops and CatMan) 10'!CK15=Reference!$A$8,'Bid Tab (F&B Ops and CatMan) 10'!CG15,IF('Bid Tab (F&B Ops and CatMan) 10'!CQ15=Reference!$A$8,'Bid Tab (F&B Ops and CatMan) 10'!CM15,0)))))))))) -> 0 | Y15: =IFERROR(IF(Reference!$A$8=HLOOKUP(Reference!$A$8,'Bid Tab (F&B Ops and CatMan) 10'!AJ15:CQ15,1,0),TRUE,FALSE),FALSE) -> FALSE | Z15: =MIN(IF(AO15=Reference!$A$10,100000000,AK15),IF(AU15=Reference!$A$10,100000000,AQ15),IF(BA15=Reference!$A$10,100000000,AW15),IF(BG15=Reference!$A$10,100000000,BC15),IF(BM15=Reference!$A$10,100000000,BI15),IF(BS15=Reference!$A$10,100000000,BO15),IF(BY15=Reference!$A$10,100000000,BU15),IF(CE15=Reference!$A$10,100000000,CA15),IF(CK15=Reference!$A$10,100000000,CG15),IF(CQ15=Reference!$A$10,100000000,CM15)) -> 0 | AA15: =IF(X15>0,X15*D15,Z15*D15) -> 0 | AB15: =IF(Reference!A22>0,Reference!A22,MAX(IF(TODAY()-H15<365,IF(G15>=N15,G15,P15),P15),G15)) -> 0 | AC15: =IF(AE15>0,AB15*$D15,O15) -> 0 | AD15: =IF(N15>$AB15,0,(($AB15-N15))) -> 0 | AE15: =IF(N15>$AB15,0,(($AB15-N15)*$D15)) -> 0 | AF15: =IF(AND((AD15=0),(F15=M15),(G15=N15),(TODAY()-H15<365)),"PRICE EXTENSION",IF(AND(G15=AB15,G15>0),"LAST SYSTEM PRICE",IF(AB15>0,"INITIAL LOWEST BID"," "))) | AG15: =IF(G15>0,G15-Z15,0) -> 0 | AH15: =AG15*D15 -> 0 | AI15: =IFERROR((G15-Z15)/G15,0) -> 0 | AL15: =IFERROR(AK15*$D15,0) -> 0 | AM15: =IFERROR(($G15-AK15)/$G15,0) -> 0 | AR15: =IFERROR(AQ15*$D15,0) -> 0 | AS15: =IFERROR(($G15-AQ15)/$G15,0) -> 0 | AX15: =IFERROR(AW15*$D15,0) -> 0 | AY15: =IFERROR(($G15-AW15)/$G15,0) -> 0 | BD15: =IFERROR(BC15*$D15,0) -> 0 | BE15: =IFERROR(($G15-BC15)/$G15,0) -> 0 | BJ15: =IFERROR(BI15*$D15,0) -> 0 | BK15: =IFERROR(($G15-BI15)/$G15,0) -> 0 | BP15: =IFERROR(BO15*$D15,0) -> 0 | BQ15: =IFERROR(($G15-BO15)/$G15,0) -> 0 | BV15: =IFERROR(BU15*$D15,0) -> 0 | BW15: =IFERROR(($G15-BU15)/$G15,0) -> 0 | CB15: =IFERROR(CA15*$D15,0) -> 0 | CC15: =IFERROR(($G15-CA15)/$G15,0) -> 0 | CH15: =IFERROR(CG15*$D15,0) -> 0 | CI15: =IFERROR(($G15-CG15)/$G15,0) -> 0 | CN15: =IFERROR(CM15*$D15,0) -> 0 | CO15: =IFERROR(($G15-CM15)/$G15,0) -> 0
A16: 6 | I16: =G16*D16 -> 0 | L16: =IFERROR((J16-N16)/J16,0) -> 0 | M16: =IF(N16>0,IF(N16=AK16,$AJ$9,IF(N16=AQ16,$AP$9,IF(N16=AW16,$AV$9,IF(N16=BC16,$BB$9,IF(N16=BI16,$BH$9,IF(N16=BO16,$BN$9,IF(N16=BU16,$BT$9,IF(N16=CA16,$BZ$9,IF(N16=CG16,$CF$9,IF(N16=CM16,$CL$9,"")))))))))),"") | N16: =IF(X16>0,X16,Z16) -> 0 | O16: =IFERROR(N16*D16,"") -> 0 | P16: =MIN(IF($AO16=Reference!$A$10,100000000,AJ16),IF($AU16=Reference!$A$10,100000000,AP16),IF($BA16=Reference!$A$10,100000000,AV16),IF($BG16=Reference!$A$10,100000000,BB16),IF($BM16=Reference!$A$10,100000000,BH16),IF($BS16=Reference!$A$10,100000000,BN16),IF($BY16=Reference!$A$10,100000000,BT16),IF($CE16=Reference!$A$10,100000000,BZ16),IF($CK16=Reference!$A$10,100000000,CF16),IF($CQ16=Reference!$A$10,100000000,CL16)) -> 0 | Q16: =W16=F16 -> FALSE | R16: =COUNT(BC16,AK16,AQ16,AW16,BI16,BO16,BU16,CA16,CG16,CM16) -> 0 | S16: =MIN(AK16,AQ16,AW16,BC16,BI16,BO16,BU16,CA16,CG16,CM16)=N16 -> TRUE | T16: =IFERROR(AVERAGE(AK16,AQ16,AW16,BC16,BI16,BO16,BU16,CA16,CG16,CM16),"") | U16: =IFERROR(((G16-T16)/G16),"") | V16: =$Z16=$N16 -> TRUE | W16: =IF(Z16=AK16,$AJ$9,IF(Z16=AQ16,$AP$9,IF(Z16=AW16,$AV$9,IF(Z16=BC16,$BB$9,IF(Z16=BI16,$BH$9,IF(Z16=BO16,$BN$9,IF(Z16=BU16,$BT$9,IF(Z16=CA16,$BZ$9,IF(Z16=CG16,$CF$9,IF(Z16=CM16,$CL$9,"")))))))))) -> VENDOR 1 | X16: =IF(AO16=Reference!$A$8,'Bid Tab (F&B Ops and CatMan) 10'!AK16,IF('Bid Tab (F&B Ops and CatMan) 10'!AU16=Reference!$A$8,'Bid Tab (F&B Ops and CatMan) 10'!AQ16,IF('Bid Tab (F&B Ops and CatMan) 10'!BA16=Reference!$A$8,'Bid Tab (F&B Ops and CatMan) 10'!AW16,IF('Bid Tab (F&B Ops and CatMan) 10'!BG16=Reference!$A$8,'Bid Tab (F&B Ops and CatMan) 10'!BC16,IF('Bid Tab (F&B Ops and CatMan) 10'!BM16=Reference!$A$8,'Bid Tab (F&B Ops and CatMan) 10'!BI16,IF('Bid Tab (F&B Ops and CatMan) 10'!BS16=Reference!$A$8,'Bid Tab (F&B Ops and CatMan) 10'!BO16,IF('Bid Tab (F&B Ops and CatMan) 10'!BY16=Reference!$A$8,'Bid Tab (F&B Ops and CatMan) 10'!BU16,IF('Bid Tab (F&B Ops and CatMan) 10'!CE16=Reference!$A$8,'Bid Tab (F&B Ops and CatMan) 10'!CA16,IF('Bid Tab (F&B Ops and CatMan) 10'!CK16=Reference!$A$8,'Bid Tab (F&B Ops and CatMan) 10'!CG16,IF('Bid Tab (F&B Ops and CatMan) 10'!CQ16=Reference!$A$8,'Bid Tab (F&B Ops and CatMan) 10'!CM16,0)))))))))) -> 0 | Y16: =IFERROR(IF(Reference!$A$8=HLOOKUP(Reference!$A$8,'Bid Tab (F&B Ops and CatMan) 10'!AJ16:CQ16,1,0),TRUE,FALSE),FALSE) -> FALSE | Z16: =MIN(IF(AO16=Reference!$A$10,100000000,AK16),IF(AU16=Reference!$A$10,100000000,AQ16),IF(BA16=Reference!$A$10,100000000,AW16),IF(BG16=Reference!$A$10,100000000,BC16),IF(BM16=Reference!$A$10,100000000,BI16),IF(BS16=Reference!$A$10,100000000,BO16),IF(BY16=Reference!$A$10,100000000,BU16),IF(CE16=Reference!$A$10,100000000,CA16),IF(CK16=Reference!$A$10,100000000,CG16),IF(CQ16=Reference!$A$10,100000000,CM16)) -> 0 | AA16: =IF(X16>0,X16*D16,Z16*D16) -> 0 | AB16: =IF(Reference!A23>0,Reference!A23,MAX(IF(TODAY()-H16<365,IF(G16>=N16,G16,P16),P16),G16)) -> 0 | AC16: =IF(AE16>0,AB16*$D16,O16) -> 0 | AD16: =IF(N16>$AB16,0,(($AB16-N16))) -> 0 | AE16: =IF(N16>$AB16,0,(($AB16-N16)*$D16)) -> 0 | AF16: =IF(AND((AD16=0),(F16=M16),(G16=N16),(TODAY()-H16<365)),"PRICE EXTENSION",IF(AND(G16=AB16,G16>0),"LAST SYSTEM PRICE",IF(AB16>0,"INITIAL LOWEST BID"," "))) | AG16: =IF(G16>0,G16-Z16,0) -> 0 | AH16: =AG16*D16 -> 0 | AI16: =IFERROR((G16-Z16)/G16,0) -> 0 | AL16: =IFERROR(AK16*$D16,0) -> 0 | AM16: =IFERROR(($G16-AK16)/$G16,0) -> 0 | AR16: =IFERROR(AQ16*$D16,0) -> 0 | AS16: =IFERROR(($G16-AQ16)/$G16,0) -> 0 | AX16: =IFERROR(AW16*$D16,0) -> 0 | AY16: =IFERROR(($G16-AW16)/$G16,0) -> 0 | BD16: =IFERROR(BC16*$D16,0) -> 0 | BE16: =IFERROR(($G16-BC16)/$G16,0) -> 0 | BJ16: =IFERROR(BI16*$D16,0) -> 0 | BK16: =IFERROR(($G16-BI16)/$G16,0) -> 0 | BP16: =IFERROR(BO16*$D16,0) -> 0 | BQ16: =IFERROR(($G16-BO16)/$G16,0) -> 0 | BV16: =IFERROR(BU16*$D16,0) -> 0 | BW16: =IFERROR(($G16-BU16)/$G16,0) -> 0 | CB16: =IFERROR(CA16*$D16,0) -> 0 | CC16: =IFERROR(($G16-CA16)/$G16,0) -> 0 | CH16: =IFERROR(CG16*$D16,0) -> 0 | CI16: =IFERROR(($G16-CG16)/$G16,0) -> 0 | CN16: =IFERROR(CM16*$D16,0) -> 0 | CO16: =IFERROR(($G16-CM16)/$G16,0) -> 0
A17: 7 | I17: =G17*D17 -> 0 | L17: =IFERROR((J17-N17)/J17,0) -> 0 | M17: =IF(N17>0,IF(N17=AK17,$AJ$9,IF(N17=AQ17,$AP$9,IF(N17=AW17,$AV$9,IF(N17=BC17,$BB$9,IF(N17=BI17,$BH$9,IF(N17=BO17,$BN$9,IF(N17=BU17,$BT$9,IF(N17=CA17,$BZ$9,IF(N17=CG17,$CF$9,IF(N17=CM17,$CL$9,"")))))))))),"") | N17: =IF(X17>0,X17,Z17) -> 0 | O17: =IFERROR(N17*D17,"") -> 0 | P17: =MIN(IF($AO17=Reference!$A$10,100000000,AJ17),IF($AU17=Reference!$A$10,100000000,AP17),IF($BA17=Reference!$A$10,100000000,AV17),IF($BG17=Reference!$A$10,100000000,BB17),IF($BM17=Reference!$A$10,100000000,BH17),IF($BS17=Reference!$A$10,100000000,BN17),IF($BY17=Reference!$A$10,100000000,BT17),IF($CE17=Reference!$A$10,100000000,BZ17),IF($CK17=Reference!$A$10,100000000,CF17),IF($CQ17=Reference!$A$10,100000000,CL17)) -> 0 | Q17: =W17=F17 -> FALSE | R17: =COUNT(BC17,AK17,AQ17,AW17,BI17,BO17,BU17,CA17,CG17,CM17) -> 0 | S17: =MIN(AK17,AQ17,AW17,BC17,BI17,BO17,BU17,CA17,CG17,CM17)=N17 -> TRUE | T17: =IFERROR(AVERAGE(AK17,AQ17,AW17,BC17,BI17,BO17,BU17,CA17,CG17,CM17),"") | U17: =IFERROR(((G17-T17)/G17),"") | V17: =$Z17=$N17 -> TRUE | W17: =IF(Z17=AK17,$AJ$9,IF(Z17=AQ17,$AP$9,IF(Z17=AW17,$AV$9,IF(Z17=BC17,$BB$9,IF(Z17=BI17,$BH$9,IF(Z17=BO17,$BN$9,IF(Z17=BU17,$BT$9,IF(Z17=CA17,$BZ$9,IF(Z17=CG17,$CF$9,IF(Z17=CM17,$CL$9,"")))))))))) -> VENDOR 1 | X17: =IF(AO17=Reference!$A$8,'Bid Tab (F&B Ops and CatMan) 10'!AK17,IF('Bid Tab (F&B Ops and CatMan) 10'!AU17=Reference!$A$8,'Bid Tab (F&B Ops and CatMan) 10'!AQ17,IF('Bid Tab (F&B Ops and CatMan) 10'!BA17=Reference!$A$8,'Bid Tab (F&B Ops and CatMan) 10'!AW17,IF('Bid Tab (F&B Ops and CatMan) 10'!BG17=Reference!$A$8,'Bid Tab (F&B Ops and CatMan) 10'!BC17,IF('Bid Tab (F&B Ops and CatMan) 10'!BM17=Reference!$A$8,'Bid Tab (F&B Ops and CatMan) 10'!BI17,IF('Bid Tab (F&B Ops and CatMan) 10'!BS17=Reference!$A$8,'Bid Tab (F&B Ops and CatMan) 10'!BO17,IF('Bid Tab (F&B Ops and CatMan) 10'!BY17=Reference!$A$8,'Bid Tab (F&B Ops and CatMan) 10'!BU17,IF('Bid Tab (F&B Ops and CatMan) 10'!CE17=Reference!$A$8,'Bid Tab (F&B Ops and CatMan) 10'!CA17,IF('Bid Tab (F&B Ops and CatMan) 10'!CK17=Reference!$A$8,'Bid Tab (F&B Ops and CatMan) 10'!CG17,IF('Bid Tab (F&B Ops and CatMan) 10'!CQ17=Reference!$A$8,'Bid Tab (F&B Ops and CatMan) 10'!CM17,0)))))))))) -> 0 | Y17: =IFERROR(IF(Reference!$A$8=HLOOKUP(Reference!$A$8,'Bid Tab (F&B Ops and CatMan) 10'!AJ17:CQ17,1,0),TRUE,FALSE),FALSE) -> FALSE | Z17: =MIN(IF(AO17=Reference!$A$10,100000000,AK17),IF(AU17=Reference!$A$10,100000000,AQ17),IF(BA17=Reference!$A$10,100000000,AW17),IF(BG17=Reference!$A$10,100000000,BC17),IF(BM17=Reference!$A$10,100000000,BI17),IF(BS17=Reference!$A$10,100000000,BO17),IF(BY17=Reference!$A$10,100000000,BU17),IF(CE17=Reference!$A$10,100000000,CA17),IF(CK17=Reference!$A$10,100000000,CG17),IF(CQ17=Reference!$A$10,100000000,CM17)) -> 0 | AA17: =IF(X17>0,X17*D17,Z17*D17) -> 0 | AB17: =IF(Reference!A24>0,Reference!A24,MAX(IF(TODAY()-H17<365,IF(G17>=N17,G17,P17),P17),G17)) -> 0 | AC17: =IF(AE17>0,AB17*$D17,O17) -> 0 | AD17: =IF(N17>$AB17,0,(($AB17-N17))) -> 0 | AE17: =IF(N17>$AB17,0,(($AB17-N17)*$D17)) -> 0 | AF17: =IF(AND((AD17=0),(F17=M17),(G17=N17),(TODAY()-H17<365)),"PRICE EXTENSION",IF(AND(G17=AB17,G17>0),"LAST SYSTEM PRICE",IF(AB17>0,"INITIAL LOWEST BID"," "))) | AG17: =IF(G17>0,G17-Z17,0) -> 0 | AH17: =AG17*D17 -> 0 | AI17: =IFERROR((G17-Z17)/G17,0) -> 0 | AL17: =IFERROR(AK17*$D17,0) -> 0 | AM17: =IFERROR(($G17-AK17)/$G17,0) -> 0 | AR17: =IFERROR(AQ17*$D17,0) -> 0 | AS17: =IFERROR(($G17-AQ17)/$G17,0) -> 0 | AX17: =IFERROR(AW17*$D17,0) -> 0 | AY17: =IFERROR(($G17-AW17)/$G17,0) -> 0 | BD17: =IFERROR(BC17*$D17,0) -> 0 | BE17: =IFERROR(($G17-BC17)/$G17,0) -> 0 | BJ17: =IFERROR(BI17*$D17,0) -> 0 | BK17: =IFERROR(($G17-BI17)/$G17,0) -> 0 | BP17: =IFERROR(BO17*$D17,0) -> 0 | BQ17: =IFERROR(($G17-BO17)/$G17,0) -> 0 | BV17: =IFERROR(BU17*$D17,0) -> 0 | BW17: =IFERROR(($G17-BU17)/$G17,0) -> 0 | CB17: =IFERROR(CA17*$D17,0) -> 0 | CC17: =IFERROR(($G17-CA17)/$G17,0) -> 0 | CH17: =IFERROR(CG17*$D17,0) -> 0 | CI17: =IFERROR(($G17-CG17)/$G17,0) -> 0 | CN17: =IFERROR(CM17*$D17,0) -> 0 | CO17: =IFERROR(($G17-CM17)/$G17,0) -> 0
A18: 8 | I18: =G18*D18 -> 0 | L18: =IFERROR((J18-N18)/J18,0) -> 0 | M18: =IF(N18>0,IF(N18=AK18,$AJ$9,IF(N18=AQ18,$AP$9,IF(N18=AW18,$AV$9,IF(N18=BC18,$BB$9,IF(N18=BI18,$BH$9,IF(N18=BO18,$BN$9,IF(N18=BU18,$BT$9,IF(N18=CA18,$BZ$9,IF(N18=CG18,$CF$9,IF(N18=CM18,$CL$9,"")))))))))),"") | N18: =IF(X18>0,X18,Z18) -> 0 | O18: =IFERROR(N18*D18,"") -> 0 | P18: =MIN(IF($AO18=Reference!$A$10,100000000,AJ18),IF($AU18=Reference!$A$10,100000000,AP18),IF($BA18=Reference!$A$10,100000000,AV18),IF($BG18=Reference!$A$10,100000000,BB18),IF($BM18=Reference!$A$10,100000000,BH18),IF($BS18=Reference!$A$10,100000000,BN18),IF($BY18=Reference!$A$10,100000000,BT18),IF($CE18=Reference!$A$10,100000000,BZ18),IF($CK18=Reference!$A$10,100000000,CF18),IF($CQ18=Reference!$A$10,100000000,CL18)) -> 0 | Q18: =W18=F18 -> FALSE | R18: =COUNT(BC18,AK18,AQ18,AW18,BI18,BO18,BU18,CA18,CG18,CM18) -> 0 | S18: =MIN(AK18,AQ18,AW18,BC18,BI18,BO18,BU18,CA18,CG18,CM18)=N18 -> TRUE | T18: =IFERROR(AVERAGE(AK18,AQ18,AW18,BC18,BI18,BO18,BU18,CA18,CG18,CM18),"") | U18: =IFERROR(((G18-T18)/G18),"") | V18: =$Z18=$N18 -> TRUE | W18: =IF(Z18=AK18,$AJ$9,IF(Z18=AQ18,$AP$9,IF(Z18=AW18,$AV$9,IF(Z18=BC18,$BB$9,IF(Z18=BI18,$BH$9,IF(Z18=BO18,$BN$9,IF(Z18=BU18,$BT$9,IF(Z18=CA18,$BZ$9,IF(Z18=CG18,$CF$9,IF(Z18=CM18,$CL$9,"")))))))))) -> VENDOR 1 | X18: =IF(AO18=Reference!$A$8,'Bid Tab (F&B Ops and CatMan) 10'!AK18,IF('Bid Tab (F&B Ops and CatMan) 10'!AU18=Reference!$A$8,'Bid Tab (F&B Ops and CatMan) 10'!AQ18,IF('Bid Tab (F&B Ops and CatMan) 10'!BA18=Reference!$A$8,'Bid Tab (F&B Ops and CatMan) 10'!AW18,IF('Bid Tab (F&B Ops and CatMan) 10'!BG18=Reference!$A$8,'Bid Tab (F&B Ops and CatMan) 10'!BC18,IF('Bid Tab (F&B Ops and CatMan) 10'!BM18=Reference!$A$8,'Bid Tab (F&B Ops and CatMan) 10'!BI18,IF('Bid Tab (F&B Ops and CatMan) 10'!BS18=Reference!$A$8,'Bid Tab (F&B Ops and CatMan) 10'!BO18,IF('Bid Tab (F&B Ops and CatMan) 10'!BY18=Reference!$A$8,'Bid Tab (F&B Ops and CatMan) 10'!BU18,IF('Bid Tab (F&B Ops and CatMan) 10'!CE18=Reference!$A$8,'Bid Tab (F&B Ops and CatMan) 10'!CA18,IF('Bid Tab (F&B Ops and CatMan) 10'!CK18=Reference!$A$8,'Bid Tab (F&B Ops and CatMan) 10'!CG18,IF('Bid Tab (F&B Ops and CatMan) 10'!CQ18=Reference!$A$8,'Bid Tab (F&B Ops and CatMan) 10'!CM18,0)))))))))) -> 0 | Y18: =IFERROR(IF(Reference!$A$8=HLOOKUP(Reference!$A$8,'Bid Tab (F&B Ops and CatMan) 10'!AJ18:CQ18,1,0),TRUE,FALSE),FALSE) -> FALSE | Z18: =MIN(IF(AO18=Reference!$A$10,100000000,AK18),IF(AU18=Reference!$A$10,100000000,AQ18),IF(BA18=Reference!$A$10,100000000,AW18),IF(BG18=Reference!$A$10,100000000,BC18),IF(BM18=Reference!$A$10,100000000,BI18),IF(BS18=Reference!$A$10,100000000,BO18),IF(BY18=Reference!$A$10,100000000,BU18),IF(CE18=Reference!$A$10,100000000,CA18),IF(CK18=Reference!$A$10,100000000,CG18),IF(CQ18=Reference!$A$10,100000000,CM18)) -> 0 | AA18: =IF(X18>0,X18*D18,Z18*D18) -> 0 | AB18: =IF(Reference!A25>0,Reference!A25,MAX(IF(TODAY()-H18<365,IF(G18>=N18,G18,P18),P18),G18)) -> 0 | AC18: =IF(AE18>0,AB18*$D18,O18) -> 0 | AD18: =IF(N18>$AB18,0,(($AB18-N18))) -> 0 | AE18: =IF(N18>$AB18,0,(($AB18-N18)*$D18)) -> 0 | AF18: =IF(AND((AD18=0),(F18=M18),(G18=N18),(TODAY()-H18<365)),"PRICE EXTENSION",IF(AND(G18=AB18,G18>0),"LAST SYSTEM PRICE",IF(AB18>0,"INITIAL LOWEST BID"," "))) | AG18: =IF(G18>0,G18-Z18,0) -> 0 | AH18: =AG18*D18 -> 0 | AI18: =IFERROR((G18-Z18)/G18,0) -> 0 | AL18: =IFERROR(AK18*$D18,0) -> 0 | AM18: =IFERROR(($G18-AK18)/$G18,0) -> 0 | AR18: =IFERROR(AQ18*$D18,0) -> 0 | AS18: =IFERROR(($G18-AQ18)/$G18,0) -> 0 | AX18: =IFERROR(AW18*$D18,0) -> 0 | AY18: =IFERROR(($G18-AW18)/$G18,0) -> 0 | BD18: =IFERROR(BC18*$D18,0) -> 0 | BE18: =IFERROR(($G18-BC18)/$G18,0) -> 0 | BJ18: =IFERROR(BI18*$D18,0) -> 0 | BK18: =IFERROR(($G18-BI18)/$G18,0) -> 0 | BP18: =IFERROR(BO18*$D18,0) -> 0 | BQ18: =IFERROR(($G18-BO18)/$G18,0) -> 0 | BV18: =IFERROR(BU18*$D18,0) -> 0 | BW18: =IFERROR(($G18-BU18)/$G18,0) -> 0 | CB18: =IFERROR(CA18*$D18,0) -> 0 | CC18: =IFERROR(($G18-CA18)/$G18,0) -> 0 | CH18: =IFERROR(CG18*$D18,0) -> 0 | CI18: =IFERROR(($G18-CG18)/$G18,0) -> 0 | CN18: =IFERROR(CM18*$D18,0) -> 0 | CO18: =IFERROR(($G18-CM18)/$G18,0) -> 0
A19: 9 | I19: =G19*D19 -> 0 | L19: =IFERROR((J19-N19)/J19,0) -> 0 | M19: =IF(N19>0,IF(N19=AK19,$AJ$9,IF(N19=AQ19,$AP$9,IF(N19=AW19,$AV$9,IF(N19=BC19,$BB$9,IF(N19=BI19,$BH$9,IF(N19=BO19,$BN$9,IF(N19=BU19,$BT$9,IF(N19=CA19,$BZ$9,IF(N19=CG19,$CF$9,IF(N19=CM19,$CL$9,"")))))))))),"") | N19: =IF(X19>0,X19,Z19) -> 0 | O19: =IFERROR(N19*D19,"") -> 0 | P19: =MIN(IF($AO19=Reference!$A$10,100000000,AJ19),IF($AU19=Reference!$A$10,100000000,AP19),IF($BA19=Reference!$A$10,100000000,AV19),IF($BG19=Reference!$A$10,100000000,BB19),IF($BM19=Reference!$A$10,100000000,BH19),IF($BS19=Reference!$A$10,100000000,BN19),IF($BY19=Reference!$A$10,100000000,BT19),IF($CE19=Reference!$A$10,100000000,BZ19),IF($CK19=Reference!$A$10,100000000,CF19),IF($CQ19=Reference!$A$10,100000000,CL19)) -> 0 | Q19: =W19=F19 -> FALSE | R19: =COUNT(BC19,AK19,AQ19,AW19,BI19,BO19,BU19,CA19,CG19,CM19) -> 0 | S19: =MIN(AK19,AQ19,AW19,BC19,BI19,BO19,BU19,CA19,CG19,CM19)=N19 -> TRUE | T19: =IFERROR(AVERAGE(AK19,AQ19,AW19,BC19,BI19,BO19,BU19,CA19,CG19,CM19),"") | U19: =IFERROR(((G19-T19)/G19),"") | V19: =$Z19=$N19 -> TRUE | W19: =IF(Z19=AK19,$AJ$9,IF(Z19=AQ19,$AP$9,IF(Z19=AW19,$AV$9,IF(Z19=BC19,$BB$9,IF(Z19=BI19,$BH$9,IF(Z19=BO19,$BN$9,IF(Z19=BU19,$BT$9,IF(Z19=CA19,$BZ$9,IF(Z19=CG19,$CF$9,IF(Z19=CM19,$CL$9,"")))))))))) -> VENDOR 1 | X19: =IF(AO19=Reference!$A$8,'Bid Tab (F&B Ops and CatMan) 10'!AK19,IF('Bid Tab (F&B Ops and CatMan) 10'!AU19=Reference!$A$8,'Bid Tab (F&B Ops and CatMan) 10'!AQ19,IF('Bid Tab (F&B Ops and CatMan) 10'!BA19=Reference!$A$8,'Bid Tab (F&B Ops and CatMan) 10'!AW19,IF('Bid Tab (F&B Ops and CatMan) 10'!BG19=Reference!$A$8,'Bid Tab (F&B Ops and CatMan) 10'!BC19,IF('Bid Tab (F&B Ops and CatMan) 10'!BM19=Reference!$A$8,'Bid Tab (F&B Ops and CatMan) 10'!BI19,IF('Bid Tab (F&B Ops and CatMan) 10'!BS19=Reference!$A$8,'Bid Tab (F&B Ops and CatMan) 10'!BO19,IF('Bid Tab (F&B Ops and CatMan) 10'!BY19=Reference!$A$8,'Bid Tab (F&B Ops and CatMan) 10'!BU19,IF('Bid Tab (F&B Ops and CatMan) 10'!CE19=Reference!$A$8,'Bid Tab (F&B Ops and CatMan) 10'!CA19,IF('Bid Tab (F&B Ops and CatMan) 10'!CK19=Reference!$A$8,'Bid Tab (F&B Ops and CatMan) 10'!CG19,IF('Bid Tab (F&B Ops and CatMan) 10'!CQ19=Reference!$A$8,'Bid Tab (F&B Ops and CatMan) 10'!CM19,0)))))))))) -> 0 | Y19: =IFERROR(IF(Reference!$A$8=HLOOKUP(Reference!$A$8,'Bid Tab (F&B Ops and CatMan) 10'!AJ19:CQ19,1,0),TRUE,FALSE),FALSE) -> FALSE | Z19: =MIN(IF(AO19=Reference!$A$10,100000000,AK19),IF(AU19=Reference!$A$10,100000000,AQ19),IF(BA19=Reference!$A$10,100000000,AW19),IF(BG19=Reference!$A$10,100000000,BC19),IF(BM19=Reference!$A$10,100000000,BI19),IF(BS19=Reference!$A$10,100000000,BO19),IF(BY19=Reference!$A$10,100000000,BU19),IF(CE19=Reference!$A$10,100000000,CA19),IF(CK19=Reference!$A$10,100000000,CG19),IF(CQ19=Reference!$A$10,100000000,CM19)) -> 0 | AA19: =IF(X19>0,X19*D19,Z19*D19) -> 0 | AB19: =IF(Reference!A26>0,Reference!A26,MAX(IF(TODAY()-H19<365,IF(G19>=N19,G19,P19),P19),G19)) -> 0 | AC19: =IF(AE19>0,AB19*$D19,O19) -> 0 | AD19: =IF(N19>$AB19,0,(($AB19-N19))) -> 0 | AE19: =IF(N19>$AB19,0,(($AB19-N19)*$D19)) -> 0 | AF19: =IF(AND((AD19=0),(F19=M19),(G19=N19),(TODAY()-H19<365)),"PRICE EXTENSION",IF(AND(G19=AB19,G19>0),"LAST SYSTEM PRICE",IF(AB19>0,"INITIAL LOWEST BID"," "))) | AG19: =IF(G19>0,G19-Z19,0) -> 0 | AH19: =AG19*D19 -> 0 | AI19: =IFERROR((G19-Z19)/G19,0) -> 0 | AL19: =IFERROR(AK19*$D19,0) -> 0 | AM19: =IFERROR(($G19-AK19)/$G19,0) -> 0 | AR19: =IFERROR(AQ19*$D19,0) -> 0 | AS19: =IFERROR(($G19-AQ19)/$G19,0) -> 0 | AX19: =IFERROR(AW19*$D19,0) -> 0 | AY19: =IFERROR(($G19-AW19)/$G19,0) -> 0 | BD19: =IFERROR(BC19*$D19,0) -> 0 | BE19: =IFERROR(($G19-BC19)/$G19,0) -> 0 | BJ19: =IFERROR(BI19*$D19,0) -> 0 | BK19: =IFERROR(($G19-BI19)/$G19,0) -> 0 | BP19: =IFERROR(BO19*$D19,0) -> 0 | BQ19: =IFERROR(($G19-BO19)/$G19,0) -> 0 | BV19: =IFERROR(BU19*$D19,0) -> 0 | BW19: =IFERROR(($G19-BU19)/$G19,0) -> 0 | CB19: =IFERROR(CA19*$D19,0) -> 0 | CC19: =IFERROR(($G19-CA19)/$G19,0) -> 0 | CH19: =IFERROR(CG19*$D19,0) -> 0 | CI19: =IFERROR(($G19-CG19)/$G19,0) -> 0 | CN19: =IFERROR(CM19*$D19,0) -> 0 | CO19: =IFERROR(($G19-CM19)/$G19,0) -> 0
A20: 10 | I20: =G20*D20 -> 0 | L20: =IFERROR((J20-N20)/J20,0) -> 0 | M20: =IF(N20>0,IF(N20=AK20,$AJ$9,IF(N20=AQ20,$AP$9,IF(N20=AW20,$AV$9,IF(N20=BC20,$BB$9,IF(N20=BI20,$BH$9,IF(N20=BO20,$BN$9,IF(N20=BU20,$BT$9,IF(N20=CA20,$BZ$9,IF(N20=CG20,$CF$9,IF(N20=CM20,$CL$9,"")))))))))),"") | N20: =IF(X20>0,X20,Z20) -> 0 | O20: =IFERROR(N20*D20,"") -> 0 | P20: =MIN(IF($AO20=Reference!$A$10,100000000,AJ20),IF($AU20=Reference!$A$10,100000000,AP20),IF($BA20=Reference!$A$10,100000000,AV20),IF($BG20=Reference!$A$10,100000000,BB20),IF($BM20=Reference!$A$10,100000000,BH20),IF($BS20=Reference!$A$10,100000000,BN20),IF($BY20=Reference!$A$10,100000000,BT20),IF($CE20=Reference!$A$10,100000000,BZ20),IF($CK20=Reference!$A$10,100000000,CF20),IF($CQ20=Reference!$A$10,100000000,CL20)) -> 0 | Q20: =W20=F20 -> FALSE | R20: =COUNT(BC20,AK20,AQ20,AW20,BI20,BO20,BU20,CA20,CG20,CM20) -> 0 | S20: =MIN(AK20,AQ20,AW20,BC20,BI20,BO20,BU20,CA20,CG20,CM20)=N20 -> TRUE | T20: =IFERROR(AVERAGE(AK20,AQ20,AW20,BC20,BI20,BO20,BU20,CA20,CG20,CM20),"") | U20: =IFERROR(((G20-T20)/G20),"") | V20: =$Z20=$N20 -> TRUE | W20: =IF(Z20=AK20,$AJ$9,IF(Z20=AQ20,$AP$9,IF(Z20=AW20,$AV$9,IF(Z20=BC20,$BB$9,IF(Z20=BI20,$BH$9,IF(Z20=BO20,$BN$9,IF(Z20=BU20,$BT$9,IF(Z20=CA20,$BZ$9,IF(Z20=CG20,$CF$9,IF(Z20=CM20,$CL$9,"")))))))))) -> VENDOR 1 | X20: =IF(AO20=Reference!$A$8,'Bid Tab (F&B Ops and CatMan) 10'!AK20,IF('Bid Tab (F&B Ops and CatMan) 10'!AU20=Reference!$A$8,'Bid Tab (F&B Ops and CatMan) 10'!AQ20,IF('Bid Tab (F&B Ops and CatMan) 10'!BA20=Reference!$A$8,'Bid Tab (F&B Ops and CatMan) 10'!AW20,IF('Bid Tab (F&B Ops and CatMan) 10'!BG20=Reference!$A$8,'Bid Tab (F&B Ops and CatMan) 10'!BC20,IF('Bid Tab (F&B Ops and CatMan) 10'!BM20=Reference!$A$8,'Bid Tab (F&B Ops and CatMan) 10'!BI20,IF('Bid Tab (F&B Ops and CatMan) 10'!BS20=Reference!$A$8,'Bid Tab (F&B Ops and CatMan) 10'!BO20,IF('Bid Tab (F&B Ops and CatMan) 10'!BY20=Reference!$A$8,'Bid Tab (F&B Ops and CatMan) 10'!BU20,IF('Bid Tab (F&B Ops and CatMan) 10'!CE20=Reference!$A$8,'Bid Tab (F&B Ops and CatMan) 10'!CA20,IF('Bid Tab (F&B Ops and CatMan) 10'!CK20=Reference!$A$8,'Bid Tab (F&B Ops and CatMan) 10'!CG20,IF('Bid Tab (F&B Ops and CatMan) 10'!CQ20=Reference!$A$8,'Bid Tab (F&B Ops and CatMan) 10'!CM20,0)))))))))) -> 0 | Y20: =IFERROR(IF(Reference!$A$8=HLOOKUP(Reference!$A$8,'Bid Tab (F&B Ops and CatMan) 10'!AJ20:CQ20,1,0),TRUE,FALSE),FALSE) -> FALSE | Z20: =MIN(IF(AO20=Reference!$A$10,100000000,AK20),IF(AU20=Reference!$A$10,100000000,AQ20),IF(BA20=Reference!$A$10,100000000,AW20),IF(BG20=Reference!$A$10,100000000,BC20),IF(BM20=Reference!$A$10,100000000,BI20),IF(BS20=Reference!$A$10,100000000,BO20),IF(BY20=Reference!$A$10,100000000,BU20),IF(CE20=Reference!$A$10,100000000,CA20),IF(CK20=Reference!$A$10,100000000,CG20),IF(CQ20=Reference!$A$10,100000000,CM20)) -> 0 | AA20: =IF(X20>0,X20*D20,Z20*D20) -> 0 | AB20: =IF(Reference!A27>0,Reference!A27,MAX(IF(TODAY()-H20<365,IF(G20>=N20,G20,P20),P20),G20)) -> 0 | AC20: =IF(AE20>0,AB20*$D20,O20) -> 0 | AD20: =IF(N20>$AB20,0,(($AB20-N20))) -> 0 | AE20: =IF(N20>$AB20,0,(($AB20-N20)*$D20)) -> 0 | AF20: =IF(AND((AD20=0),(F20=M20),(G20=N20),(TODAY()-H20<365)),"PRICE EXTENSION",IF(AND(G20=AB20,G20>0),"LAST SYSTEM PRICE",IF(AB20>0,"INITIAL LOWEST BID"," "))) | AG20: =IF(G20>0,G20-Z20,0) -> 0 | AH20: =AG20*D20 -> 0 | AI20: =IFERROR((G20-Z20)/G20,0) -> 0 | AL20: =IFERROR(AK20*$D20,0) -> 0 | AM20: =IFERROR(($G20-AK20)/$G20,0) -> 0 | AR20: =IFERROR(AQ20*$D20,0) -> 0 | AS20: =IFERROR(($G20-AQ20)/$G20,0) -> 0 | AX20: =IFERROR(AW20*$D20,0) -> 0 | AY20: =IFERROR(($G20-AW20)/$G20,0) -> 0 | BD20: =IFERROR(BC20*$D20,0) -> 0 | BE20: =IFERROR(($G20-BC20)/$G20,0) -> 0 | BJ20: =IFERROR(BI20*$D20,0) -> 0 | BK20: =IFERROR(($G20-BI20)/$G20,0) -> 0 | BP20: =IFERROR(BO20*$D20,0) -> 0 | BQ20: =IFERROR(($G20-BO20)/$G20,0) -> 0 | BV20: =IFERROR(BU20*$D20,0) -> 0 | BW20: =IFERROR(($G20-BU20)/$G20,0) -> 0 | CB20: =IFERROR(CA20*$D20,0) -> 0 | CC20: =IFERROR(($G20-CA20)/$G20,0) -> 0 | CH20: =IFERROR(CG20*$D20,0) -> 0 | CI20: =IFERROR(($G20-CG20)/$G20,0) -> 0 | CN20: =IFERROR(CM20*$D20,0) -> 0 | CO20: =IFERROR(($G20-CM20)/$G20,0) -> 0
A21: 11 | I21: =G21*D21 -> 0 | L21: =IFERROR((J21-N21)/J21,0) -> 0 | M21: =IF(N21>0,IF(N21=AK21,$AJ$9,IF(N21=AQ21,$AP$9,IF(N21=AW21,$AV$9,IF(N21=BC21,$BB$9,IF(N21=BI21,$BH$9,IF(N21=BO21,$BN$9,IF(N21=BU21,$BT$9,IF(N21=CA21,$BZ$9,IF(N21=CG21,$CF$9,IF(N21=CM21,$CL$9,"")))))))))),"") | N21: =IF(X21>0,X21,Z21) -> 0 | O21: =IFERROR(N21*D21,"") -> 0 | P21: =MIN(IF($AO21=Reference!$A$10,100000000,AJ21),IF($AU21=Reference!$A$10,100000000,AP21),IF($BA21=Reference!$A$10,100000000,AV21),IF($BG21=Reference!$A$10,100000000,BB21),IF($BM21=Reference!$A$10,100000000,BH21),IF($BS21=Reference!$A$10,100000000,BN21),IF($BY21=Reference!$A$10,100000000,BT21),IF($CE21=Reference!$A$10,100000000,BZ21),IF($CK21=Reference!$A$10,100000000,CF21),IF($CQ21=Reference!$A$10,100000000,CL21)) -> 0 | Q21: =W21=F21 -> FALSE | R21: =COUNT(BC21,AK21,AQ21,AW21,BI21,BO21,BU21,CA21,CG21,CM21) -> 0 | S21: =MIN(AK21,AQ21,AW21,BC21,BI21,BO21,BU21,CA21,CG21,CM21)=N21 -> TRUE | T21: =IFERROR(AVERAGE(AK21,AQ21,AW21,BC21,BI21,BO21,BU21,CA21,CG21,CM21),"") | U21: =IFERROR(((G21-T21)/G21),"") | V21: =$Z21=$N21 -> TRUE | W21: =IF(Z21=AK21,$AJ$9,IF(Z21=AQ21,$AP$9,IF(Z21=AW21,$AV$9,IF(Z21=BC21,$BB$9,IF(Z21=BI21,$BH$9,IF(Z21=BO21,$BN$9,IF(Z21=BU21,$BT$9,IF(Z21=CA21,$BZ$9,IF(Z21=CG21,$CF$9,IF(Z21=CM21,$CL$9,"")))))))))) -> VENDOR 1 | X21: =IF(AO21=Reference!$A$8,'Bid Tab (F&B Ops and CatMan) 10'!AK21,IF('Bid Tab (F&B Ops and CatMan) 10'!AU21=Reference!$A$8,'Bid Tab (F&B Ops and CatMan) 10'!AQ21,IF('Bid Tab (F&B Ops and CatMan) 10'!BA21=Reference!$A$8,'Bid Tab (F&B Ops and CatMan) 10'!AW21,IF('Bid Tab (F&B Ops and CatMan) 10'!BG21=Reference!$A$8,'Bid Tab (F&B Ops and CatMan) 10'!BC21,IF('Bid Tab (F&B Ops and CatMan) 10'!BM21=Reference!$A$8,'Bid Tab (F&B Ops and CatMan) 10'!BI21,IF('Bid Tab (F&B Ops and CatMan) 10'!BS21=Reference!$A$8,'Bid Tab (F&B Ops and CatMan) 10'!BO21,IF('Bid Tab (F&B Ops and CatMan) 10'!BY21=Reference!$A$8,'Bid Tab (F&B Ops and CatMan) 10'!BU21,IF('Bid Tab (F&B Ops and CatMan) 10'!CE21=Reference!$A$8,'Bid Tab (F&B Ops and CatMan) 10'!CA21,IF('Bid Tab (F&B Ops and CatMan) 10'!CK21=Reference!$A$8,'Bid Tab (F&B Ops and CatMan) 10'!CG21,IF('Bid Tab (F&B Ops and CatMan) 10'!CQ21=Reference!$A$8,'Bid Tab (F&B Ops and CatMan) 10'!CM21,0)))))))))) -> 0 | Y21: =IFERROR(IF(Reference!$A$8=HLOOKUP(Reference!$A$8,'Bid Tab (F&B Ops and CatMan) 10'!AJ21:CQ21,1,0),TRUE,FALSE),FALSE) -> FALSE | Z21: =MIN(IF(AO21=Reference!$A$10,100000000,AK21),IF(AU21=Reference!$A$10,100000000,AQ21),IF(BA21=Reference!$A$10,100000000,AW21),IF(BG21=Reference!$A$10,100000000,BC21),IF(BM21=Reference!$A$10,100000000,BI21),IF(BS21=Reference!$A$10,100000000,BO21),IF(BY21=Reference!$A$10,100000000,BU21),IF(CE21=Reference!$A$10,100000000,CA21),IF(CK21=Reference!$A$10,100000000,CG21),IF(CQ21=Reference!$A$10,100000000,CM21)) -> 0 | AA21: =IF(X21>0,X21*D21,Z21*D21) -> 0 | AB21: =IF(Reference!A28>0,Reference!A28,MAX(IF(TODAY()-H21<365,IF(G21>=N21,G21,P21),P21),G21)) -> 0 | AC21: =IF(AE21>0,AB21*$D21,O21) -> 0 | AD21: =IF(N21>$AB21,0,(($AB21-N21))) -> 0 | AE21: =IF(N21>$AB21,0,(($AB21-N21)*$D21)) -> 0 | AF21: =IF(AND((AD21=0),(F21=M21),(G21=N21),(TODAY()-H21<365)),"PRICE EXTENSION",IF(AND(G21=AB21,G21>0),"LAST SYSTEM PRICE",IF(AB21>0,"INITIAL LOWEST BID"," "))) | AG21: =IF(G21>0,G21-Z21,0) -> 0 | AH21: =AG21*D21 -> 0 | AI21: =IFERROR((G21-Z21)/G21,0) -> 0 | AL21: =IFERROR(AK21*$D21,0) -> 0 | AM21: =IFERROR(($G21-AK21)/$G21,0) -> 0 | AR21: =IFERROR(AQ21*$D21,0) -> 0 | AS21: =IFERROR(($G21-AQ21)/$G21,0) -> 0 | AX21: =IFERROR(AW21*$D21,0) -> 0 | AY21: =IFERROR(($G21-AW21)/$G21,0) -> 0 | BD21: =IFERROR(BC21*$D21,0) -> 0 | BE21: =IFERROR(($G21-BC21)/$G21,0) -> 0 | BJ21: =IFERROR(BI21*$D21,0) -> 0 | BK21: =IFERROR(($G21-BI21)/$G21,0) -> 0 | BP21: =IFERROR(BO21*$D21,0) -> 0 | BQ21: =IFERROR(($G21-BO21)/$G21,0) -> 0 | BV21: =IFERROR(BU21*$D21,0) -> 0 | BW21: =IFERROR(($G21-BU21)/$G21,0) -> 0 | CB21: =IFERROR(CA21*$D21,0) -> 0 | CC21: =IFERROR(($G21-CA21)/$G21,0) -> 0 | CH21: =IFERROR(CG21*$D21,0) -> 0 | CI21: =IFERROR(($G21-CG21)/$G21,0) -> 0 | CN21: =IFERROR(CM21*$D21,0) -> 0 | CO21: =IFERROR(($G21-CM21)/$G21,0) -> 0
A22: 12 | I22: =G22*D22 -> 0 | L22: =IFERROR((J22-N22)/J22,0) -> 0 | M22: =IF(N22>0,IF(N22=AK22,$AJ$9,IF(N22=AQ22,$AP$9,IF(N22=AW22,$AV$9,IF(N22=BC22,$BB$9,IF(N22=BI22,$BH$9,IF(N22=BO22,$BN$9,IF(N22=BU22,$BT$9,IF(N22=CA22,$BZ$9,IF(N22=CG22,$CF$9,IF(N22=CM22,$CL$9,"")))))))))),"") | N22: =IF(X22>0,X22,Z22) -> 0 | O22: =IFERROR(N22*D22,"") -> 0 | P22: =MIN(IF($AO22=Reference!$A$10,100000000,AJ22),IF($AU22=Reference!$A$10,100000000,AP22),IF($BA22=Reference!$A$10,100000000,AV22),IF($BG22=Reference!$A$10,100000000,BB22),IF($BM22=Reference!$A$10,100000000,BH22),IF($BS22=Reference!$A$10,100000000,BN22),IF($BY22=Reference!$A$10,100000000,BT22),IF($CE22=Reference!$A$10,100000000,BZ22),IF($CK22=Reference!$A$10,100000000,CF22),IF($CQ22=Reference!$A$10,100000000,CL22)) -> 0 | Q22: =W22=F22 -> FALSE | R22: =COUNT(BC22,AK22,AQ22,AW22,BI22,BO22,BU22,CA22,CG22,CM22) -> 0 | S22: =MIN(AK22,AQ22,AW22,BC22,BI22,BO22,BU22,CA22,CG22,CM22)=N22 -> TRUE | T22: =IFERROR(AVERAGE(AK22,AQ22,AW22,BC22,BI22,BO22,BU22,CA22,CG22,CM22),"") | U22: =IFERROR(((G22-T22)/G22),"") | V22: =$Z22=$N22 -> TRUE | W22: =IF(Z22=AK22,$AJ$9,IF(Z22=AQ22,$AP$9,IF(Z22=AW22,$AV$9,IF(Z22=BC22,$BB$9,IF(Z22=BI22,$BH$9,IF(Z22=BO22,$BN$9,IF(Z22=BU22,$BT$9,IF(Z22=CA22,$BZ$9,IF(Z22=CG22,$CF$9,IF(Z22=CM22,$CL$9,"")))))))))) -> VENDOR 1 | X22: =IF(AO22=Reference!$A$8,'Bid Tab (F&B Ops and CatMan) 10'!AK22,IF('Bid Tab (F&B Ops and CatMan) 10'!AU22=Reference!$A$8,'Bid Tab (F&B Ops and CatMan) 10'!AQ22,IF('Bid Tab (F&B Ops and CatMan) 10'!BA22=Reference!$A$8,'Bid Tab (F&B Ops and CatMan) 10'!AW22,IF('Bid Tab (F&B Ops and CatMan) 10'!BG22=Reference!$A$8,'Bid Tab (F&B Ops and CatMan) 10'!BC22,IF('Bid Tab (F&B Ops and CatMan) 10'!BM22=Reference!$A$8,'Bid Tab (F&B Ops and CatMan) 10'!BI22,IF('Bid Tab (F&B Ops and CatMan) 10'!BS22=Reference!$A$8,'Bid Tab (F&B Ops and CatMan) 10'!BO22,IF('Bid Tab (F&B Ops and CatMan) 10'!BY22=Reference!$A$8,'Bid Tab (F&B Ops and CatMan) 10'!BU22,IF('Bid Tab (F&B Ops and CatMan) 10'!CE22=Reference!$A$8,'Bid Tab (F&B Ops and CatMan) 10'!CA22,IF('Bid Tab (F&B Ops and CatMan) 10'!CK22=Reference!$A$8,'Bid Tab (F&B Ops and CatMan) 10'!CG22,IF('Bid Tab (F&B Ops and CatMan) 10'!CQ22=Reference!$A$8,'Bid Tab (F&B Ops and CatMan) 10'!CM22,0)))))))))) -> 0 | Y22: =IFERROR(IF(Reference!$A$8=HLOOKUP(Reference!$A$8,'Bid Tab (F&B Ops and CatMan) 10'!AJ22:CQ22,1,0),TRUE,FALSE),FALSE) -> FALSE | Z22: =MIN(IF(AO22=Reference!$A$10,100000000,AK22),IF(AU22=Reference!$A$10,100000000,AQ22),IF(BA22=Reference!$A$10,100000000,AW22),IF(BG22=Reference!$A$10,100000000,BC22),IF(BM22=Reference!$A$10,100000000,BI22),IF(BS22=Reference!$A$10,100000000,BO22),IF(BY22=Reference!$A$10,100000000,BU22),IF(CE22=Reference!$A$10,100000000,CA22),IF(CK22=Reference!$A$10,100000000,CG22),IF(CQ22=Reference!$A$10,100000000,CM22)) -> 0 | AA22: =IF(X22>0,X22*D22,Z22*D22) -> 0 | AB22: =IF(Reference!A29>0,Reference!A29,MAX(IF(TODAY()-H22<365,IF(G22>=N22,G22,P22),P22),G22)) -> 0 | AC22: =IF(AE22>0,AB22*$D22,O22) -> 0 | AD22: =IF(N22>$AB22,0,(($AB22-N22))) -> 0 | AE22: =IF(N22>$AB22,0,(($AB22-N22)*$D22)) -> 0 | AF22: =IF(AND((AD22=0),(F22=M22),(G22=N22),(TODAY()-H22<365)),"PRICE EXTENSION",IF(AND(G22=AB22,G22>0),"LAST SYSTEM PRICE",IF(AB22>0,"INITIAL LOWEST BID"," "))) | AG22: =IF(G22>0,G22-Z22,0) -> 0 | AH22: =AG22*D22 -> 0 | AI22: =IFERROR((G22-Z22)/G22,0) -> 0 | AL22: =IFERROR(AK22*$D22,0) -> 0 | AM22: =IFERROR(($G22-AK22)/$G22,0) -> 0 | AR22: =IFERROR(AQ22*$D22,0) -> 0 | AS22: =IFERROR(($G22-AQ22)/$G22,0) -> 0 | AX22: =IFERROR(AW22*$D22,0) -> 0 | AY22: =IFERROR(($G22-AW22)/$G22,0) -> 0 | BD22: =IFERROR(BC22*$D22,0) -> 0 | BE22: =IFERROR(($G22-BC22)/$G22,0) -> 0 | BJ22: =IFERROR(BI22*$D22,0) -> 0 | BK22: =IFERROR(($G22-BI22)/$G22,0) -> 0 | BP22: =IFERROR(BO22*$D22,0) -> 0 | BQ22: =IFERROR(($G22-BO22)/$G22,0) -> 0 | BV22: =IFERROR(BU22*$D22,0) -> 0 | BW22: =IFERROR(($G22-BU22)/$G22,0) -> 0 | CB22: =IFERROR(CA22*$D22,0) -> 0 | CC22: =IFERROR(($G22-CA22)/$G22,0) -> 0 | CH22: =IFERROR(CG22*$D22,0) -> 0 | CI22: =IFERROR(($G22-CG22)/$G22,0) -> 0 | CN22: =IFERROR(CM22*$D22,0) -> 0 | CO22: =IFERROR(($G22-CM22)/$G22,0) -> 0
A23: 13 | I23: =G23*D23 -> 0 | L23: =IFERROR((J23-N23)/J23,0) -> 0 | M23: =IF(N23>0,IF(N23=AK23,$AJ$9,IF(N23=AQ23,$AP$9,IF(N23=AW23,$AV$9,IF(N23=BC23,$BB$9,IF(N23=BI23,$BH$9,IF(N23=BO23,$BN$9,IF(N23=BU23,$BT$9,IF(N23=CA23,$BZ$9,IF(N23=CG23,$CF$9,IF(N23=CM23,$CL$9,"")))))))))),"") | N23: =IF(X23>0,X23,Z23) -> 0 | O23: =IFERROR(N23*D23,"") -> 0 | P23: =MIN(IF($AO23=Reference!$A$10,100000000,AJ23),IF($AU23=Reference!$A$10,100000000,AP23),IF($BA23=Reference!$A$10,100000000,AV23),IF($BG23=Reference!$A$10,100000000,BB23),IF($BM23=Reference!$A$10,100000000,BH23),IF($BS23=Reference!$A$10,100000000,BN23),IF($BY23=Reference!$A$10,100000000,BT23),IF($CE23=Reference!$A$10,100000000,BZ23),IF($CK23=Reference!$A$10,100000000,CF23),IF($CQ23=Reference!$A$10,100000000,CL23)) -> 0 | Q23: =W23=F23 -> FALSE | R23: =COUNT(BC23,AK23,AQ23,AW23,BI23,BO23,BU23,CA23,CG23,CM23) -> 0 | S23: =MIN(AK23,AQ23,AW23,BC23,BI23,BO23,BU23,CA23,CG23,CM23)=N23 -> TRUE | T23: =IFERROR(AVERAGE(AK23,AQ23,AW23,BC23,BI23,BO23,BU23,CA23,CG23,CM23),"") | U23: =IFERROR(((G23-T23)/G23),"") | V23: =$Z23=$N23 -> TRUE | W23: =IF(Z23=AK23,$AJ$9,IF(Z23=AQ23,$AP$9,IF(Z23=AW23,$AV$9,IF(Z23=BC23,$BB$9,IF(Z23=BI23,$BH$9,IF(Z23=BO23,$BN$9,IF(Z23=BU23,$BT$9,IF(Z23=CA23,$BZ$9,IF(Z23=CG23,$CF$9,IF(Z23=CM23,$CL$9,"")))))))))) -> VENDOR 1 | X23: =IF(AO23=Reference!$A$8,'Bid Tab (F&B Ops and CatMan) 10'!AK23,IF('Bid Tab (F&B Ops and CatMan) 10'!AU23=Reference!$A$8,'Bid Tab (F&B Ops and CatMan) 10'!AQ23,IF('Bid Tab (F&B Ops and CatMan) 10'!BA23=Reference!$A$8,'Bid Tab (F&B Ops and CatMan) 10'!AW23,IF('Bid Tab (F&B Ops and CatMan) 10'!BG23=Reference!$A$8,'Bid Tab (F&B Ops and CatMan) 10'!BC23,IF('Bid Tab (F&B Ops and CatMan) 10'!BM23=Reference!$A$8,'Bid Tab (F&B Ops and CatMan) 10'!BI23,IF('Bid Tab (F&B Ops and CatMan) 10'!BS23=Reference!$A$8,'Bid Tab (F&B Ops and CatMan) 10'!BO23,IF('Bid Tab (F&B Ops and CatMan) 10'!BY23=Reference!$A$8,'Bid Tab (F&B Ops and CatMan) 10'!BU23,IF('Bid Tab (F&B Ops and CatMan) 10'!CE23=Reference!$A$8,'Bid Tab (F&B Ops and CatMan) 10'!CA23,IF('Bid Tab (F&B Ops and CatMan) 10'!CK23=Reference!$A$8,'Bid Tab (F&B Ops and CatMan) 10'!CG23,IF('Bid Tab (F&B Ops and CatMan) 10'!CQ23=Reference!$A$8,'Bid Tab (F&B Ops and CatMan) 10'!CM23,0)))))))))) -> 0 | Y23: =IFERROR(IF(Reference!$A$8=HLOOKUP(Reference!$A$8,'Bid Tab (F&B Ops and CatMan) 10'!AJ23:CQ23,1,0),TRUE,FALSE),FALSE) -> FALSE | Z23: =MIN(IF(AO23=Reference!$A$10,100000000,AK23),IF(AU23=Reference!$A$10,100000000,AQ23),IF(BA23=Reference!$A$10,100000000,AW23),IF(BG23=Reference!$A$10,100000000,BC23),IF(BM23=Reference!$A$10,100000000,BI23),IF(BS23=Reference!$A$10,100000000,BO23),IF(BY23=Reference!$A$10,100000000,BU23),IF(CE23=Reference!$A$10,100000000,CA23),IF(CK23=Reference!$A$10,100000000,CG23),IF(CQ23=Reference!$A$10,100000000,CM23)) -> 0 | AA23: =IF(X23>0,X23*D23,Z23*D23) -> 0 | AB23: =IF(Reference!A30>0,Reference!A30,MAX(IF(TODAY()-H23<365,IF(G23>=N23,G23,P23),P23),G23)) -> 0 | AC23: =IF(AE23>0,AB23*$D23,O23) -> 0 | AD23: =IF(N23>$AB23,0,(($AB23-N23))) -> 0 | AE23: =IF(N23>$AB23,0,(($AB23-N23)*$D23)) -> 0 | AF23: =IF(AND((AD23=0),(F23=M23),(G23=N23),(TODAY()-H23<365)),"PRICE EXTENSION",IF(AND(G23=AB23,G23>0),"LAST SYSTEM PRICE",IF(AB23>0,"INITIAL LOWEST BID"," "))) | AG23: =IF(G23>0,G23-Z23,0) -> 0 | AH23: =AG23*D23 -> 0 | AI23: =IFERROR((G23-Z23)/G23,0) -> 0 | AL23: =IFERROR(AK23*$D23,0) -> 0 | AM23: =IFERROR(($G23-AK23)/$G23,0) -> 0 | AR23: =IFERROR(AQ23*$D23,0) -> 0 | AS23: =IFERROR(($G23-AQ23)/$G23,0) -> 0 | AX23: =IFERROR(AW23*$D23,0) -> 0 | AY23: =IFERROR(($G23-AW23)/$G23,0) -> 0 | BD23: =IFERROR(BC23*$D23,0) -> 0 | BE23: =IFERROR(($G23-BC23)/$G23,0) -> 0 | BJ23: =IFERROR(BI23*$D23,0) -> 0 | BK23: =IFERROR(($G23-BI23)/$G23,0) -> 0 | BP23: =IFERROR(BO23*$D23,0) -> 0 | BQ23: =IFERROR(($G23-BO23)/$G23,0) -> 0 | BV23: =IFERROR(BU23*$D23,0) -> 0 | BW23: =IFERROR(($G23-BU23)/$G23,0) -> 0 | CB23: =IFERROR(CA23*$D23,0) -> 0 | CC23: =IFERROR(($G23-CA23)/$G23,0) -> 0 | CH23: =IFERROR(CG23*$D23,0) -> 0 | CI23: =IFERROR(($G23-CG23)/$G23,0) -> 0 | CN23: =IFERROR(CM23*$D23,0) -> 0 | CO23: =IFERROR(($G23-CM23)/$G23,0) -> 0
... A30: 20 | I30: =G30*D30 -> 0 | L30: =IFERROR((J30-N30)/J30,0) -> 0 | M30: =IF(N30>0,IF(N30=AK30,$AJ$9,IF(N30=AQ30,$AP$9,IF(N30=AW30,$AV$9,IF(N30=BC30,$BB$9,IF(N30=BI30,$BH$9,IF(N30=BO30,$BN$9,IF(N30=BU30,$BT$9,IF(N30=CA30,$BZ$9,IF(N30=CG30,$CF$9,IF(N30=CM30,$CL$9,"")))))))))),"") | N30: =IF(X30>0,X30,Z30) -> 0 | O30: =IFERROR(N30*D30,"") -> 0 | P30: =MIN(IF($AO30=Reference!$A$10,100000000,AJ30),IF($AU30=Reference!$A$10,100000000,AP30),IF($BA30=Reference!$A$10,100000000,AV30),IF($BG30=Reference!$A$10,100000000,BB30),IF($BM30=Reference!$A$10,100000000,BH30),IF($BS30=Reference!$A$10,100000000,BN30),IF($BY30=Reference!$A$10,100000000,BT30),IF($CE30=Reference!$A$10,100000000,BZ30),IF($CK30=Reference!$A$10,100000000,CF30),IF($CQ30=Reference!$A$10,100000000,CL30)) -> 0 | Q30: =W30=F30 -> FALSE | R30: =COUNT(BC30,AK30,AQ30,AW30,BI30,BO30,BU30,CA30,CG30,CM30) -> 0 | S30: =MIN(AK30,AQ30,AW30,BC30,BI30,BO30,BU30,CA30,CG30,CM30)=N30 -> TRUE | T30: =IFERROR(AVERAGE(AK30,AQ30,AW30,BC30,BI30,BO30,BU30,CA30,CG30,CM30),"") | U30: =IFERROR(((G30-T30)/G30),"") | V30: =$Z30=$N30 -> TRUE | W30: =IF(Z30=AK30,$AJ$9,IF(Z30=AQ30,$AP$9,IF(Z30=AW30,$AV$9,IF(Z30=BC30,$BB$9,IF(Z30=BI30,$BH$9,IF(Z30=BO30,$BN$9,IF(Z30=BU30,$BT$9,IF(Z30=CA30,$BZ$9,IF(Z30=CG30,$CF$9,IF(Z30=CM30,$CL$9,"")))))))))) -> VENDOR 1 | X30: =IF(AO30=Reference!$A$8,'Bid Tab (F&B Ops and CatMan) 10'!AK30,IF('Bid Tab (F&B Ops and CatMan) 10'!AU30=Reference!$A$8,'Bid Tab (F&B Ops and CatMan) 10'!AQ30,IF('Bid Tab (F&B Ops and CatMan) 10'!BA30=Reference!$A$8,'Bid Tab (F&B Ops and CatMan) 10'!AW30,IF('Bid Tab (F&B Ops and CatMan) 10'!BG30=Reference!$A$8,'Bid Tab (F&B Ops and CatMan) 10'!BC30,IF('Bid Tab (F&B Ops and CatMan) 10'!BM30=Reference!$A$8,'Bid Tab (F&B Ops and CatMan) 10'!BI30,IF('Bid Tab (F&B Ops and CatMan) 10'!BS30=Reference!$A$8,'Bid Tab (F&B Ops and CatMan) 10'!BO30,IF('Bid Tab (F&B Ops and CatMan) 10'!BY30=Reference!$A$8,'Bid Tab (F&B Ops and CatMan) 10'!BU30,IF('Bid Tab (F&B Ops and CatMan) 10'!CE30=Reference!$A$8,'Bid Tab (F&B Ops and CatMan) 10'!CA30,IF('Bid Tab (F&B Ops and CatMan) 10'!CK30=Reference!$A$8,'Bid Tab (F&B Ops and CatMan) 10'!CG30,IF('Bid Tab (F&B Ops and CatMan) 10'!CQ30=Reference!$A$8,'Bid Tab (F&B Ops and CatMan) 10'!CM30,0)))))))))) -> 0 | Y30: =IFERROR(IF(Reference!$A$8=HLOOKUP(Reference!$A$8,'Bid Tab (F&B Ops and CatMan) 10'!AJ30:CQ30,1,0),TRUE,FALSE),FALSE) -> FALSE | Z30: =MIN(IF(AO30=Reference!$A$10,100000000,AK30),IF(AU30=Reference!$A$10,100000000,AQ30),IF(BA30=Reference!$A$10,100000000,AW30),IF(BG30=Reference!$A$10,100000000,BC30),IF(BM30=Reference!$A$10,100000000,BI30),IF(BS30=Reference!$A$10,100000000,BO30),IF(BY30=Reference!$A$10,100000000,BU30),IF(CE30=Reference!$A$10,100000000,CA30),IF(CK30=Reference!$A$10,100000000,CG30),IF(CQ30=Reference!$A$10,100000000,CM30)) -> 0 | AA30: =IF(X30>0,X30*D30,Z30*D30) -> 0 | AB30: =IF(Reference!A37>0,Reference!A37,MAX(IF(TODAY()-H30<365,IF(G30>=N30,G30,P30),P30),G30)) -> 0 | AC30: =IF(AE30>0,AB30*$D30,O30) -> 0 | AD30: =IF(N30>$AB30,0,(($AB30-N30))) -> 0 | AE30: =IF(N30>$AB30,0,(($AB30-N30)*$D30)) -> 0 | AF30: =IF(AND((AD30=0),(F30=M30),(G30=N30),(TODAY()-H30<365)),"PRICE EXTENSION",IF(AND(G30=AB30,G30>0),"LAST SYSTEM PRICE",IF(AB30>0,"INITIAL LOWEST BID"," "))) | AG30: =IF(G30>0,G30-Z30,0) -> 0 | AH30: =AG30*D30 -> 0 | AI30: =IFERROR((G30-Z30)/G30,0) -> 0 | AL30: =IFERROR(AK30*$D30,0) -> 0 | AM30: =IFERROR(($G30-AK30)/$G30,0) -> 0 | AR30: =IFERROR(AQ30*$D30,0) -> 0 | AS30: =IFERROR(($G30-AQ30)/$G30,0) -> 0 | AX30: =IFERROR(AW30*$D30,0) -> 0 | AY30: =IFERROR(($G30-AW30)/$G30,0) -> 0 | BD30: =IFERROR(BC30*$D30,0) -> 0 | BE30: =IFERROR(($G30-BC30)/$G30,0) -> 0 | BJ30: =IFERROR(BI30*$D30,0) -> 0 | BK30: =IFERROR(($G30-BI30)/$G30,0) -> 0 | BP30: =IFERROR(BO30*$D30,0) -> 0 | BQ30: =IFERROR(($G30-BO30)/$G30,0) -> 0 | BV30: =IFERROR(BU30*$D30,0) -> 0 | BW30: =IFERROR(($G30-BU30)/$G30,0) -> 0 | CB30: =IFERROR(CA30*$D30,0) -> 0 | CC30: =IFERROR(($G30-CA30)/$G30,0) -> 0 | CH30: =IFERROR(CG30*$D30,0) -> 0 | CI30: =IFERROR(($G30-CG30)/$G30,0) -> 0 | CN30: =IFERROR(CM30*$D30,0) -> 0 | CO30: =IFERROR(($G30-CM30)/$G30,0) -> 0
A32: =SUBTOTAL(3,A11:A31) -> 20 | B32: =SUBTOTAL(3,B11:B31) -> 0 | C32: GRAND TOTAL (EXCLUSIVE OF VAT) | D32: =SUBTOTAL(9,D11:D31) -> 0 | I32: =SUBTOTAL(9,I11:I31) -> 0 | O32: =ROUNDUP(SUBTOTAL(9,O11:O31),2) -> 0 | AA32: =ROUNDUP(SUBTOTAL(9,AA11:AA31),2) -> 0 | AC32: =SUBTOTAL(9,AC11:AC31) -> 0 | AE32: =SUBTOTAL(9,AE11:AE31) -> 0 | AH32: =SUBTOTAL(9,AH11:AH31) -> 0 | AI32: =IFERROR(AH32/I32,0) -> 0 | AJ32: =SUM(AL11:AL30) -> 0 | AP32: =SUM(AR11:AR30) -> 0 | AV32: =SUM(AX11:AX30) -> 0 | BB32: =SUM(BD11:BD30) -> 0 | BH32: =SUM(BJ11:BJ30) -> 0 | BN32: =SUM(BP11:BP30) -> 0 | BT32: =SUM(BV11:BV30) -> 0 | BZ32: =SUM(CB11:CB30) -> 0 | CF32: =SUM(CH11:CH30) -> 0 | CL32: =SUM(CN11:CN30) -> 0
AA33: =O32=AA32 -> TRUE | AE33: =IFERROR(AE32/AC32,0) -> 0
AI34: CONVERSION RATE: | AJ34: 1 | AL34: DATE:
AI35: LOGISTICS COST (as applicable):
B36: AWARD SUMMARY | C36: =C32 -> GRAND TOTAL (EXCLUSIVE OF VAT) | D36: Item Count | E36: % Savings | F36: Procurement Savings | G36: % Award Share by Amount | H36: % Award Share by Volume | I36: % Award Share by SKU | J36: GRAND TOTAL AWARDED (VAT Ex / Inc) | K36: BID VALIDITY | L36: LEAD TIME | M36: EXECUTION | AI36: ACQUISITION COST (Exclusive of VAT): | AJ36: =AJ32+AJ35 -> 0 | AP36: =AP32+AP35 -> 0 | AV36: =AV32+AV35 -> 0 | BB36: =BB32+BB35 -> 0 | BH36: =BH32+BH35 -> 0 | BN36: =BN32+BN35 -> 0 | BT36: =BT32+BT35 -> 0 | BZ36: =BZ32+BZ35 -> 0 | CF36: =CF32+CF35 -> 0 | CL36: =CL32+CL35 -> 0
B37: =AJ9 -> VENDOR 1 | C37: =SUMIF($M$11:$M$30,B37,$O$11:$O$30) -> 0 | D37: =COUNTIF($M$11:$M$30,B37) -> 0 | E37: =IFERROR(F37/(C37+F37),0) -> 0 | F37: =SUMIF($M$11:$M$30,B37,$AE$11:$AE$30) -> 0 | G37: =IFERROR(C37/$C$47,"") | H37: =IFERROR((SUMIFS($D$11:$D$30,$M$11:$M$30,$B37))/$D$32,"") | I37: =IFERROR($D37/$B$32,"") | J37: =IF(Reference!$A$13=HLOOKUP('Bid Tab (F&B Ops and CatMan) 10'!$B37,$AJ$50:$CQ$59,9,0),'Bid Tab (F&B Ops and CatMan) 10'!$C37*1.12,'Bid Tab (F&B Ops and CatMan) 10'!$C37) -> 0 | K37: =IF(AJ52="","",HLOOKUP($B37,$AJ$50:$CQ$59,3,0)) | L37: =IF(AJ53="","",HLOOKUP($B37,$AJ$50:$CQ$59,4,0)) | AI37: TOTAL PAYABLE TO SUPPLIER (Inclusive of VAT, as applicable) | AJ37: =(IF(AJ58="VAT Inclusive",AJ32*0.12,0)+AJ32) -> 0 | AP37: =(IF(AP58="VAT Inclusive",AP32*0.12,0)+AP32) -> 0 | AV37: =(IF(AV58="VAT Inclusive",AV32*0.12,0)+AV32) -> 0 | BB37: =(IF(BB58="VAT Inclusive",BB32*0.12,0)+BB32) -> 0 | BH37: =(IF(BH58="VAT Inclusive",BH32*0.12,0)+BH32) -> 0 | BN37: =(IF(BN58="VAT Inclusive",BN32*0.12,0)+BN32) -> 0 | BT37: =(IF(BT58="VAT Inclusive",BT32*0.12,0)+BT32) -> 0 | BZ37: =(IF(BZ58="VAT Inclusive",BZ32*0.12,0)+BZ32) -> 0 | CF37: =(IF(CF58="VAT Inclusive",CF32*0.12,0)+CF32) -> 0 | CL37: =(IF(CL58="VAT Inclusive",CL32*0.12,0)+CL32) -> 0
B38: =AP9 -> VENDOR 2 | C38: =SUMIF($M$11:$M$30,B38,$O$11:$O$30) -> 0 | D38: =COUNTIF($M$11:$M$30,B38) -> 0 | E38: =IFERROR(F38/(C38+F38),0) -> 0 | F38: =SUMIF($M$11:$M$30,B38,$AE$11:$AE$30) -> 0 | G38: =IFERROR(C38/$C$47,"") | H38: =IFERROR((SUMIFS($D$11:$D$30,$M$11:$M$30,$B38))/$D$32,"") | I38: =IFERROR($D38/$B$32,"") | J38: =IF(Reference!$A$13=HLOOKUP('Bid Tab (F&B Ops and CatMan) 10'!$B38,$AJ$50:$CQ$59,9,0),'Bid Tab (F&B Ops and CatMan) 10'!$C38*1.12,'Bid Tab (F&B Ops and CatMan) 10'!$C38) -> 0 | K38: =IF(AP52="","",HLOOKUP($B38,$AJ$50:$CQ$59,3,0)) | L38: =IF(AP53="","",HLOOKUP($B38,$AJ$50:$CQ$59,4,0)) | AI38: TOTAL COST OF ACQUISITION (for Ringi Amount, as applicable): | AJ38: =AJ35+AJ37 -> 0 | AP38: =AP35+AP37 -> 0 | AV38: =AV35+AV37 -> 0 | BB38: =BB35+BB37 -> 0 | BH38: =BH35+BH37 -> 0 | BN38: =BN35+BN37 -> 0 | BT38: =BT35+BT37 -> 0 | BZ38: =BZ35+BZ37 -> 0 | CF38: =CF35+CF37 -> 0 | CL38: =CL35+CL37 -> 0
B39: =AV9 -> VENDOR 3 | C39: =SUMIF($M$11:$M$30,B39,$O$11:$O$30) -> 0 | D39: =COUNTIF($M$11:$M$30,B39) -> 0 | E39: =IFERROR(F39/(C39+F39),0) -> 0 | F39: =SUMIF($M$11:$M$30,B39,$AE$11:$AE$30) -> 0 | G39: =IFERROR(C39/$C$47,"") | H39: =IFERROR((SUMIFS($D$11:$D$30,$M$11:$M$30,$B39))/$D$32,"") | I39: =IFERROR($D39/$B$32,"") | J39: =IF(Reference!$A$13=HLOOKUP('Bid Tab (F&B Ops and CatMan) 10'!$B39,$AJ$50:$CQ$59,9,0),'Bid Tab (F&B Ops and CatMan) 10'!$C39*1.12,'Bid Tab (F&B Ops and CatMan) 10'!$C39) -> 0 | K39: =IF(AV52="","",HLOOKUP($B39,$AJ$50:$CQ$59,3,0)) | L39: =IF(AV53="","",HLOOKUP($B39,$AJ$50:$CQ$59,4,0))
B40: =BB9 -> VENDOR 4 | C40: =SUMIF($M$11:$M$30,B40,$O$11:$O$30) -> 0 | D40: =COUNTIF($M$11:$M$30,B40) -> 0 | E40: =IFERROR(F40/(C40+F40),0) -> 0 | F40: =SUMIF($M$11:$M$30,B40,$AE$11:$AE$30) -> 0 | G40: =IFERROR(C40/$C$47,"") | H40: =IFERROR((SUMIFS($D$11:$D$30,$M$11:$M$30,$B40))/$D$32,"") | I40: =IFERROR($D40/$B$32,"") | J40: =IF(Reference!$A$13=HLOOKUP('Bid Tab (F&B Ops and CatMan) 10'!$B40,$AJ$50:$CQ$59,9,0),'Bid Tab (F&B Ops and CatMan) 10'!$C40*1.12,'Bid Tab (F&B Ops and CatMan) 10'!$C40) -> 0 | K40: =IF(BB52="","",HLOOKUP($B40,$AJ$50:$CQ$59,3,0)) | L40: =IF(BB53="","",HLOOKUP($B40,$AJ$50:$CQ$59,4,0)) | AJ40: =AJ9 -> VENDOR 1 | AP40: =AP9 -> VENDOR 2 | AV40: =AV9 -> VENDOR 3 | BB40: =BB9 -> VENDOR 4 | BH40: =BH9 -> VENDOR 5 | BN40: =BN9 -> VENDOR 6 | BT40: =BT9 -> VENDOR 7 | BZ40: =BZ9 -> VENDOR 8 | CF40: =CF9 -> VENDOR 9 | CL40: =CL9 -> VENDOR 10
B41: =BH9 -> VENDOR 5 | C41: =SUMIF($M$11:$M$30,B41,$O$11:$O$30) -> 0 | D41: =COUNTIF($M$11:$M$30,B41) -> 0 | E41: =IFERROR(F41/(C41+F41),0) -> 0 | F41: =SUMIF($M$11:$M$30,B41,$AE$11:$AE$30) -> 0 | G41: =IFERROR(C41/$C$47,"") | H41: =IFERROR((SUMIFS($D$11:$D$30,$M$11:$M$30,$B41))/$D$32,"") | I41: =IFERROR($D41/$B$32,"") | J41: =IF(Reference!$A$13=HLOOKUP('Bid Tab (F&B Ops and CatMan) 10'!$B41,$AJ$50:$CQ$59,9,0),'Bid Tab (F&B Ops and CatMan) 10'!$C41*1.12,'Bid Tab (F&B Ops and CatMan) 10'!$C41) -> 0 | K41: =IF(BH52="","",HLOOKUP($B41,$AJ$50:$CQ$59,3,0)) | L41: =IF(BH53="","",HLOOKUP($B41,$AJ$50:$CQ$59,4,0)) | AI41: BUSINESS SUPPORT / OTHER SAVINGS: | AJ41: DESCRIPTION | AM41: VALUE | AP41: DESCRIPTION | AS41: VALUE | AV41: DESCRIPTION | AY41: VALUE | BB41: DESCRIPTION | BE41: VALUE | BH41: DESCRIPTION | BK41: VALUE | BN41: DESCRIPTION | BQ41: VALUE | BT41: DESCRIPTION | BW41: VALUE | BZ41: DESCRIPTION | CC41: VALUE | CF41: DESCRIPTION | CI41: VALUE | CL41: DESCRIPTION | CO41: VALUE
B42: =BN9 -> VENDOR 6 | C42: =SUMIF($M$11:$M$30,B42,$O$11:$O$30) -> 0 | D42: =COUNTIF($M$11:$M$30,B42) -> 0 | E42: =IFERROR(F42/(C42+F42),0) -> 0 | F42: =SUMIF($M$11:$M$30,B42,$AE$11:$AE$30) -> 0 | G42: =IFERROR(C42/$C$47,"") | H42: =IFERROR((SUMIFS($D$11:$D$30,$M$11:$M$30,$B42))/$D$32,"") | I42: =IFERROR($D42/$B$32,"") | J42: =IF(Reference!$A$13=HLOOKUP('Bid Tab (F&B Ops and CatMan) 10'!$B42,$AJ$50:$CQ$59,9,0),'Bid Tab (F&B Ops and CatMan) 10'!$C42*1.12,'Bid Tab (F&B Ops and CatMan) 10'!$C42) -> 0 | K42: =IF(BN52="","",HLOOKUP($B42,$AJ$50:$CQ$59,3,0)) | L42: =IF(BN53="","",HLOOKUP($B42,$AJ$50:$CQ$59,4,0)) | AI42: BUSINESS / SERVICES SUPPORT
B43: =BT9 -> VENDOR 7 | C43: =SUMIF($M$11:$M$30,B43,$O$11:$O$30) -> 0 | D43: =COUNTIF($M$11:$M$30,B43) -> 0 | E43: =IFERROR(F43/(C43+F43),0) -> 0 | F43: =SUMIF($M$11:$M$30,B43,$AE$11:$AE$30) -> 0 | G43: =IFERROR(C43/$C$47,"") | H43: =IFERROR((SUMIFS($D$11:$D$30,$M$11:$M$30,$B43))/$D$32,"") | I43: =IFERROR($D43/$B$32,"") | J43: =IF(Reference!$A$13=HLOOKUP('Bid Tab (F&B Ops and CatMan) 10'!$B43,$AJ$50:$CQ$59,9,0),'Bid Tab (F&B Ops and CatMan) 10'!$C43*1.12,'Bid Tab (F&B Ops and CatMan) 10'!$C43) -> 0 | K43: =IF(BT52="","",HLOOKUP($B43,$AJ$50:$CQ$59,3,0)) | L43: =IF(BT53="","",HLOOKUP($B43,$AJ$50:$CQ$59,4,0)) | AI43: MARKETING / PRODUCT SUPPORT
B44: =BZ9 -> VENDOR 8 | C44: =SUMIF($M$11:$M$30,B44,$O$11:$O$30) -> 0 | D44: =COUNTIF($M$11:$M$30,B44) -> 0 | E44: =IFERROR(F44/(C44+F44),0) -> 0 | F44: =SUMIF($M$11:$M$30,B44,$AE$11:$AE$30) -> 0 | G44: =IFERROR(C44/$C$47,"") | H44: =IFERROR((SUMIFS($D$11:$D$30,$M$11:$M$30,$B44))/$D$32,"") | I44: =IFERROR($D44/$B$32,"") | J44: =IF(Reference!$A$13=HLOOKUP('Bid Tab (F&B Ops and CatMan) 10'!$B44,$AJ$50:$CQ$59,9,0),'Bid Tab (F&B Ops and CatMan) 10'!$C44*1.12,'Bid Tab (F&B Ops and CatMan) 10'!$C44) -> 0 | K44: =IF(BZ52="","",HLOOKUP($B44,$AJ$50:$CQ$59,3,0)) | L44: =IF(BZ53="","",HLOOKUP($B44,$AJ$50:$CQ$59,4,0)) | AI44: BUSINESS RECIPROCAL
B45: =CF9 -> VENDOR 9 | C45: =SUMIF($M$11:$M$30,B45,$O$11:$O$30) -> 0 | D45: =COUNTIF($M$11:$M$30,B45) -> 0 | E45: =IFERROR(F45/(C45+F45),0) -> 0 | F45: =SUMIF($M$11:$M$30,B45,$AE$11:$AE$30) -> 0 | G45: =IFERROR(C45/$C$47,"") | H45: =IFERROR((SUMIFS($D$11:$D$30,$M$11:$M$30,$B45))/$D$32,"") | I45: =IFERROR($D45/$B$32,"") | J45: =IF(Reference!$A$13=HLOOKUP('Bid Tab (F&B Ops and CatMan) 10'!$B45,$AJ$50:$CQ$59,9,0),'Bid Tab (F&B Ops and CatMan) 10'!$C45*1.12,'Bid Tab (F&B Ops and CatMan) 10'!$C45) -> 0 | K45: =IF(CF52="","",HLOOKUP($B45,$AJ$50:$CQ$59,3,0)) | L45: =IF(CF53="","",HLOOKUP($B45,$AJ$50:$CQ$59,4,0))
B46: =CL9 -> VENDOR 10 | C46: =SUMIF($M$11:$M$30,B46,$O$11:$O$30) -> 0 | D46: =COUNTIF($M$11:$M$30,B46) -> 0 | E46: =IFERROR(F46/(C46+F46),0) -> 0 | F46: =SUMIF($M$11:$M$30,B46,$AE$11:$AE$30) -> 0 | G46: =IFERROR(C46/$C$47,"") | H46: =IFERROR((SUMIFS($D$11:$D$30,$M$11:$M$30,$B46))/$D$32,"") | I46: =IFERROR($D46/$B$32,"") | J46: =IF(Reference!$A$13=HLOOKUP('Bid Tab (F&B Ops and CatMan) 10'!$B46,$AJ$50:$CQ$59,9,0),'Bid Tab (F&B Ops and CatMan) 10'!$C46*1.12,'Bid Tab (F&B Ops and CatMan) 10'!$C46) -> 0 | K46: =IF(CL52="","",HLOOKUP($B46,$AJ$50:$CQ$59,3,0)) | L46: =IF(CL53="","",HLOOKUP($B46,$AJ$50:$CQ$59,4,0))
B47: GRAND TOTAL | C47: =ROUNDUP(SUM(C37:C46),2) -> 0 | D47: =ROUNDUP(SUM(D37:D46),2) -> 0 | E47: =IFERROR(F47/C47+F47,0) -> 0 | F47: =SUM(F37:F46) -> 0 | G47: =SUM(G37:G46) -> 0 | H47: =SUM(H37:H46) -> 0 | I47: =SUM(I37:I46) -> 0 | J47: =SUM(J37:J46) -> 0
C48: =C47=O32 -> TRUE | D48: =D47=$B$32 -> TRUE | E48: =E47=$AE$33 -> TRUE | F48: =F47=$AE$32 -> TRUE | AI48: TOTAL OTHER SAVINGS | AJ48: =SUM(AM42:AO44) -> 0 | AP48: =SUM(AS42:AU44) -> 0 | AV48: =SUM(AY42:BA44) -> 0 | BB48: =SUM(BE42:BG44) -> 0 | BH48: =SUM(BK42:BM44) -> 0 | BN48: =SUM(BQ42:BS44) -> 0 | BT48: =SUM(BW42:BY44) -> 0 | BZ48: =SUM(CC42:CE44) -> 0 | CF48: =SUM(CI42:CK44) -> 0 | CL48: =SUM(CO42:CQ44) -> 0
AI50: TERMS AND CONDITIONS: | AJ50: =AJ9 -> VENDOR 1 | AP50: =AP9 -> VENDOR 2 | AV50: =AV9 -> VENDOR 3 | BB50: =BB9 -> VENDOR 4 | BH50: =BH9 -> VENDOR 5 | BN50: =BN9 -> VENDOR 6 | BT50: =BT9 -> VENDOR 7 | BZ50: =BZ9 -> VENDOR 8 | CF50: =CF9 -> VENDOR 9 | CL50: =CL9 -> VENDOR 10
B51: BID TURNOUT SUMMARY | C51: Total Quoted Amount (per Supplier) | D51: No. of SKUs | E51: % Amount | F51: % SKU | H51: PRICE REFERENCE | I51: Total Quoted Amount (per Supplier) | J51: No. of SKUs | K51: % Amount | L51: % SKU | AI51: BID EFFECTIVITY DATE:
B52: 1 | C52: =SUMIF($R$11:$R$30,B52,$O$11:$O$30) -> 0 | D52: =COUNTIF($R$11:$R$30,B52) -> 0 | E52: =IFERROR(C52/$C$56,"") | F52: =IFERROR(D52/$D$56,"") | H52: INITIAL LOWEST BID | I52: =SUMIF($AF$11:$AF$30,H52,$O$11:$O$30) -> 0 | J52: =COUNTIF($AF$11:$AF$30,H52) -> 0 | K52: =IFERROR(I52/$I$55,"") | L52: =IFERROR(J52/$J$55,"") | AI52: BID EXPIRY DATE:
B53: 2 | C53: =SUMIF($R$11:$R$30,B53,$O$11:$O$30) -> 0 | D53: =COUNTIF($R$11:$R$30,B53) -> 0 | E53: =IFERROR(C53/$C$56,"") | F53: =IFERROR(D53/$D$56,"") | H53: LAST SYSTEM PRICE | I53: =SUMIF($AF$11:$AF$30,H53,$O$11:$O$30) -> 0 | J53: =COUNTIF($AF$11:$AF$30,H53) -> 0 | K53: =IFERROR(I53/$I$55,"") | L53: =IFERROR(J53/$J$55,"") | AI53: DELIVERY LEAD TIME:
B54: 3 | C54: =SUMIF($R$11:$R$30,B54,$O$11:$O$30) -> 0 | D54: =COUNTIF($R$11:$R$30,B54) -> 0 | E54: =IFERROR(C54/$C$56,"") | F54: =IFERROR(D54/$D$56,"") | H54: PRICE EXTENSION | I54: =SUMIF($AF$11:$AF$30,H54,$O$11:$O$30) -> 0 | J54: =COUNTIF($AF$11:$AF$30,H54) -> 0 | K54: =IFERROR(I54/$I$55,"") | L54: =IFERROR(J54/$J$55,"") | AI54: PAYMENT TERMS
B55: 4 or more | C55: =SUMIF($R$11:$R$30,">="&4,$O$11:$O$30) -> 0 | D55: =COUNTIF($R$11:$R$30,">="&4) -> 0 | E55: =IFERROR(C55/$C$56,"") | F55: =IFERROR(D55/$D$56,"") | H55: GRAND TOTAL | I55: =ROUNDUP(SUM(I51:I54),2) -> 0 | J55: =SUM(J51:J54) -> 0 | K55: =SUM(K51:K54) -> 0 | L55: =SUM(L51:L54) -> 0 | AI55: WARRANTY
B56: GRAND TOTAL | C56: =ROUNDUP(SUM(C52:C55),2) -> 0 | D56: =SUM(D52:D55) -> 0 | E56: =SUM(E52:E55) -> 0 | F56: =SUM(F52:F55) -> 0 | I56: =I55=$C$47 -> TRUE | J56: =J55=$D$47 -> TRUE | AI56: INCOTERMS
C57: =C56=$C$47 -> TRUE | D57: =D56=$D$47 -> TRUE | H57: ADD. SPEND | I57: =SUM(I52:I53) -> 0 | J57: =SUM(J52:J53) -> 0 | K57: =IFERROR(I57/$I$55,"") | L57: =IFERROR(J57/$J$55,"") | AI57: BONDS & INSURANCES
AI58: VAT: | AJ58: VAT Inclusive | AP58: VAT Inclusive | AV58: VAT Inclusive
AI59: OTHER VENDOR NOTES:
B61: Recommendation: | C61: =CONCATENATE("Award to: ",IF(C37>0,B37,""),IF(C37>0,", ",""),IF(C38>0,B38,""),IF(C38>0,", ",""),IF(C39>0,B39,""),IF(C39>0,", ",""),IF(C40>0,B40,""),IF(C40>0,", ",""),IF(C41>0,B41,""),IF(C41>0,", ",""),IF(C42>0,B42,""),IF(C42>0,", ",""),IF(C43>0,B43,""),IF(C43>0,", ",""),IF(C44>0,B44,""),IF(C44>0,", ",""),IF(C45>0,B45,""),IF(C45>0,", ",""),IF(C46>0,B46,""),IF(C46>0,", ","")) -> Award to:
B64: Purpose of the Purchase:
B67: Remarks:
B85: Prepared by: | D85: Reviewed By: | I85: =IF(AND($J$47>100000,G91=FALSE,H91=FALSE),"Reviewed By:","") | L85: =IF($J$47>500000,"Noted By:","") | AB85: =IF($J$47>1000000,"Recommended By:","") | AI85: =IF(ISBLANK(AI91),"",AI91) | AL85: =IF(ISBLANK(AL$91),"",AL$91) | AO85: =IF(ISBLANK(AO$91),"",AO$91) | AR85: =IF(ISBLANK(AR$91),"",AR$91) | AU85: =IF(ISBLANK(AU$91),"",AU$91) | AX85: =IFERROR(HLOOKUP("Approved By",$AX$90:$BX$93,2,FALSE),"") | BA85: =IFERROR(HLOOKUP("Approved By",$AX$94:$BP$97,2,FALSE),"") | BD85: =IFERROR(HLOOKUP("Approved By",$AX$99:$AZ$101,1,FALSE),"")
D87: =IFERROR(VLOOKUP($B87,Reference!$G$2:$K$100,2,FALSE),"") | I87: =IFERROR(IF($J$47>=100001,VLOOKUP($B87,Reference!$G$2:$K$100,3,FALSE),""),"") | L87: =IFERROR(IF($J$47>=500001,VLOOKUP($B87,Reference!$G$2:$K$100,4,FALSE),""),"") | AB87: =IFERROR(IF($J$47>=1000001,VLOOKUP($B87,Reference!$G$2:$K$100,5,FALSE),""),"") | AI87: =IF(ISBLANK(AI93),"",AI$93) | AL87: =IF(ISBLANK(AL$93),"",AL$93) | AO87: =IF(ISBLANK(AO$93),"",AO$93) | AR87: =IF(ISBLANK(AR$93),"",AR$93) | AU87: =IF(ISBLANK(AU$93),"",AU$93) | AX87: =IFERROR(HLOOKUP("Approved By",$AX$90:$BX$93,4,FALSE),"") | BA87: =IFERROR(HLOOKUP("Approved By",$AX$94:$BP$97,4,FALSE),"") | BD87: =IFERROR(HLOOKUP("Approved By",$AX$99:$AZ$101,3,FALSE),"")
B88: Project Lead | D88: =IFERROR(VLOOKUP(D87,Reference!$M$2:$N$100,2,0),"") | I88: =IFERROR(VLOOKUP(I87,Reference!$M$2:$N$100,2,0),"") | L88: =IFERROR(VLOOKUP($L87,Reference!$M:$N,2,0),"") | AB88: =IFERROR(VLOOKUP($AB87,Reference!$M:$N,2,0),"") | AI88: =IFERROR(VLOOKUP(AI87,Approvers!$AJ$2:$AK$106,2,FALSE),"") | AL88: =IFERROR(VLOOKUP(AL87,Approvers!$AJ$2:$AK$106,2,FALSE),"") | AO88: =IFERROR(VLOOKUP(AO87,Approvers!$AJ$2:$AK$106,2,FALSE),"") | AR88: =IFERROR(VLOOKUP(AR87,Approvers!$AJ$2:$AK$106,2,FALSE),"") | AU88: =IFERROR(VLOOKUP(AU87,Approvers!$AJ$2:$AK$106,2,FALSE),"") | AX88: =IFERROR(VLOOKUP(AX87,Approvers!$AJ$2:$AK$106,2,FALSE),"") | BA88: =IFERROR(VLOOKUP(BA87,Approvers!$AJ$2:$AK$106,2,FALSE),"") | BD88: =IFERROR(VLOOKUP(BD87,Approvers!$AJ$2:$AK$106,2,FALSE),"")
AX90: =TEXT(AX91,) | AZ90: =TEXT(AZ91,) | BB90: =TEXT(BB91,) | BD90: =TEXT(BD91,) | BF90: =TEXT(BF91,) | BH90: =TEXT(BH91,) | BJ90: =TEXT(BJ91,) | BL90: =TEXT(BL91,) | BN90: =TEXT(BN91,) | BP90: =TEXT(BP91,) | BR90: =TEXT(BR91,) | BT90: =TEXT(BT91,) | BV90: =TEXT(BV91,) | BX90: =TEXT(BX91,)
G91: =D87=I87 -> TRUE | H91: =I87="" -> TRUE | AI91: =IFERROR(VLOOKUP(Approvers!$AH$1,Approvers!$I:$L,3,FALSE),"") | AL91: =IFERROR(VLOOKUP(Approvers!$AH$1,Approvers!$I:$N,5,FALSE),"") | AO91: =IFERROR(VLOOKUP(Approvers!$AH$1,Approvers!$I:$P,7,FALSE),"") | AR91: =IFERROR(VLOOKUP(Approvers!$AH$1,Approvers!$I:$T,9,FALSE),"") | AU91: =IFERROR(VLOOKUP(Approvers!$AH$1,Approvers!$I:$T,11,FALSE),"") | AX91: =IFERROR(IF(AND($AR$93=VLOOKUP($AR$93,Approvers!R172:R183,1,FALSE),'Bid Tab (F&B Ops and CatMan) 10'!$J47>9999),"Approved By",""),"") | AZ91: =IFERROR(IF(AND($AR$93=VLOOKUP($AR$93,Approvers!R57:R59,1,FALSE),'Bid Tab (F&B Ops and CatMan) 10'!$J47>14999),"Approved By",""),"") | BB91: =IFERROR(IF(AND($AR$93=VLOOKUP($AR$93,Approvers!R62:R84,1,FALSE),'Bid Tab (F&B Ops and CatMan) 10'!$J47>24999),"Approved By",""),"") | BD91: =IFERROR(IF(AND($AR$93=VLOOKUP($AR$93,Approvers!R37:R39,1,FALSE),'Bid Tab (F&B Ops and CatMan) 10'!$J47>49999),"Approved By",""),"") | BF91: =IFERROR(IF(AND($AR$93=VLOOKUP($AR$93,Approvers!$R$34,1,FALSE),'Bid Tab (F&B Ops and CatMan) 10'!$J47>999999,Approvers!$I$34=Approvers!$AH$1),"Approved By",""),"") | BH91: =IFERROR(IF(AND($AR$93=VLOOKUP($AR$93,Approvers!$R$34,1,FALSE),'Bid Tab (F&B Ops and CatMan) 10'!$J47>999999,Approvers!$AH$1=Approvers!$I$35),"Approved By",""),"") | BJ91: =IFERROR(IF(AND($AR$93=VLOOKUP($AR$93,Approvers!$R$28:$R$33,1,FALSE),'Bid Tab (F&B Ops and CatMan) 10'!$J47>4999999),"Approved By",""),"") | BL91: =IFERROR(IF(AND($AR$93=VLOOKUP($AR$93,Approvers!$R$40,1,FALSE),'Bid Tab (F&B Ops and CatMan) 10'!$J47>4999999),"Approved By",""),"") | BN91: =IFERROR(IF(AND($AR$93=VLOOKUP($AR$93,Approvers!$R$42:$R$44,1,FALSE),'Bid Tab (F&B Ops and CatMan) 10'!$J47>4999999),"Approved By",""),"") | BP91: =IFERROR(IF(AND($AR$93=VLOOKUP($AR$93,Approvers!$R$45,1,FALSE),'Bid Tab (F&B Ops and CatMan) 10'!$J47>4999999),"Approved By",""),"") | BR91: =IFERROR(IF(AND($AR$93=VLOOKUP($AR$93,Approvers!$R$47,1,FALSE),'Bid Tab (F&B Ops and CatMan) 10'!$J47>4999999),"Approved By",""),"") | BT91: =IFERROR(IF(AND($AR$93=VLOOKUP($AR$93,Approvers!$R$48,1,FALSE),'Bid Tab (F&B Ops and CatMan) 10'!$J47>4999999),"Approved By",""),"") | BV91: =IFERROR(IF(AND($AR$93=VLOOKUP($AR$93,Approvers!$R$54:$R$56,1,FALSE),'Bid Tab (F&B Ops and CatMan) 10'!$J47>4999999),"Approved By",""),"") | BX91: =IFERROR(IF(AND($AU$93=VLOOKUP($AU$93,Approvers!$T$128:$T$130,1,FALSE)),"Approved By",""),"")
G93: =IF($J$47>=100001,VLOOKUP($B87,Reference!$G$2:$K$53,3,FALSE),"") | AI93: =IFERROR(VLOOKUP(Approvers!$AH$1,Approvers!$I:$L,4,FALSE),"") | AL93: =IFERROR(VLOOKUP(Approvers!$AH$1,Approvers!$I:$N,6,FALSE),"") | AO93: =IFERROR(VLOOKUP(Approvers!$AH$1,Approvers!$I:$P,8,FALSE),"") | AR93: =IFERROR(VLOOKUP(Approvers!$AH$1,Approvers!$I:$T,10,FALSE),"") | AU93: =IFERROR(VLOOKUP(Approvers!$AH$1,Approvers!$I:$T,12,FALSE),"") | AX93: =IFERROR(IF(AND($AR$93=VLOOKUP($AR$93,Approvers!R172:R183,1,FALSE),'Bid Tab (F&B Ops and CatMan) 10'!$J47>9999),Approvers!$U$172,""),"") | AZ93: =IFERROR(IF(AND($AR$93=VLOOKUP($AR$93,Approvers!R57:R59,1,FALSE),'Bid Tab (F&B Ops and CatMan) 10'!$J47>14999),Approvers!$V$57,""),"") | BB93: =IFERROR(IF(AND($AR$93=VLOOKUP($AR$93,Approvers!R62:R84,1,FALSE),'Bid Tab (F&B Ops and CatMan) 10'!$J47>24999),Approvers!$W$62,""),"") | BD93: =IFERROR(IF(AND($AR$93=VLOOKUP($AR$93,Approvers!R37:R39,1,FALSE),'Bid Tab (F&B Ops and CatMan) 10'!$J47>49999),Approvers!$X$37,""),"") | BF93: =IFERROR(IF(AND($AR$93=VLOOKUP($AR$93,Approvers!$R$34,1,FALSE),'Bid Tab (F&B Ops and CatMan) 10'!$J47>999999,Approvers!$I$34=Approvers!$AH$1),Approvers!$Y$34,""),"") | BH93: =IFERROR(IF(AND($AR$93=VLOOKUP($AR$93,Approvers!$R$34,1,FALSE),'Bid Tab (F&B Ops and CatMan) 10'!$J47>999999,Approvers!$AH$1=Approvers!$I$35),Approvers!$Y$35,""),"") | BJ93: =IFERROR(IF(AND($AR$93=VLOOKUP($AR$93,Approvers!$R$28:$R$33,1,FALSE),'Bid Tab (F&B Ops and CatMan) 10'!$J47>4999999),Approvers!$Z$28,""),"") | BL93: =IFERROR(IF(AND($AR$93=VLOOKUP($AR$93,Approvers!$R$40,1,FALSE),'Bid Tab (F&B Ops and CatMan) 10'!$J47>4999999),Approvers!$Z$40,""),"") | BN93: =IFERROR(IF(AND($AR$93=VLOOKUP($AR$93,Approvers!$R$42:$R$44,1,FALSE),'Bid Tab (F&B Ops and CatMan) 10'!$J47>4999999),Approvers!$Z$42,""),"") | BP93: =IFERROR(IF(AND($AR$93=VLOOKUP($AR$93,Approvers!$R$45,1,FALSE),'Bid Tab (F&B Ops and CatMan) 10'!$J47>4999999),Approvers!$Z$45,""),"") | BR93: =IFERROR(IF(AND($AR$93=VLOOKUP($AR$93,Approvers!$R$47,1,FALSE),'Bid Tab (F&B Ops and CatMan) 10'!$J47>4999999),Approvers!$Z$47,""),"") | BT93: =IFERROR(IF(AND($AR$93=VLOOKUP($AR$93,Approvers!$R$48,1,FALSE),'Bid Tab (F&B Ops and CatMan) 10'!$J47>4999999),Approvers!$Z$48,""),"") | BV93: =IFERROR(IF(AND($AR$93=VLOOKUP($AR$93,Approvers!$R$54:$R$56,1,FALSE),'Bid Tab (F&B Ops and CatMan) 10'!$J47>4999999),Approvers!$Z$54,""),"") | BX93: =IFERROR(IF(AND($AU$93=VLOOKUP($AU$93,Approvers!$T$128:$T$130,1,FALSE)),"Andreas Balla",""),"")
AX94: =TEXT(AX95,) | AZ94: =TEXT(AZ95,) | BB94: =TEXT(BB95,) | BD94: =TEXT(BD95,) | BF94: =TEXT(BF95,) | BH94: =TEXT(BH95,)
AX95: =IFERROR(IF(AND($AR$93=VLOOKUP($AR$93,Approvers!$R$28:$R$33,1,FALSE),'Bid Tab (F&B Ops and CatMan) 10'!$J47>9999999),"Approved By",""),"") | AZ95: =IFERROR(IF(AND($AR$93=VLOOKUP($AR$93,Approvers!$R$40:$R$44,1,FALSE),'Bid Tab (F&B Ops and CatMan) 10'!$J47>9999999),"Approved By",""),"") | BB95: =IFERROR(IF(AND($AR$93=VLOOKUP($AR$93,Approvers!$R$45:$R$47,1,FALSE),'Bid Tab (F&B Ops and CatMan) 10'!$J47>9999999),"Approved By",""),"") | BD95: =IFERROR(IF(AND($AR$93=VLOOKUP($AR$93,Approvers!$R$49,1,FALSE),'Bid Tab (F&B Ops and CatMan) 10'!$J47>9999999),"Approved By",""),"") | BF95: =IFERROR(IF(AND($AR$93=VLOOKUP($AR$93,Approvers!$R$54:$R$56,1,FALSE),'Bid Tab (F&B Ops and CatMan) 10'!$J47>9999999),"Approved By",""),"") | BH95: =IFERROR(IF(AND($AR$93=VLOOKUP($AR$93,Approvers!$R$162:$R$164,1,FALSE),'Bid Tab (F&B Ops and CatMan) 10'!$J47>9999999),"Approved By",""),"")
AX96: =TEXT(AX95,) | AZ96: =TEXT(AZ95,) | BB96: =TEXT(BB95,) | BD96: =TEXT(BD95,) | BF96: =TEXT(BF95,) | BH96: =TEXT(BH95,)
AX97: =IFERROR(IF(AND($AR$93=VLOOKUP($AR$93,Approvers!$R$28:$R$33,1,FALSE),'Bid Tab (F&B Ops and CatMan) 10'!$J47>9999999),Approvers!$AA$28,""),"") | AZ97: =IFERROR(IF(AND($AR$93=VLOOKUP($AR$93,Approvers!$R$40:$R$44,1,FALSE),'Bid Tab (F&B Ops and CatMan) 10'!$J47>9999999),Approvers!$AA$40,""),"") | BB97: =IFERROR(IF(AND($AR$93=VLOOKUP($AR$93,Approvers!$R$45:$R$47,1,FALSE),'Bid Tab (F&B Ops and CatMan) 10'!$J47>9999999),Approvers!$AA$45,""),"") | BD97: =IFERROR(IF(AND($AR$93=VLOOKUP($AR$93,Approvers!$R$49,1,FALSE),'Bid Tab (F&B Ops and CatMan) 10'!$J47>9999999),Approvers!$AA$49,""),"") | BF97: =IFERROR(IF(AND($AR$93=VLOOKUP($AR$93,Approvers!$R$54:$R$56,1,FALSE),'Bid Tab (F&B Ops and CatMan) 10'!$J47>9999999),Approvers!$AA$54,""),"") | BH97: =IFERROR(IF(AND($AR$93=VLOOKUP($AR$93,Approvers!$R$162:$R$164,1,FALSE),'Bid Tab (F&B Ops and CatMan) 10'!$J47>9999999),Approvers!$AA$162,""),"")
AX99: =IFERROR(IF(AND($AR$93=VLOOKUP($AR$93,Approvers!$R$49:$R$49,1,FALSE),'Bid Tab (F&B Ops and CatMan) 10'!$J47>14999999),"Approved By",""),"") | AZ99: =IFERROR(IF(AND($AR$93=VLOOKUP($AR$93,Approvers!$R$34:$R$36,1,FALSE),'Bid Tab (F&B Ops and CatMan) 10'!$J47>19999999),"Approved By",""),"")
AX101: =IFERROR(IF(AND($AR$93=VLOOKUP($AR$93,Approvers!$R$49:$R$49,1,FALSE),'Bid Tab (F&B Ops and CatMan) 10'!$J47>14999999),Approvers!$AB$49,""),"") | AZ101: =IFERROR(IF(AND($AR$93=VLOOKUP($AR$93,Approvers!$R$34:$R$36,1,FALSE),'Bid Tab (F&B Ops and CatMan) 10'!$J47>19999999),Approvers!$AC$34,""),"")

Sheet Header
C9: ='Bid Tab (F&B Ops and CatMan) 10'!B36 -> AWARD SUMMARY | D9: ='Bid Tab (F&B Ops and CatMan) 10'!C36 -> GRAND TOTAL (EXCLUSIVE OF VAT) | E9: ='Bid Tab (F&B Ops and CatMan) 10'!D36 -> Item Count | F9: ='Bid Tab (F&B Ops and CatMan) 10'!E36 -> % Savings | G9: ='Bid Tab (F&B Ops and CatMan) 10'!F36 -> Procurement Savings | H9: ='Bid Tab (F&B Ops and CatMan) 10'!G36 -> % Award Share by Amount | I9: ='Bid Tab (F&B Ops and CatMan) 10'!H36 -> % Award Share by Volume | J9: ='Bid Tab (F&B Ops and CatMan) 10'!I36 -> % Award Share by SKU | ... N9: ='Bid Tab (F&B Ops and CatMan) 10'!M36 -> EXECUTION
C10: ='Bid Tab (F&B Ops and CatMan) 10'!B37 -> VENDOR 1 | D10: ='Bid Tab (F&B Ops and CatMan) 10'!C37 -> 0 | E10: ='Bid Tab (F&B Ops and CatMan) 10'!D37 -> 0 | F10: ='Bid Tab (F&B Ops and CatMan) 10'!E37 -> 0 | G10: ='Bid Tab (F&B Ops and CatMan) 10'!F37 -> 0 | H10: ='Bid Tab (F&B Ops and CatMan) 10'!G37 | I10: ='Bid Tab (F&B Ops and CatMan) 10'!H37 | J10: ='Bid Tab (F&B Ops and CatMan) 10'!I37 | ... N10: ='Bid Tab (F&B Ops and CatMan) 10'!M37 -> 0
C11: ='Bid Tab (F&B Ops and CatMan) 10'!B38 -> VENDOR 2 | D11: ='Bid Tab (F&B Ops and CatMan) 10'!C38 -> 0 | E11: ='Bid Tab (F&B Ops and CatMan) 10'!D38 -> 0 | F11: ='Bid Tab (F&B Ops and CatMan) 10'!E38 -> 0 | G11: ='Bid Tab (F&B Ops and CatMan) 10'!F38 -> 0 | H11: ='Bid Tab (F&B Ops and CatMan) 10'!G38 | I11: ='Bid Tab (F&B Ops and CatMan) 10'!H38 | J11: ='Bid Tab (F&B Ops and CatMan) 10'!I38 | ... N11: ='Bid Tab (F&B Ops and CatMan) 10'!M38 -> 0
C12: ='Bid Tab (F&B Ops and CatMan) 10'!B39 -> VENDOR 3 | D12: ='Bid Tab (F&B Ops and CatMan) 10'!C39 -> 0 | E12: ='Bid Tab (F&B Ops and CatMan) 10'!D39 -> 0 | F12: ='Bid Tab (F&B Ops and CatMan) 10'!E39 -> 0 | G12: ='Bid Tab (F&B Ops and CatMan) 10'!F39 -> 0 | H12: ='Bid Tab (F&B Ops and CatMan) 10'!G39 | I12: ='Bid Tab (F&B Ops and CatMan) 10'!H39 | J12: ='Bid Tab (F&B Ops and CatMan) 10'!I39 | ... N12: ='Bid Tab (F&B Ops and CatMan) 10'!M39 -> 0
C13: ='Bid Tab (F&B Ops and CatMan) 10'!B40 -> VENDOR 4 | D13: ='Bid Tab (F&B Ops and CatMan) 10'!C40 -> 0 | E13: ='Bid Tab (F&B Ops and CatMan) 10'!D40 -> 0 | F13: ='Bid Tab (F&B Ops and CatMan) 10'!E40 -> 0 | G13: ='Bid Tab (F&B Ops and CatMan) 10'!F40 -> 0 | H13: ='Bid Tab (F&B Ops and CatMan) 10'!G40 | I13: ='Bid Tab (F&B Ops and CatMan) 10'!H40 | J13: ='Bid Tab (F&B Ops and CatMan) 10'!I40 | ... N13: ='Bid Tab (F&B Ops and CatMan) 10'!M40 -> 0
C14: ='Bid Tab (F&B Ops and CatMan) 10'!B41 -> VENDOR 5 | D14: ='Bid Tab (F&B Ops and CatMan) 10'!C41 -> 0 | E14: ='Bid Tab (F&B Ops and CatMan) 10'!D41 -> 0 | F14: ='Bid Tab (F&B Ops and CatMan) 10'!E41 -> 0 | G14: ='Bid Tab (F&B Ops and CatMan) 10'!F41 -> 0 | H14: ='Bid Tab (F&B Ops and CatMan) 10'!G41 | I14: ='Bid Tab (F&B Ops and CatMan) 10'!H41 | J14: ='Bid Tab (F&B Ops and CatMan) 10'!I41 | ... N14: ='Bid Tab (F&B Ops and CatMan) 10'!M41 -> 0
C15: ='Bid Tab (F&B Ops and CatMan) 10'!B42 -> VENDOR 6 | D15: ='Bid Tab (F&B Ops and CatMan) 10'!C42 -> 0 | E15: ='Bid Tab (F&B Ops and CatMan) 10'!D42 -> 0 | F15: ='Bid Tab (F&B Ops and CatMan) 10'!E42 -> 0 | G15: ='Bid Tab (F&B Ops and CatMan) 10'!F42 -> 0 | H15: ='Bid Tab (F&B Ops and CatMan) 10'!G42 | I15: ='Bid Tab (F&B Ops and CatMan) 10'!H42 | J15: ='Bid Tab (F&B Ops and CatMan) 10'!I42 | ... N15: ='Bid Tab (F&B Ops and CatMan) 10'!M42 -> 0
C16: ='Bid Tab (F&B Ops and CatMan) 10'!B43 -> VENDOR 7 | D16: ='Bid Tab (F&B Ops and CatMan) 10'!C43 -> 0 | E16: ='Bid Tab (F&B Ops and CatMan) 10'!D43 -> 0 | F16: ='Bid Tab (F&B Ops and CatMan) 10'!E43 -> 0 | G16: ='Bid Tab (F&B Ops and CatMan) 10'!F43 -> 0 | H16: ='Bid Tab (F&B Ops and CatMan) 10'!G43 | I16: ='Bid Tab (F&B Ops and CatMan) 10'!H43 | J16: ='Bid Tab (F&B Ops and CatMan) 10'!I43 | ... N16: ='Bid Tab (F&B Ops and CatMan) 10'!M43 -> 0
C17: ='Bid Tab (F&B Ops and CatMan) 10'!B44 -> VENDOR 8 | D17: ='Bid Tab (F&B Ops and CatMan) 10'!C44 -> 0 | E17: ='Bid Tab (F&B Ops and CatMan) 10'!D44 -> 0 | F17: ='Bid Tab (F&B Ops and CatMan) 10'!E44 -> 0 | G17: ='Bid Tab (F&B Ops and CatMan) 10'!F44 -> 0 | H17: ='Bid Tab (F&B Ops and CatMan) 10'!G44 | I17: ='Bid Tab (F&B Ops and CatMan) 10'!H44 | J17: ='Bid Tab (F&B Ops and CatMan) 10'!I44 | ... N17: ='Bid Tab (F&B Ops and CatMan) 10'!M44 -> 0
C18: ='Bid Tab (F&B Ops and CatMan) 10'!B45 -> VENDOR 9 | D18: ='Bid Tab (F&B Ops and CatMan) 10'!C45 -> 0 | E18: ='Bid Tab (F&B Ops and CatMan) 10'!D45 -> 0 | F18: ='Bid Tab (F&B Ops and CatMan) 10'!E45 -> 0 | G18: ='Bid Tab (F&B Ops and CatMan) 10'!F45 -> 0 | H18: ='Bid Tab (F&B Ops and CatMan) 10'!G45 | I18: ='Bid Tab (F&B Ops and CatMan) 10'!H45 | J18: ='Bid Tab (F&B Ops and CatMan) 10'!I45 | ... N18: ='Bid Tab (F&B Ops and CatMan) 10'!M45 -> 0
C19: ='Bid Tab (F&B Ops and CatMan) 10'!B46 -> VENDOR 10 | D19: ='Bid Tab (F&B Ops and CatMan) 10'!C46 -> 0 | E19: ='Bid Tab (F&B Ops and CatMan) 10'!D46 -> 0 | F19: ='Bid Tab (F&B Ops and CatMan) 10'!E46 -> 0 | G19: ='Bid Tab (F&B Ops and CatMan) 10'!F46 -> 0 | H19: ='Bid Tab (F&B Ops and CatMan) 10'!G46 | I19: ='Bid Tab (F&B Ops and CatMan) 10'!H46 | J19: ='Bid Tab (F&B Ops and CatMan) 10'!I46 | ... N19: ='Bid Tab (F&B Ops and CatMan) 10'!M46 -> 0
C20: ='Bid Tab (F&B Ops and CatMan) 10'!B47 -> GRAND TOTAL | D20: ='Bid Tab (F&B Ops and CatMan) 10'!C47 -> 0 | E20: ='Bid Tab (F&B Ops and CatMan) 10'!D47 -> 0 | F20: ='Bid Tab (F&B Ops and CatMan) 10'!E47 -> 0 | G20: ='Bid Tab (F&B Ops and CatMan) 10'!F47 -> 0 | H20: ='Bid Tab (F&B Ops and CatMan) 10'!G47 -> 0 | I20: ='Bid Tab (F&B Ops and CatMan) 10'!H47 -> 0 | J20: ='Bid Tab (F&B Ops and CatMan) 10'!I47 -> 0 | K20: ='Bid Tab (F&B Ops and CatMan) 10'!J47 -> 0
D23: Recommendation: | E23: ='Bid Tab (F&B Ops and CatMan) 10'!C61 -> Award to:
D25: Purpose of the Purchase: | E25: ='Bid Tab (F&B Ops and CatMan) 10'!$C$64 -> 0
D27: Remarks:

Sheet Approvers
A1: DIVISION | B1: DEPARTMENT | C1: COST CENTER | E1: DIVISION CODE | F1: DIVISION | G1: DEPARTMENT CODE | H1: DEPARTMENT | I1: COST CENTER CODE | J1: COST CENTER | K1: NOTED BY | L1: NOTED BY | M1: REVIEWED BY | N1: REVIEWED BY | O1: ENDORSED BY | P1: ENDORSED BY | Q1: Approved By | R1: APPROVER1 | S1: Approved By | T1: APPROVER2 | U1: >=100001 | V1: >=150000 | W1: >=250000 | X1: >=500001 | Y1: >=1000001 | Z1: >=5000001 | AA1: >=10000001 | AB1: >=15000001 | AC1: >=20000001 | AF1: =INDEX($E:$E,MATCH('Bid Tab (F&B Ops and CatMan) 10'!$I$4,Approvers!$F:$F,0)) -> #N/A | AH1: =INDEX($I:$I,MATCH('Bid Tab (F&B Ops and CatMan) 10'!$I$5,Approvers!$J:$J,0)) -> #N/A | AJ1: APPROVERS | AK1: POSITION
A2: *MULTI - DIVISION | B2: *MULTI - DIVISION | C2: *MULTI - DIVISION | E2: MULTI___BU | F2: MULTI - DIVISION | G2: MULTI___BU | H2: MULTI - DIVISION | I2: MULTI___BU | J2: MULTI - DIVISION | AJ2: Abegail Fulla | AK2: Assistant Vice President - Accounting
A3: Inventory | B3: 100 - FOOD INVENTORY | C3: [PD] Administration | E3: _01_ | F3: Inventory | G3: 100_ | H3: 100 - FOOD INVENTORY | I3: 100 | J3: FOOD INVENTORY | Q3: Approved By | R3: Jowel Benoza | Y3: Ricardo Aguas Jr. | AJ3: Alan Jacalne | AK3: Director - Table Games
A4: Accounting | B4: 1100 - TOBACCO | C4: [SES] Administration | E4: _01_ | F4: Inventory | G4: 1100_ | H4: 1100 - TOBACCO | I4: 1100 | J4: TOBACCO | Q4: Approved By | R4: Jowel Benoza | Y4: Ricardo Aguas Jr. | AJ4: Alan Teoh | AK4: Assistant Vice President - Gaming Technical Services
A5: AML and Casino Regulatory Compliance | B5: 150 - GLACIER FOOD INVENTORY | C5: Accounts Payable | E5: _01_ | F5: Inventory | G5: 150_ | H5: 150 - GLACIER FOOD INVENTORY | I5: 150 | J5: GLACIER FOOD INVENTORY | Q5: Approved By | R5: Jowel Benoza | Y5: Ricardo Aguas Jr. | AJ5: Alda Madrid | AK5: Director of Housekeeping - Rooms
A6: Business Solutions | B6: 200 - BEVERAGE INVENTORY (ALCOHOLIC) | C6: Accounts Receivable | E6: _01_ | F6: Inventory | G6: 200_ | H6: 200 - BEVERAGE INVENTORY (ALCOHOLIC) | I6: 200 | J6: BEVERAGE INVENTORY (ALCOHOLIC) | Q6: Approved By | R6: Jowel Benoza | Y6: Ricardo Aguas Jr. | AJ6: Alexandrea Herrera | AK6: Director of Sales & Marketing
A7: Cage, Count and Credit | B7: 201 - BEVERAGE INVENTORY (NON-ALCOHOLIC) | C7: Administration & Project Management | E7: _01_ | F7: Inventory | G7: 201_ | H7: 201 - BEVERAGE INVENTORY (NON-ALCOHOLIC) | I7: 201 | J7: BEVERAGE INVENTORY (NON-ALCOHOLIC) | Q7: Approved By | R7: Jowel Benoza | Y7: Ricardo Aguas Jr. | AJ7: Allan Lescano | AK7: Director - Program Management Office
A8: Construction & Design | B8: 250 - GLACIER BEVERAGE INVENTORY | C8: Administration and Training | E8: _01_ | F8: Inventory | G8: 250_ | H8: 250 - GLACIER BEVERAGE INVENTORY | I8: 250 | J8: GLACIER BEVERAGE INVENTORY | Q8: Approved By | R8: Jowel Benoza | Y8: Ricardo Aguas Jr. | AJ8: Alvaro Ramos | AK8: Assistant Vice President - Retail
A9: Corporate Finance | B9: 300 - WINE | C9: Airport Lounge | E9: _01_ | F9: Inventory | G9: 300_ | H9: 300 - WINE | I9: 300 | J9: WINE | Q9: Approved By | R9: Jowel Benoza | Y9: Ricardo Aguas Jr. | AJ9: Andreas Balla | AK9: Vice President - Food & Beverage
A10: Corporate Marketing & Communications | B10: 350 - GLACIER WINE INVENTORY | C10: AML Compliance | E10: _01_ | F10: Inventory | G10: 350_ | H10: 350 - GLACIER WINE INVENTORY | I10: 350 | J10: GLACIER WINE INVENTORY | Q10: Approved By | R10: Jowel Benoza | Y10: Ricardo Aguas Jr. | AJ10: Anthony Santos | AK10: Manager - SQEW
A11: Corporate Planning | B11: 400 - CHILLER | C11: Analytics | E11: _01_ | F11: Inventory | G11: 400_ | H11: 400 - CHILLER | I11: 400 | J11: CHILLER | Q11: Approved By | R11: Jowel Benoza | Y11: Ricardo Aguas Jr. | AJ11: Anthony Veloso | AK11: Assistant Director - Customer Relation Management
A12: Electronic Gaming | B12: 450 - GLACIER CHILLER INVENTORY | C12: Anime World Backlot Tour | E12: _01_ | F12: Inventory | G12: 450_ | H12: 450 - GLACIER CHILLER INVENTORY | I12: 450 | J12: GLACIER CHILLER INVENTORY | Q12: Approved By | R12: Jowel Benoza | Y12: Ricardo Aguas Jr. | AJ12: Ashley Chen | AK12: Director - International Marketing
A13: Facility Management | B13: 500 - FREEZER | C13: Art Aquarium | E13: _01_ | F13: Inventory | G13: 500_ | H13: 500 - FREEZER | I13: 500 | J13: FREEZER | Q13: Approved By | R13: Jowel Benoza | Y13: Ricardo Aguas Jr. | AJ13: Bethoven Nalo | AK13: Director - Housekeeping - Public Area
A14: Food and Beverage | B14: 550 - GLACIER FROZEN INVENTORY | C14: AVL Animation | E14: _01_ | F14: Inventory | G14: 550_ | H14: 550 - GLACIER FROZEN INVENTORY | I14: 550 | J14: GLACIER FROZEN INVENTORY | Q14: Approved By | R14: Jowel Benoza | Y14: Ricardo Aguas Jr. | AJ14: Chong Yao Tan | AK14: Associate Director - Support Services
... A18: Information Technology | B18: 950 - MEDICAL AND EMERGENCY PPE’s INVENTORY | C18: Banquets | E18: _01_ | F18: Inventory | G18: 950_ | H18: 950 - MEDICAL AND EMERGENCY PPE’s INVENTORY | I18: 950 | J18: MEDICAL AND EMERGENCY PPE’s INVENTORY | Q18: Approved By | R18: Jowel Benoza | Y18: Ricardo Aguas Jr. | AJ18: Diana Wu | AK18: Director - Gaming OS&E Control
A19: Internal Audit | B19: Administration | C19: Barbeque Kitchen | E19: _01_ | F19: Inventory | G19: R700_ | H19: R700 - GIFT SHOP INVENTORY | I19: R700 | J19: GIFT SHOP INVENTORY | Q19: Approved By | R19: Alvaro Ramos | AJ19: Edward John Sta. Maria | AK19: Associate Director - Security & Compliance
A20: Legal & Compliance | B20: Administration & Finance | C20: Beach Club | E20: AM110000_ | F20: AML and Casino Regulatory Compliance | G20: AM110100_ | H20: AML Compliance | I20: AM110101 | J20: AML Compliance | Q20: Approved By | R20: Han Tee Yap | AJ20: Eunice Villaluz | AK20: Assistant Director - Transportation
A21: Premium Dining | B21: Administration and Training | C21: BEVERAGE INVENTORY (ALCOHOLIC) | E21: AM110000_ | F21: AML and Casino Regulatory Compliance | G21: AM110100_ | H21: Casino Regulatory Compliance | I21: AM110201 | J21: Casino Regulatory Compliance | Q21: Approved By | R21: Han Tee Yap | AJ21: Faustino Mercado | AK21: Assistant Director of Events
A22: Premium Marketing | B22: AML Compliance | C22: BEVERAGE INVENTORY (NON-ALCOHOLIC) | E22: CP110000_ | F22: Corporate Planning | G22: CP110100_ | H22: Corporate Management & Administration | I22: CP110101 | J22: Corporate Management & Administration | Q22: Approved By | R22: Kentaro Amamoto | AJ22: Federico Manalo | AK22: Senior Manager - Project Management
A23: Retail | B23: Analytics | C23: Beverage Production | E23: CP110000_ | F23: Corporate Planning | G23: CP110400_ | H23: Internal Control | I23: CP110401 | J23: Internal Control | Q23: Approved By | R23: Kentaro Amamoto | AJ23: Fenalyn Reyes | AK23: Director - Human Resources
A24: Security & Safety | B24: AVL Technology | C24: Brand and Product Marketing | E24: CP110000_ | F24: Corporate Planning | G24: CP110500_ | H24: Strategic Planning | I24: CP110501 | J24: Strategic Planning | Q24: Approved By | R24: Kentaro Amamoto | AJ24: Francisco Varca | AK24: Vice President - Table Games
A25: Strategic Marketing | B25: Brand and Product Marketing | C25: Business Insight and Research | E25: CT110000_ | F25: Construction & Design | G25: CT110100_ | H25: Technical Assurance | I25: CT110101 | J25: Technical Assurance | Q25: Approved By | R25: Mitsukazu Nakata | AJ25: Gen. Debold Sinas | AK25: Chief Security Officer
A26: Supply Chain | B26: Business Development | C26: Business Solutions | E26: CT110000_ | F26: Construction & Design | G26: CT110200_ | H26: Interim FFE/OSM Management | I26: CT110201 | J26: Interim FFE/OSM Management | Q26: Approved By | R26: Mitsukazu Nakata | AJ26: Giancarlo Baldonido | AK26: Assistant Director - Destination Marketing
A27: Surveillance | B27: Business Insight and Research | C27: Butchery | E27: CT110000_ | F27: Construction & Design | G27: CT110300_ | H27: Construction Admin | I27: CT110301 | J27: Construction Admin | Q27: Approved By | R27: Mitsukazu Nakata | AJ27: Gizelle Leong | AK27: Assistant Vice President - Premium Marketing
A28: Table Games | B28: Business Solutions | C28: Cage | E28: GM110000_ | F28: Table Games | G28: GM110100_ | H28: Table Games Operations | I28: GM110101 | J28: Table Games Operations | Q28: Approved By | R28: Imelda Ordona | S28: Approved By | T28: Alan Jacalne | Z28: Jenilyn Merza | AA28: Francisco Varca | AJ28: Goddfrey Sebur | AK28: Chief Engineer, Hotel & Public Area
B29: Cage | C29: Call Center / Reservations | E29: GM110000_ | F29: Table Games | G29: GM110100_ | H29: Table Games Operations | I29: GM110102 | J29: Poker Stars-Cash Game | Q29: Approved By | R29: Imelda Ordona | S29: Approved By | T29: Alan Jacalne | Z29: Jenilyn Merza | AA29: Francisco Varca | AJ29: Han Tee Yap | AK29: Director - AML and Casino Regulatory Compliance
B30: Card Room | C30: Card Room | E30: GM110000_ | F30: Table Games | G30: GM110100_ | H30: Table Games Operations | I30: GM110103 | J30: Sports Book | Q30: Approved By | R30: Imelda Ordona | S30: Approved By | T30: Alan Jacalne | Z30: Jenilyn Merza | AA30: Francisco Varca | AJ30: Hans van der Sande | AK30: Chief Financial Officer & Treasurer
B31: Casino Finance | C31: Casino Accounting | E31: GM110000_ | F31: Table Games | G31: GM110100_ | H31: Table Games Operations | I31: GM110104 | J31: Poker Stars-Tournament | Q31: Approved By | R31: Imelda Ordona | S31: Approved By | T31: Alan Jacalne | Z31: Jenilyn Merza | AA31: Francisco Varca | AJ31: Henry Tan | AK31: Assistant Director - Count
B32: Casino Regulatory Compliance | C32: Casino Regulatory Compliance | E32: GM110000_ | F32: Table Games | G32: GM110200_ | H32: Training & Development | I32: GM110201 | J32: Training & Development | Q32: Approved By | R32: Imelda Ordona | S32: Approved By | T32: Alan Jacalne | Z32: Jenilyn Merza | AA32: Francisco Varca | AJ32: Ian Mariano | AK32: Assistant Director - Facility Management
B33: Centralization Service | C33: Casino Service | E33: GM110000_ | F33: Table Games | G33: GM110400_ | H33: Card Room | I33: GM110401 | J33: Card Room | Q33: Approved By | R33: Imelda Ordona | S33: Approved By | T33: Alan Jacalne | Z33: Jenilyn Merza | AA33: Francisco Varca | AJ33: Imelda Ordona | AK33: Director - Table Games
B34: Chief Security Office | C34: Centralization Service | E34: GM210000_ | F34: Electronic Gaming | G34: GM210100_ | H34: Electronic Gaming Operations | I34: GM210101 | J34: Electronic Gaming Operations | Q34: Approved By | R34: Diana Wu | Y34: Rick Colman | AC34: Jerry Chan | AJ34: Jane Tan | AK34: Director of Cage and Count Operations
B35: Compliance | C35: CHEMICAL INVENTORY | E35: GM210000_ | F35: Electronic Gaming | G35: GM210200_ | H35: Gaming Technical Services | I35: GM210201 | J35: Gaming Technical Services | Q35: Approved By | R35: Diana Wu | Y35: Alan Teoh | AC35: Jerry Chan | AJ35: Jayvee Villanueva | AK35: Call Center & Reservations Manager
B36: Construction Admin | C36: CHILLER | E36: GM210000_ | F36: Electronic Gaming | G36: GM210300_ | H36: Gaming OS&E Control | I36: GM210301 | J36: Gaming OS&E Control | Q36: Approved By | R36: Diana Wu | AC36: Jerry Chan | AJ36: Jenilyn Merza | AK36: Assistant Vice President - Table Games
B37: Corporate Management & Administration | C37: Compliance | E37: GM410000_ | F37: Cage, Count and Credit | G37: GM410100_ | H37: Cage | I37: GM410101 | J37: Cage | Q37: Approved By | R37: Jane Tan | X37: Nynn Tan | AJ37: Jeremy Cristobal | AK37: Director - Floral Operations
B38: Count | C38: Concierge/Bell Services | E38: GM410000_ | F38: Cage, Count and Credit | G38: GM410200_ | H38: Count | I38: GM410201 | J38: Count | Q38: Approved By | R38: Henry Tan | X38: Nynn Tan | AJ38: Jerome Sarte | AK38: Senior Vice President - Chief HR Officer
B39: Creative Entertainment | C39: Construction Admin | E39: GM410000_ | F39: Cage, Count and Credit | G39: GM410300_ | H39: Credit & Collection | I39: GM410301 | J39: Credit & Collection | Q39: Approved By | R39: Sherman Lim | X39: Nynn Tan | AJ39: Jerry Chan | AK39: Senior Vice President - Electronic Gaming Operations
B40: Creatives and Production | C40: Corporate Management & Administration | E40: GM510000_ | F40: Premium Marketing | G40: GM510100_ | H40: Marketing Operations | I40: GM510101 | J40: Marketing Operations | Q40: Approved By | R40: Chin Yang / Sasha Lan | Z40: Ashley Chen | AA40: Wendy Ni | AJ40: Joe Sam | AK40: Assistant Vice President - Loyalty
B41: Credit & Collection | C41: Corporate Sales & Marketing (B2B) | E41: GM510000_ | F41: Premium Marketing | G41: GM510200_ | H41: Business Development | I41: GM510201 | J41: Overseas Sales | Q41: Approved By | R41: Gizelle Leong | AA41: Wendy Ni | AJ41: Joemer Perez | AK41: Chief Legal Officer
B42: Customer Relation Management | C42: Cost Control Management | E42: GM510000_ | F42: Premium Marketing | G42: GM510200_ | H42: Business Development | I42: GM510202 | J42: Local Region | Q42: Approved By | R42: Sandy Valeriano / Jennylyn Ang | Z42: Gizelle Leong | AA42: Wendy Ni | AJ42: John Escueta | AK42: Manager - Gaming
B43: Destination Marketing | C43: Count | E43: GM510000_ | F43: Premium Marketing | G43: GM510200_ | H43: Business Development | I43: GM510203 | J43: Korean Region | Q43: Approved By | R43: Nick Park / Kangnae Lee | Z43: Gizelle Leong | AA43: Wendy Ni | AJ43: Josef Teuschler | AK43: Director - Culinary
B44: Distribution | C44: Creative Entertainment | E44: GM510000_ | F44: Premium Marketing | G44: GM510200_ | H44: Business Development | I44: GM510204 | J44: SEA Regions | Q44: Approved By | R44: Weng Sim | Z44: Gizelle Leong | AA44: Wendy Ni | AJ44: Jowel Benoza | AK44: Senior Manager - Distribution
B45: Electronic Gaming Operations | C45: Creatives and Production | E45: GM510000_ | F45: Premium Marketing | G45: GM510300_ | H45: Customer Relation Management | I45: GM510301 | J45: Customer Relation Management | Q45: Approved By | R45: Anthony Veloso | Z45: Joe Sam | AA45: Wendy Ni | AJ45: Kel Telford | AK45: Chief Information Officer
B46: ELV Technology | C46: Credit & Collection | E46: GM510000_ | F46: Premium Marketing | G46: GM510400_ | H46: Loyalty Marketing | I46: GM510401 | J46: Loyalty Marketing | Q46: Approved By | R46: Joe Sam | AA46: Wendy Ni | AJ46: Kentaro Amamoto | AK46: Vice President - Corporate Planning
B47: Employee Dining Room | C47: Customer Relation Management | E47: GM510000_ | F47: Premium Marketing | G47: GM510500_ | H47: Promotion and Events | I47: GM510501 | J47: Promotion and Events | Q47: Approved By | R47: Estee Sang | Z47: Joe Sam | AA47: Wendy Ni | AJ47: Louie Urrutia | AK47: Assistant Vice President - Business Solutions
B48: Employee Relations | C48: Destination Marketing | E48: GM510000_ | F48: Premium Marketing | G48: GM510600_ | H48: Destination Marketing | I48: GM510601 | J48: Destination Marketing | Q48: Approved By | R48: Giancarlo Baldonido | Z48: Wendy Ni | AJ48: Manida Lau | AK48: Vice President - Business Solutions
B49: F&B Administration | C49: Dimsum Kitchen | E49: GM610000_ | F49: Gaming Promoter Relations | G49: GM610100_ | H49: Gaming Promoter Relations | I49: GM610101 | J49: Gaming Promoter Relations | Q49: Approved By | R49: Ashley Chen | AA49: Sam Chea | AB49: Yuichiro Okazaki | AJ49: Maria Kristalyn Osillo | AK49: HR Manager - Talent Selection
B50: F&B Kitchen | C50: Distribution | E50: GM710000_ | F50: Strategic Marketing | G50: GM710100_ | H50: Optimization | I50: GM710101 | J50: Optimization | Q50: Approved By | R50: Wendy Ni | AJ50: Maria Roa Tansiking | AK50: Senior Manager - Workforce Planning
B51: F&B Service | C51: Electronic Gaming Operations | E51: GM710000_ | F51: Strategic Marketing | G51: GM710200_ | H51: Analytics | I51: GM710201 | J51: Analytics | Q51: Approved By | R51: Wendy Ni | AJ51: Maria Theresa Romeo | AK51: Assistant Manager - F&B Administration
B52: Finance Administration | C52: ELV Construction | E52: GM710000_ | F52: Strategic Marketing | G52: GM710300_ | H52: Business Insight and Research | I52: GM710301 | J52: Business Insight and Research | Q52: Approved By | R52: Wendy Ni | AJ52: Marie Verzosa | AK52: Junior Officer - Security & Compliance
B53: Financial Planning & Analysis | C53: ELV Infra & Projects | E53: GM710000_ | F53: Strategic Marketing | G53: GM710400_ | H53: Creative Entertainment | I53: GM710401 | J53: Creative Entertainment | Q53: Approved By | R53: Wendy Ni | AJ53: Marinisa Forschler | AK53: Associate Director - Digital Marketing
B54: Gaming & Podium | C54: ELV Operations | E54: GM810000_ | F54: Business Solutions | G54: GM810100_ | H54: Business Solutions | I54: GM810101 | J54: Business Solutions | Q54: Approved By | R54: Maria Theresa Romeo | Z54: Louie Urrutia | AA54: Manida Lau | AJ54: Miaki Narita | AK54: Associate Director - Premium Dining
B55: Gaming OS&E Control | C55: Emergency Response Team (ERT) | E55: GM810000_ | F55: Business Solutions | G55: GM810200_ | H55: Administration and Training | I55: GM810201 | J55: Administration and Training | Q55: Approved By | R55: Maria Theresa Romeo | Z55: Louie Urrutia | AA55: Manida Lau | AJ55: Mike Waite | AK55: Vice President - Surveillance
B56: Gaming Promoter Relations | C56: Employee Dining Room | E56: GM810000_ | F56: Business Solutions | G56: GM810300_ | H56: Premium Marketing and VIP Services | I56: GM810301 | J56: Premium Marketing and VIP Services | Q56: Approved By | R56: Sue Gooi | Z56: Louie Urrutia | AA56: Manida Lau | AJ56: Mitsukazu Nakata | AK56: Director and Chief Engineer
B57: Gaming Technical Services | C57: Employee Relations | E57: GM910000_ | F57: Surveillance | G57: GM910100_ | H57: Surveillance Operations | I57: GM910101 | J57: Surveillance Operations | Q57: Approved By | R57: Robert Doe | V57: Mike Waite | AJ57: Naoshi Nema | AK57: Vice President - Accounting
B58: General Accounting | C58: Enbu | E58: GM910000_ | F58: Surveillance | G58: GM910200_ | H58: Surveillance Services | I58: GM910201 | J58: Surveillance Services | Q58: Approved By | R58: Chris Hamill | V58: Mike Waite | AJ58: Nino Emmanuel Telan | AK58: Associate Director - Rewards & Employee Services
B59: Hospitality Finance | C59: Event Sales & Marketing (B2C) | E59: GM910000_ | F59: Surveillance | G59: GM910300_ | H59: Surveillance Special Projects | I59: GM910301 | J59: Surveillance Special Projects | Q59: Approved By | R59: Valentin Popescu | V59: Mike Waite | AJ59: Nona Mendoza | AK59: Director of Internal Audit
B60: Hospitality Shared Services | C60: Executive Lounge | E60: GM910000_ | F60: Surveillance | G60: GM910400_ | H60: Surveillance Administration | I60: GM910401 | J60: Surveillance Administration | Q60: Approved By | R60: Mike Waite | AJ60: Nynn Tan | AK60: Vice President - Cage, Count and Credit
B61: Hotel & Public Area | C61: F&B Administration | E61: HS110000_ | F61: Hotel | G61: HS110100_ | H61: Hotel Administration | I61: HS110101 | J61: Hotel Administration | Q61: Approved By | R61: Robert Scott | AJ61: Reddy Leong | AK61: Vice President - Corporate Marketing & Communications
B62: Hotel Administration | C62: F&B Sales & Marketing | E62: HS110000_ | F62: Hotel | G62: HS110200_ | H62: Rooms | I62: HS110201 | J62: Front Office | Q62: Approved By | R62: Zahid Ahmed | W62: Robert Scott | AJ62: Regel Ymalay | AK62: Senior Creative Manager
B63: HR Administration | C63: FCIE DASMARINAS GENERAL SUPPLIES | E63: HS110000_ | F63: Hotel | G63: HS110200_ | H63: Rooms | I63: HS110202 | J63: Executive Lounge | Q63: Approved By | R63: Andreas Balla | AJ63: Reynald Ngo | AK63: Assistant Vice President - Information Systems
B64: Infrastructure Operations | C64: Finance Administration | E64: HS110000_ | F64: Hotel | G64: HS110200_ | H64: Rooms | I64: HS110204 | J64: Guest Services | Q64: Approved By | R64: Zahid Ahmed | W64: Robert Scott | AJ64: Ricardo Aguas Jr. | AK64: Vice President - Supply Chain
B65: Interim FFE/OSM Management | C65: Financial Compliance | E65: HS110000_ | F65: Hotel | G65: HS110200_ | H65: Rooms | I65: HS110205 | J65: Concierge/Bell Services | Q65: Approved By | R65: Zahid Ahmed | W65: Robert Scott | AJ65: Rick Colman | AK65: Vice President - Electronic Gaming Operations
B66: Internal Audit | C66: Financial Planning & Analysis | E66: HS110000_ | F66: Hotel | G66: HS110200_ | H66: Rooms | I66: HS110206 | J66: Rooms-Housekeeping | Q66: Approved By | R66: Alda Madrid | W66: Robert Scott | AJ66: Robert Doe | AK66: Director - Surveillance Operations
B67: Internal Control | C67: Financial Research and Studies | E67: HS110000_ | F67: Hotel | G67: HS110200_ | H67: Rooms | I67: HS110207 | J67: Private Bar | Q67: Approved By | R67: Alda Madrid | W67: Robert Scott | AJ67: Robert Scott | AK67: Vice President - Hotel Operations
B68: Kitchen | C68: Fixed Assets | E68: HS110000_ | F68: Hotel | G68: HS110300_ | H68: Hospitality Shared Services | I68: HS110301 | J68: Call Center / Reservations | Q68: Approved By | R68: Alexandrea Herrera | S68: Approved By | T68: Jayvee Villanueva | W68: Robert Scott | AJ68: Sam Chea | AK68: Assistant Vice President - International Marketing
B69: Leasing/Retail | C69: Floral Design & Decorations | E69: HS110000_ | F69: Hotel | G69: HS110300_ | H69: Hospitality Shared Services | I69: HS110302 | J69: Transportation - Land | Q69: Approved By | R69: Eunice Villaluz | W69: Robert Scott | AJ69: Sharon Yabut | AK69: Assistant Director of Events - F&B Administration
B70: Legal | C70: FOOD INVENTORY | E70: HS110000_ | F70: Hotel | G70: HS110300_ | H70: Hospitality Shared Services | I70: HS110306 | J70: Hospitality Training | Q70: Approved By | R70: Marie Verzosa | W70: Robert Scott | AJ70: Sherman Lim | AK70: Assistant Director - Credit & Collections
B71: Loyalty Marketing | C71: FREEZER | E71: HS110000_ | F71: Hotel | G71: HS110300_ | H71: Hospitality Shared Services | I71: HS110307 | J71: Airport Lounge | Q71: Approved By | R71: Zahid Ahmed | W71: Robert Scott | AJ71: Shin Zamora | AK71: Senior Manager - Facility Management Administration
B72: Marketing Operations | C72: Front Office | E72: HS110000_ | F72: Hotel | G72: HS110300_ | H72: Hospitality Shared Services | I72: HS110308 | J72: Housekeeping Public Area | Q72: Approved By | R72: Bethoven Nalo | W72: Robert Scott | AJ72: Sonny Jarlos | AK72: Senior Manager - Finance & Admin
B73: Media Relations and Partnership | C73: Gaming & Podium | E73: HS110000_ | F73: Hotel | G73: HS110300_ | H73: Hospitality Shared Services | I73: HS110309 | J73: In-house Laundry | Q73: Approved By | R73: Robert Scott | AJ73: Sue Gooi | AK73: Director - Premium Marketing & VIP Services
B74: MEPF | C74: Gaming Audit | E74: HS110000_ | F74: Hotel | G74: HS110300_ | H74: Hospitality Shared Services | I74: HS110310 | J74: Offsite Laundry | Q74: Approved By | R74: Robert Scott | AJ74: Sumit Rajput | AK74: Director - F&B Operations
B75: Optimization | C75: Gaming OS&E Control | E75: HS110000_ | F75: Hotel | G75: HS110300_ | H75: Hospitality Shared Services | I75: HS110311 | J75: Wardrobe & Uniforms | Q75: Approved By | R75: Robert Scott | AJ75: Valentin Popescu | AK75: Associate Director - Surveillance Special Projects
B76: Payroll | C76: Gaming Promoter Relations | E76: HS110000_ | F76: Hotel | G76: HS110300_ | H76: Hospitality Shared Services | I76: HS110312 | J76: Floral Design & Decorations | Q76: Approved By | R76: Jeremy Cristobal | W76: Robert Scott | AJ76: Victor Galzote | AK76: Director - Property Marketing & Branding
B77: Physical Security | C77: Gaming Technical Services | E77: HS110000_ | F77: Hotel | G77: HS110500_ | H77: Spas, Recreation & Kids Club | I77: HS110501 | J77: The Retreat Spa | Q77: Approved By | R77: Victoria Cecilia Aquino | W77: Robert Scott | AJ77: Victoria Cecilia Aquino | AK77: Executive Director - Wellness & Leisure
B78: Premium Marketing and VIP Services | C78: Garde Manger | E78: HS110000_ | F78: Hotel | G78: HS110500_ | H78: Spas, Recreation & Kids Club | I78: HS110506 | J78: Sole Retreat | Q78: Approved By | R78: Victoria Cecilia Aquino | W78: Robert Scott | AJ78: Wendy Ni | AK78: Vice President - Strategic Marketing & Business Planning
B79: Procurement & Strategic Planning | C79: General Ledger | E79: HS110000_ | F79: Hotel | G79: HS110500_ | H79: Spas, Recreation & Kids Club | I79: HS110507 | J79: Kids Club | Q79: Approved By | R79: Victoria Cecilia Aquino | W79: Robert Scott | AJ79: Wilfredo Co | AK79: Director - Banquet Operations
B80: Project Accounting | C80: GENERAL SUPPLIES | E80: HS110000_ | F80: Hotel | G80: HS110500_ | H80: Spas, Recreation & Kids Club | I80: HS110508 | J80: Recreation | Q80: Approved By | R80: Victoria Cecilia Aquino | W80: Robert Scott | AJ80: Yuichiro Okazaki | AK80: Vice President - International Marketing
B81: Project Management | C81: GIFT SHOP INVENTORY | E81: HS110000_ | F81: Hotel | G81: HS110500_ | H81: Spas, Recreation & Kids Club | I81: HS110509 | J81: Nail Art Studio | Q81: Approved By | R81: Victoria Cecilia Aquino | W81: Robert Scott | AJ81: Estee Sang | AK81: Assistant Director - Promotion & Events
B82: Project Management Office | C82: GLACIER BEVERAGE INVENTORY | E82: HS110000_ | F82: Hotel | G82: HS110500_ | H82: Spas, Recreation & Kids Club | I82: HS110510 | J82: Thrillscape | Q82: Approved By | R82: Victoria Cecilia Aquino | W82: Robert Scott | AJ82: Jeanalyn Delfin | AK82: Senior Manager - Social & Digital Marketing
B83: Promotion and Events | C83: GLACIER CHILLER INVENTORY | E83: HS110000_ | F83: Hotel | G83: HS110500_ | H83: Spas, Recreation & Kids Club | I83: HS110511 | J83: Beach Club | Q83: Approved By | R83: Victoria Cecilia Aquino | W83: Robert Scott | AJ83: JoeBert Lazarte | AK83: Senior Manager - Strategic Communications & Creative Production
B84: R700 - GIFT SHOP INVENTORY | C84: GLACIER FOOD INVENTORY | E84: HS110000_ | F84: Hotel | G84: HS110600_ | H84: Sales & Marketing | I84: HS110601 | J84: Room Sales | Q84: Approved By | R84: Alexandrea Herrera | S84: Approved By | T84: Cielo Roberedo | W84: Robert Scott | AJ84: Chin Yang / Sasha Lan | AK84: Senior Manager - International Marketing, Operations (International Marketing) / Senior Manager - International Marketing, Operations (International Marketing)
B85: Rewards and Employee Services | C85: GLACIER FROZEN INVENTORY | E85: HS210000_ | F85: Food and Beverage | G85: HS210100_ | H85: F&B Service | I85: HS210101 | J85: Medley | Q85: Approved By | R85: Sumit Rajput | S85: Approved By | T85: Andreas Balla | AJ85: Sandy Valeriano / Jennylyn Ang | AK85: Director - Premium Marketing Business Development, Business Development / Director - Premium Marketing Business Development, Business Development
B86: Risk Management | C86: GLACIER WINE INVENTORY | E86: HS210000_ | F86: Food and Beverage | G86: HS210100_ | H86: F&B Service | I86: HS210102 | J86: Lobby Lounge and Pastry Shop | Q86: Approved By | R86: Sumit Rajput | S86: Approved By | T86: Andreas Balla | AJ86: Nick Park / Kangnae Lee | AK86: Director - International Marketing (BD), Business Development / Director - Emerging Market Business Development, Business Development
B87: Rooms | C87: Goryeo | E87: HS210000_ | F87: Food and Beverage | G87: HS210100_ | H87: F&B Service | I87: HS210103 | J87: Private Dining Room | Q87: Approved By | R87: Sumit Rajput | S87: Approved By | T87: Andreas Balla | AJ87: Weng Sim | AK87: Assistant Director - Emerging Market Business Development, Business Development
B88: Sales & Marketing | C88: Guest Services | E88: HS210000_ | F88: Food and Beverage | G88: HS210100_ | H88: F&B Service | I88: HS210106 | J88: Pool Bar | Q88: Approved By | R88: Sumit Rajput | S88: Approved By | T88: Andreas Balla | AJ88: Zahid Ahmed | AK88: Director - Hotel Operations
B89: Security & Compliance | C89: Hospitality Accounting | E89: HS210000_ | F89: Food and Beverage | G89: HS210100_ | H89: F&B Service | I89: HS210111 | J89: La Piazza | Q89: Approved By | R89: Sumit Rajput | S89: Approved By | T89: Andreas Balla | AJ89: Mark Ryan Talabis | AK89: Executive Director - Chief Information Security Officer, Security & Compliance
B90: Security Infra, R&D | C90: Hospitality Training | E90: HS210000_ | F90: Food and Beverage | G90: HS210100_ | H90: F&B Service | I90: HS210112 | J90: Enbu | Q90: Approved By | R90: Sumit Rajput | S90: Approved By | T90: Andreas Balla | AJ90: Mary Anne Lagrimas | AK90: Senior Manager - Project Management
B91: Security Technology Services | C91: Hotel & Public Area | E91: HS210000_ | F91: Food and Beverage | G91: HS210100_ | H91: F&B Service | I91: HS210115 | J91: Goryeo | Q91: Approved By | R91: Sumit Rajput | S91: Approved By | T91: Andreas Balla
B92: Service | C92: Hotel Administration | E92: HS210000_ | F92: Food and Beverage | G92: HS210100_ | H92: F&B Service | I92: HS210117 | J92: Red Spice | Q92: Approved By | R92: Sumit Rajput | S92: Approved By | T92: Andreas Balla
B93: Social and Digital Marketing | C93: Housekeeping Public Area | E93: HS210000_ | F93: Food and Beverage | G93: HS210100_ | H93: F&B Service | I93: HS210118 | J93: Kiapo | Q93: Approved By | R93: Sumit Rajput | S93: Approved By | T93: Andreas Balla
B94: Spas, Recreation & Kids Club | C94: HR Administration | E94: HS210000_ | F94: Food and Beverage | G94: HS210100_ | H94: F&B Service | I94: HS210119 | J94: Sportsbook Bar | Q94: Approved By | R94: Sumit Rajput | S94: Approved By | T94: Andreas Balla
B95: Steward | C95: Hygiene | E95: HS210000_ | F95: Food and Beverage | G95: HS210100_ | H95: F&B Service | I95: HS210122 | J95: Okada Lounge | Q95: Approved By | R95: Sumit Rajput | S95: Approved By | T95: Andreas Balla
B96: Strategic Planning | C96: In-house Laundry | E96: HS210000_ | F96: Food and Beverage | G96: HS210100_ | H96: F&B Service | I96: HS210125 | J96: Sinag | Q96: Approved By | R96: Sumit Rajput | S96: Approved By | T96: Andreas Balla
B97: Supply Chain Business Support | C97: Interim FFE/OSM Management | E97: HS210000_ | F97: Food and Beverage | G97: HS210100_ | H97: F&B Service | I97: HS210126 | J97: Luna Lounge | Q97: Approved By | R97: Sumit Rajput | S97: Approved By | T97: Andreas Balla
B98: Support Services | C98: Internal & External Security | E98: HS210000_ | F98: Food and Beverage | G98: HS210100_ | H98: F&B Service | I98: HS210129 | J98: Perlas Dining | Q98: Approved By | R98: Sumit Rajput | S98: Approved By | T98: Andreas Balla
B99: Surveillance Administration | C99: Internal Audit | E99: HS210000_ | F99: Food and Beverage | G99: HS210100_ | H99: F&B Service | I99: HS210130 | J99: Roasting by Red Spice | Q99: Approved By | R99: Sumit Rajput | S99: Approved By | T99: Andreas Balla
B100: Surveillance Operations | C100: Internal Control | E100: HS210000_ | F100: Food and Beverage | G100: HS210100_ | H100: F&B Service | I100: HS210181 | J100: Banquets | Q100: Approved By | R100: Wilfredo Co | S100: Approved By | T100: Andreas Balla
B101: Surveillance Services | C101: IT Administration | E101: HS210000_ | F101: Food and Beverage | G101: HS210200_ | H101: F&B Kitchen | I101: HS210201 | J101: Kitchen-Medley | Q101: Approved By | R101: Josef Teuschler | S101: Approved By | T101: Andreas Balla
B102: Surveillance Special Projects | C102: IT Application Support | E102: HS210000_ | F102: Food and Beverage | G102: HS210200_ | H102: F&B Kitchen | I102: HS210202 | J102: Kitchen-Lobby Lounge and Pastry Shop | Q102: Approved By | R102: Josef Teuschler | S102: Approved By | T102: Andreas Balla
... B108: Workforce Planning | C108: IT Network & Telecoms | E108: HS210000_ | F108: Food and Beverage | G108: HS210200_ | H108: F&B Kitchen | I108: HS210215 | J108: Kitchen-Red Spice | Q108: Approved By | R108: Josef Teuschler | S108: Approved By | T108: Andreas Balla
...

Sheet Reference
A1: PRICE BENCHMARK | C1: VENDORS | E1: EXECUTION | G1: BUYER | H1: AM/M | I1: M | J1: AD | K1: VP | M1: AM/M | N1: POSITION
A2: INITIAL LOWEST BID | C2: ='Bid Tab (F&B Ops and CatMan) 10'!$B37 -> VENDOR 1 | E2: BPO | G2: Angelica Vasquez | H2: Rashel Nacor | J2: Jeric Conway Miranda | K2: Ricardo Aguas, Jr. | M2: Christian Paul Bangsal | N2: Asst. Manager, Procurement - OS&E
A3: LAST SYSTEM PRICE | C3: ='Bid Tab (F&B Ops and CatMan) 10'!$B38 -> VENDOR 2 | E3: CONTRACT | G3: April Joyce Geniston | H3: Marco Gabriel Tibayan | J3: Jeric Conway Miranda | K3: Ricardo Aguas, Jr. | M3: Joanna Perl Villasis | N3: Asst. Manager, Procurement - CatMan OS&E
A4: PRICE EXTENSION | C4: ='Bid Tab (F&B Ops and CatMan) 10'!$B39 -> VENDOR 3 | E4: PMI | G4: Christian Macalindong | H4: Rashel Nacor | J4: Jeric Conway Miranda | K4: Ricardo Aguas, Jr. | M4: Dennis Dumapias | N4: Asst. Manager, Procurement - OS&E
C5: ='Bid Tab (F&B Ops and CatMan) 10'!$B40 -> VENDOR 4 | E5: PO | G5: Christian Paul Bangsal | H5: Marco Gabriel Tibayan | J5: Jeric Conway Miranda | K5: Ricardo Aguas, Jr. | M5: Martin Ruiz Mercado | N5: Asst. Manager, Procurement - CatMan OS&E
C6: ='Bid Tab (F&B Ops and CatMan) 10'!$B41 -> VENDOR 5 | G6: Dennis Dumapias | H6: Rashel Nacor | J6: Jeric Conway Miranda | K6: Ricardo Aguas, Jr. | M6: Rowie Marie Caudilla | N6: Officer, Procurement - F&B
A7: COMPLIANT | C7: ='Bid Tab (F&B Ops and CatMan) 10'!$B42 -> VENDOR 6 | G7: Erwin Toralba | H7: Christian Paul Bangsal | I7: Marco Gabriel Tibayan | J7: Jeric Conway Miranda | K7: Ricardo Aguas, Jr. | M7: Guiller Fiestada | N7: Officer, Procurement - F&B
A8: RECOMMENDED | C8: ='Bid Tab (F&B Ops and CatMan) 10'!$B43 -> VENDOR 7 | G8: Garret Neil Mojares | H8: Marco Gabriel Tibayan | J8: Jeric Conway Miranda | K8: Ricardo Aguas, Jr. | M8: JM Villacorte | N8: Officer, Procurement - F&B
A9: ACCEPTED | C9: ='Bid Tab (F&B Ops and CatMan) 10'!$B44 -> VENDOR 8 | G9: Gianina Malka Mendoza | H9: Joanna Perl Villasis / Dennis Dumapias | I9: Rashel Nacor | J9: Jeric Conway Miranda | K9: Ricardo Aguas, Jr. | M9: Sara Jane Pontero | N9: Manager, Procurement - CatMan F&B
A10: NOT ACCEPTED | C10: ='Bid Tab (F&B Ops and CatMan) 10'!$B45 -> VENDOR 9 | G10: Harvie Noriel | H10: Dennis Dumapias | I10: Rashel Nacor | J10: Jeric Conway Miranda | K10: Ricardo Aguas, Jr. | M10: Dan Errol Bavar | N10: Asst. Manager, Procurement - Projects & Services
C11: ='Bid Tab (F&B Ops and CatMan) 10'!$B46 -> VENDOR 10 | G11: Jeffry Bacani | H11: Rashel Nacor | J11: Jeric Conway Miranda | K11: Ricardo Aguas, Jr. | M11: Rashel Nacor | N11: Senior Manager, Procurement - OS&E
A12: VAT TERMS: | G12: Jelor Gusi | H12: Joanna Perl Villasis / Dennis Dumapias | I12: Rashel Nacor | J12: Jeric Conway Miranda | K12: Ricardo Aguas, Jr. | M12: Marco Gabriel Tibayan | N12: Senior Manager, Procurement - OS&E
A13: VAT Inclusive | G13: Jeric Conway Miranda | K13: Ricardo Aguas, Jr. | M13: Jennifer Enrile | N13: Senior Manager, Procurement - F&B
A14: VAT Exclusive | G14: Joanna Perl Villasis | H14: Rashel Nacor | J14: Jeric Conway Miranda | K14: Ricardo Aguas, Jr. | M14: Robert Tyron Samson | N14: Manager, Procurement - Projects & Services
A15: VAT Exempt | G15: Marco Gabriel Tibayan | J15: Jeric Conway Miranda | K15: Ricardo Aguas, Jr. | M15: Frederick Zulueta | N15: Senior Manager, Procurement - Projects & Services
G16: Martin Roland Cahiles | H16: Martin Ruiz Mercado / Christian Paul Bangsal | I16: Marco Gabriel Tibayan | J16: Jeric Conway Miranda | K16: Ricardo Aguas, Jr. | M16: Joanna Perl Villasis / Dennis Dumapias | N16: Asst. Manager, Procurement - CatMan OS&E / Asst. Manager, Procurement - OS&E
A17: INITIAL LOWEST (RECOMMENDED) | G17: Martin Ruiz Mercado | H17: Marco Gabriel Tibayan | J17: Jeric Conway Miranda | K17: Ricardo Aguas, Jr. | M17: Martin Ruiz Mercado / Christian Paul Bangsal | N17: Asst. Manager, Procurement - CatMan OS&E / Asst. Manager, Procurement - OS&E
A18: =IF('Bid Tab (F&B Ops and CatMan) 10'!AO11=Reference!$A$8,'Bid Tab (F&B Ops and CatMan) 10'!AJ11,IF('Bid Tab (F&B Ops and CatMan) 10'!AU11=Reference!$A$8,'Bid Tab (F&B Ops and CatMan) 10'!AP11,IF('Bid Tab (F&B Ops and CatMan) 10'!BA11=Reference!$A$8,'Bid Tab (F&B Ops and CatMan) 10'!AV11,IF('Bid Tab (F&B Ops and CatMan) 10'!BG11=Reference!$A$8,'Bid Tab (F&B Ops and CatMan) 10'!BB11,IF('Bid Tab (F&B Ops and CatMan) 10'!BM11=Reference!$A$8,'Bid Tab (F&B Ops and CatMan) 10'!BH11,IF('Bid Tab (F&B Ops and CatMan) 10'!BS11=Reference!$A$8,'Bid Tab (F&B Ops and CatMan) 10'!BN11,IF('Bid Tab (F&B Ops and CatMan) 10'!BY11=Reference!$A$8,'Bid Tab (F&B Ops and CatMan) 10'!BT11,IF('Bid Tab (F&B Ops and CatMan) 10'!CE11=Reference!$A$8,'Bid Tab (F&B Ops and CatMan) 10'!BZ11,IF('Bid Tab (F&B Ops and CatMan) 10'!CK11=Reference!$A$8,'Bid Tab (F&B Ops and CatMan) 10'!CF11,IF('Bid Tab (F&B Ops and CatMan) 10'!CQ11=Reference!$A$8,'Bid Tab (F&B Ops and CatMan) 10'!CL11,0)))))))))) -> 0 | G18: Prince Delos Santos | H18: Christian Paul Bangsal | I18: Marco Gabriel Tibayan | J18: Jeric Conway Miranda | K18: Ricardo Aguas, Jr. | M18: Brian Anthony Macalindong | N18: Senior Manager, Procurement - Projects & Services
A19: =IF('Bid Tab (F&B Ops and CatMan) 10'!AO12=Reference!$A$8,'Bid Tab (F&B Ops and CatMan) 10'!AJ12,IF('Bid Tab (F&B Ops and CatMan) 10'!AU12=Reference!$A$8,'Bid Tab (F&B Ops and CatMan) 10'!AP12,IF('Bid Tab (F&B Ops and CatMan) 10'!BA12=Reference!$A$8,'Bid Tab (F&B Ops and CatMan) 10'!AV12,IF('Bid Tab (F&B Ops and CatMan) 10'!BG12=Reference!$A$8,'Bid Tab (F&B Ops and CatMan) 10'!BB12,IF('Bid Tab (F&B Ops and CatMan) 10'!BM12=Reference!$A$8,'Bid Tab (F&B Ops and CatMan) 10'!BH12,IF('Bid Tab (F&B Ops and CatMan) 10'!BS12=Reference!$A$8,'Bid Tab (F&B Ops and CatMan) 10'!BN12,IF('Bid Tab (F&B Ops and CatMan) 10'!BY12=Reference!$A$8,'Bid Tab (F&B Ops and CatMan) 10'!BT12,IF('Bid Tab (F&B Ops and CatMan) 10'!CE12=Reference!$A$8,'Bid Tab (F&B Ops and CatMan) 10'!BZ12,IF('Bid Tab (F&B Ops and CatMan) 10'!CK12=Reference!$A$8,'Bid Tab (F&B Ops and CatMan) 10'!CF12,IF('Bid Tab (F&B Ops and CatMan) 10'!CQ12=Reference!$A$8,'Bid Tab (F&B Ops and CatMan) 10'!CL12,0)))))))))) -> 0 | G19: Ram Marc Ona | H19: Martin Ruiz Mercado / Christian Paul Bangsal | I19: Marco Gabriel Tibayan | J19: Jeric Conway Miranda | K19: Ricardo Aguas, Jr. | M19: Jeric Conway Miranda | N19: Associate Director - Procurement & Strategic Planning
A20: =IF('Bid Tab (F&B Ops and CatMan) 10'!AO13=Reference!$A$8,'Bid Tab (F&B Ops and CatMan) 10'!AJ13,IF('Bid Tab (F&B Ops and CatMan) 10'!AU13=Reference!$A$8,'Bid Tab (F&B Ops and CatMan) 10'!AP13,IF('Bid Tab (F&B Ops and CatMan) 10'!BA13=Reference!$A$8,'Bid Tab (F&B Ops and CatMan) 10'!AV13,IF('Bid Tab (F&B Ops and CatMan) 10'!BG13=Reference!$A$8,'Bid Tab (F&B Ops and CatMan) 10'!BB13,IF('Bid Tab (F&B Ops and CatMan) 10'!BM13=Reference!$A$8,'Bid Tab (F&B Ops and CatMan) 10'!BH13,IF('Bid Tab (F&B Ops and CatMan) 10'!BS13=Reference!$A$8,'Bid Tab (F&B Ops and CatMan) 10'!BN13,IF('Bid Tab (F&B Ops and CatMan) 10'!BY13=Reference!$A$8,'Bid Tab (F&B Ops and CatMan) 10'!BT13,IF('Bid Tab (F&B Ops and CatMan) 10'!CE13=Reference!$A$8,'Bid Tab (F&B Ops and CatMan) 10'!BZ13,IF('Bid Tab (F&B Ops and CatMan) 10'!CK13=Reference!$A$8,'Bid Tab (F&B Ops and CatMan) 10'!CF13,IF('Bid Tab (F&B Ops and CatMan) 10'!CQ13=Reference!$A$8,'Bid Tab (F&B Ops and CatMan) 10'!CL13,0)))))))))) -> 0 | G20: Rashel Nacor | J20: Jeric Conway Miranda | K20: Ricardo Aguas, Jr. | M20: Shellame Palaganas | N20: Associate Director - Procurement & Strategic Planning
A21: =IF('Bid Tab (F&B Ops and CatMan) 10'!AO14=Reference!$A$8,'Bid Tab (F&B Ops and CatMan) 10'!AJ14,IF('Bid Tab (F&B Ops and CatMan) 10'!AU14=Reference!$A$8,'Bid Tab (F&B Ops and CatMan) 10'!AP14,IF('Bid Tab (F&B Ops and CatMan) 10'!BA14=Reference!$A$8,'Bid Tab (F&B Ops and CatMan) 10'!AV14,IF('Bid Tab (F&B Ops and CatMan) 10'!BG14=Reference!$A$8,'Bid Tab (F&B Ops and CatMan) 10'!BB14,IF('Bid Tab (F&B Ops and CatMan) 10'!BM14=Reference!$A$8,'Bid Tab (F&B Ops and CatMan) 10'!BH14,IF('Bid Tab (F&B Ops and CatMan) 10'!BS14=Reference!$A$8,'Bid Tab (F&B Ops and CatMan) 10'!BN14,IF('Bid Tab (F&B Ops and CatMan) 10'!BY14=Reference!$A$8,'Bid Tab (F&B Ops and CatMan) 10'!BT14,IF('Bid Tab (F&B Ops and CatMan) 10'!CE14=Reference!$A$8,'Bid Tab (F&B Ops and CatMan) 10'!BZ14,IF('Bid Tab (F&B Ops and CatMan) 10'!CK14=Reference!$A$8,'Bid Tab (F&B Ops and CatMan) 10'!CF14,IF('Bid Tab (F&B Ops and CatMan) 10'!CQ14=Reference!$A$8,'Bid Tab (F&B Ops and CatMan) 10'!CL14,0)))))))))) -> 0 | G21: Rhey Niel Valenzuela | H21: Christian Paul Bangsal | I21: Marco Gabriel Tibayan | J21: Jeric Conway Miranda | K21: Ricardo Aguas, Jr. | M21: Ricardo Aguas, Jr. | N21: Vice President - Supply Chain Division
A22: =IF('Bid Tab (F&B Ops and CatMan) 10'!AO15=Reference!$A$8,'Bid Tab (F&B Ops and CatMan) 10'!AJ15,IF('Bid Tab (F&B Ops and CatMan) 10'!AU15=Reference!$A$8,'Bid Tab (F&B Ops and CatMan) 10'!AP15,IF('Bid Tab (F&B Ops and CatMan) 10'!BA15=Reference!$A$8,'Bid Tab (F&B Ops and CatMan) 10'!AV15,IF('Bid Tab (F&B Ops and CatMan) 10'!BG15=Reference!$A$8,'Bid Tab (F&B Ops and CatMan) 10'!BB15,IF('Bid Tab (F&B Ops and CatMan) 10'!BM15=Reference!$A$8,'Bid Tab (F&B Ops and CatMan) 10'!BH15,IF('Bid Tab (F&B Ops and CatMan) 10'!BS15=Reference!$A$8,'Bid Tab (F&B Ops and CatMan) 10'!BN15,IF('Bid Tab (F&B Ops and CatMan) 10'!BY15=Reference!$A$8,'Bid Tab (F&B Ops and CatMan) 10'!BT15,IF('Bid Tab (F&B Ops and CatMan) 10'!CE15=Reference!$A$8,'Bid Tab (F&B Ops and CatMan) 10'!BZ15,IF('Bid Tab (F&B Ops and CatMan) 10'!CK15=Reference!$A$8,'Bid Tab (F&B Ops and CatMan) 10'!CF15,IF('Bid Tab (F&B Ops and CatMan) 10'!CQ15=Reference!$A$8,'Bid Tab (F&B Ops and CatMan) 10'!CL15,0)))))))))) -> 0 | G22: Richard Cruz | H22: Marco Gabriel Tibayan | J22: Jeric Conway Miranda | K22: Ricardo Aguas, Jr. | M22: John Vincent Dimaunahan | N22: Asst. Manager, Procurement - Projects & Services
A23: =IF('Bid Tab (F&B Ops and CatMan) 10'!AO16=Reference!$A$8,'Bid Tab (F&B Ops and CatMan) 10'!AJ16,IF('Bid Tab (F&B Ops and CatMan) 10'!AU16=Reference!$A$8,'Bid Tab (F&B Ops and CatMan) 10'!AP16,IF('Bid Tab (F&B Ops and CatMan) 10'!BA16=Reference!$A$8,'Bid Tab (F&B Ops and CatMan) 10'!AV16,IF('Bid Tab (F&B Ops and CatMan) 10'!BG16=Reference!$A$8,'Bid Tab (F&B Ops and CatMan) 10'!BB16,IF('Bid Tab (F&B Ops and CatMan) 10'!BM16=Reference!$A$8,'Bid Tab (F&B Ops and CatMan) 10'!BH16,IF('Bid Tab (F&B Ops and CatMan) 10'!BS16=Reference!$A$8,'Bid Tab (F&B Ops and CatMan) 10'!BN16,IF('Bid Tab (F&B Ops and CatMan) 10'!BY16=Reference!$A$8,'Bid Tab (F&B Ops and CatMan) 10'!BT16,IF('Bid Tab (F&B Ops and CatMan) 10'!CE16=Reference!$A$8,'Bid Tab (F&B Ops and CatMan) 10'!BZ16,IF('Bid Tab (F&B Ops and CatMan) 10'!CK16=Reference!$A$8,'Bid Tab (F&B Ops and CatMan) 10'!CF16,IF('Bid Tab (F&B Ops and CatMan) 10'!CQ16=Reference!$A$8,'Bid Tab (F&B Ops and CatMan) 10'!CL16,0)))))))))) -> 0 | G23: Sollace Mae Lagne | H23: Dennis Dumapias | I23: Rashel Nacor | J23: Jeric Conway Miranda | K23: Ricardo Aguas, Jr.
A24: =IF('Bid Tab (F&B Ops and CatMan) 10'!AO17=Reference!$A$8,'Bid Tab (F&B Ops and CatMan) 10'!AJ17,IF('Bid Tab (F&B Ops and CatMan) 10'!AU17=Reference!$A$8,'Bid Tab (F&B Ops and CatMan) 10'!AP17,IF('Bid Tab (F&B Ops and CatMan) 10'!BA17=Reference!$A$8,'Bid Tab (F&B Ops and CatMan) 10'!AV17,IF('Bid Tab (F&B Ops and CatMan) 10'!BG17=Reference!$A$8,'Bid Tab (F&B Ops and CatMan) 10'!BB17,IF('Bid Tab (F&B Ops and CatMan) 10'!BM17=Reference!$A$8,'Bid Tab (F&B Ops and CatMan) 10'!BH17,IF('Bid Tab (F&B Ops and CatMan) 10'!BS17=Reference!$A$8,'Bid Tab (F&B Ops and CatMan) 10'!BN17,IF('Bid Tab (F&B Ops and CatMan) 10'!BY17=Reference!$A$8,'Bid Tab (F&B Ops and CatMan) 10'!BT17,IF('Bid Tab (F&B Ops and CatMan) 10'!CE17=Reference!$A$8,'Bid Tab (F&B Ops and CatMan) 10'!BZ17,IF('Bid Tab (F&B Ops and CatMan) 10'!CK17=Reference!$A$8,'Bid Tab (F&B Ops and CatMan) 10'!CF17,IF('Bid Tab (F&B Ops and CatMan) 10'!CQ17=Reference!$A$8,'Bid Tab (F&B Ops and CatMan) 10'!CL17,0)))))))))) -> 0 | G24: Wayne Dominic Magdaluyo | H24: Dennis Dumapias | I24: Rashel Nacor | J24: Jeric Conway Miranda | K24: Ricardo Aguas, Jr.
A25: =IF('Bid Tab (F&B Ops and CatMan) 10'!AO18=Reference!$A$8,'Bid Tab (F&B Ops and CatMan) 10'!AJ18,IF('Bid Tab (F&B Ops and CatMan) 10'!AU18=Reference!$A$8,'Bid Tab (F&B Ops and CatMan) 10'!AP18,IF('Bid Tab (F&B Ops and CatMan) 10'!BA18=Reference!$A$8,'Bid Tab (F&B Ops and CatMan) 10'!AV18,IF('Bid Tab (F&B Ops and CatMan) 10'!BG18=Reference!$A$8,'Bid Tab (F&B Ops and CatMan) 10'!BB18,IF('Bid Tab (F&B Ops and CatMan) 10'!BM18=Reference!$A$8,'Bid Tab (F&B Ops and CatMan) 10'!BH18,IF('Bid Tab (F&B Ops and CatMan) 10'!BS18=Reference!$A$8,'Bid Tab (F&B Ops and CatMan) 10'!BN18,IF('Bid Tab (F&B Ops and CatMan) 10'!BY18=Reference!$A$8,'Bid Tab (F&B Ops and CatMan) 10'!BT18,IF('Bid Tab (F&B Ops and CatMan) 10'!CE18=Reference!$A$8,'Bid Tab (F&B Ops and CatMan) 10'!BZ18,IF('Bid Tab (F&B Ops and CatMan) 10'!CK18=Reference!$A$8,'Bid Tab (F&B Ops and CatMan) 10'!CF18,IF('Bid Tab (F&B Ops and CatMan) 10'!CQ18=Reference!$A$8,'Bid Tab (F&B Ops and CatMan) 10'!CL18,0)))))))))) -> 0 | G25: Cavin Hexane Mandilag | H25: Rowie Marie Caudilla | I25: Jennifer Enrile | J25: Jeric Conway Miranda | K25: Ricardo Aguas, Jr.
A26: =IF('Bid Tab (F&B Ops and CatMan) 10'!AO19=Reference!$A$8,'Bid Tab (F&B Ops and CatMan) 10'!AJ19,IF('Bid Tab (F&B Ops and CatMan) 10'!AU19=Reference!$A$8,'Bid Tab (F&B Ops and CatMan) 10'!AP19,IF('Bid Tab (F&B Ops and CatMan) 10'!BA19=Reference!$A$8,'Bid Tab (F&B Ops and CatMan) 10'!AV19,IF('Bid Tab (F&B Ops and CatMan) 10'!BG19=Reference!$A$8,'Bid Tab (F&B Ops and CatMan) 10'!BB19,IF('Bid Tab (F&B Ops and CatMan) 10'!BM19=Reference!$A$8,'Bid Tab (F&B Ops and CatMan) 10'!BH19,IF('Bid Tab (F&B Ops and CatMan) 10'!BS19=Reference!$A$8,'Bid Tab (F&B Ops and CatMan) 10'!BN19,IF('Bid Tab (F&B Ops and CatMan) 10'!BY19=Reference!$A$8,'Bid Tab (F&B Ops and CatMan) 10'!BT19,IF('Bid Tab (F&B Ops and CatMan) 10'!CE19=Reference!$A$8,'Bid Tab (F&B Ops and CatMan) 10'!BZ19,IF('Bid Tab (F&B Ops and CatMan) 10'!CK19=Reference!$A$8,'Bid Tab (F&B Ops and CatMan) 10'!CF19,IF('Bid Tab (F&B Ops and CatMan) 10'!CQ19=Reference!$A$8,'Bid Tab (F&B Ops and CatMan) 10'!CL19,0)))))))))) -> 0 | G26: Guiller Fiestada | H26: Jennifer Enrile | J26: Jeric Conway Miranda | K26: Ricardo Aguas, Jr.
A27: =IF('Bid Tab (F&B Ops and CatMan) 10'!AO20=Reference!$A$8,'Bid Tab (F&B Ops and CatMan) 10'!AJ20,IF('Bid Tab (F&B Ops and CatMan) 10'!AU20=Reference!$A$8,'Bid Tab (F&B Ops and CatMan) 10'!AP20,IF('Bid Tab (F&B Ops and CatMan) 10'!BA20=Reference!$A$8,'Bid Tab (F&B Ops and CatMan) 10'!AV20,IF('Bid Tab (F&B Ops and CatMan) 10'!BG20=Reference!$A$8,'Bid Tab (F&B Ops and CatMan) 10'!BB20,IF('Bid Tab (F&B Ops and CatMan) 10'!BM20=Reference!$A$8,'Bid Tab (F&B Ops and CatMan) 10'!BH20,IF('Bid Tab (F&B Ops and CatMan) 10'!BS20=Reference!$A$8,'Bid Tab (F&B Ops and CatMan) 10'!BN20,IF('Bid Tab (F&B Ops and CatMan) 10'!BY20=Reference!$A$8,'Bid Tab (F&B Ops and CatMan) 10'!BT20,IF('Bid Tab (F&B Ops and CatMan) 10'!CE20=Reference!$A$8,'Bid Tab (F&B Ops and CatMan) 10'!BZ20,IF('Bid Tab (F&B Ops and CatMan) 10'!CK20=Reference!$A$8,'Bid Tab (F&B Ops and CatMan) 10'!CF20,IF('Bid Tab (F&B Ops and CatMan) 10'!CQ20=Reference!$A$8,'Bid Tab (F&B Ops and CatMan) 10'!CL20,0)))))))))) -> 0 | G27: Jennifer Enrile | J27: Jeric Conway Miranda | K27: Ricardo Aguas, Jr.
A28: =IF('Bid Tab (F&B Ops and CatMan) 10'!AO21=Reference!$A$8,'Bid Tab (F&B Ops and CatMan) 10'!AJ21,IF('Bid Tab (F&B Ops and CatMan) 10'!AU21=Reference!$A$8,'Bid Tab (F&B Ops and CatMan) 10'!AP21,IF('Bid Tab (F&B Ops and CatMan) 10'!BA21=Reference!$A$8,'Bid Tab (F&B Ops and CatMan) 10'!AV21,IF('Bid Tab (F&B Ops and CatMan) 10'!BG21=Reference!$A$8,'Bid Tab (F&B Ops and CatMan) 10'!BB21,IF('Bid Tab (F&B Ops and CatMan) 10'!BM21=Reference!$A$8,'Bid Tab (F&B Ops and CatMan) 10'!BH21,IF('Bid Tab (F&B Ops and CatMan) 10'!BS21=Reference!$A$8,'Bid Tab (F&B Ops and CatMan) 10'!BN21,IF('Bid Tab (F&B Ops and CatMan) 10'!BY21=Reference!$A$8,'Bid Tab (F&B Ops and CatMan) 10'!BT21,IF('Bid Tab (F&B Ops and CatMan) 10'!CE21=Reference!$A$8,'Bid Tab (F&B Ops and CatMan) 10'!BZ21,IF('Bid Tab (F&B Ops and CatMan) 10'!CK21=Reference!$A$8,'Bid Tab (F&B Ops and CatMan) 10'!CF21,IF('Bid Tab (F&B Ops and CatMan) 10'!CQ21=Reference!$A$8,'Bid Tab (F&B Ops and CatMan) 10'!CL21,0)))))))))) -> 0 | G28: Jevalyn Cueva | H28: Rowie Marie Caudilla | I28: Jennifer Enrile | J28: Jeric Conway Miranda | K28: Ricardo Aguas, Jr.
A29: =IF('Bid Tab (F&B Ops and CatMan) 10'!AO22=Reference!$A$8,'Bid Tab (F&B Ops and CatMan) 10'!AJ22,IF('Bid Tab (F&B Ops and CatMan) 10'!AU22=Reference!$A$8,'Bid Tab (F&B Ops and CatMan) 10'!AP22,IF('Bid Tab (F&B Ops and CatMan) 10'!BA22=Reference!$A$8,'Bid Tab (F&B Ops and CatMan) 10'!AV22,IF('Bid Tab (F&B Ops and CatMan) 10'!BG22=Reference!$A$8,'Bid Tab (F&B Ops and CatMan) 10'!BB22,IF('Bid Tab (F&B Ops and CatMan) 10'!BM22=Reference!$A$8,'Bid Tab (F&B Ops and CatMan) 10'!BH22,IF('Bid Tab (F&B Ops and CatMan) 10'!BS22=Reference!$A$8,'Bid Tab (F&B Ops and CatMan) 10'!BN22,IF('Bid Tab (F&B Ops and CatMan) 10'!BY22=Reference!$A$8,'Bid Tab (F&B Ops and CatMan) 10'!BT22,IF('Bid Tab (F&B Ops and CatMan) 10'!CE22=Reference!$A$8,'Bid Tab (F&B Ops and CatMan) 10'!BZ22,IF('Bid Tab (F&B Ops and CatMan) 10'!CK22=Reference!$A$8,'Bid Tab (F&B Ops and CatMan) 10'!CF22,IF('Bid Tab (F&B Ops and CatMan) 10'!CQ22=Reference!$A$8,'Bid Tab (F&B Ops and CatMan) 10'!CL22,0)))))))))) -> 0 | G29: JM Villacorte | H29: Jennifer Enrile | J29: Jeric Conway Miranda | K29: Ricardo Aguas, Jr.
A30: =IF('Bid Tab (F&B Ops and CatMan) 10'!AO23=Reference!$A$8,'Bid Tab (F&B Ops and CatMan) 10'!AJ23,IF('Bid Tab (F&B Ops and CatMan) 10'!AU23=Reference!$A$8,'Bid Tab (F&B Ops and CatMan) 10'!AP23,IF('Bid Tab (F&B Ops and CatMan) 10'!BA23=Reference!$A$8,'Bid Tab (F&B Ops and CatMan) 10'!AV23,IF('Bid Tab (F&B Ops and CatMan) 10'!BG23=Reference!$A$8,'Bid Tab (F&B Ops and CatMan) 10'!BB23,IF('Bid Tab (F&B Ops and CatMan) 10'!BM23=Reference!$A$8,'Bid Tab (F&B Ops and CatMan) 10'!BH23,IF('Bid Tab (F&B Ops and CatMan) 10'!BS23=Reference!$A$8,'Bid Tab (F&B Ops and CatMan) 10'!BN23,IF('Bid Tab (F&B Ops and CatMan) 10'!BY23=Reference!$A$8,'Bid Tab (F&B Ops and CatMan) 10'!BT23,IF('Bid Tab (F&B Ops and CatMan) 10'!CE23=Reference!$A$8,'Bid Tab (F&B Ops and CatMan) 10'!BZ23,IF('Bid Tab (F&B Ops and CatMan) 10'!CK23=Reference!$A$8,'Bid Tab (F&B Ops and CatMan) 10'!CF23,IF('Bid Tab (F&B Ops and CatMan) 10'!CQ23=Reference!$A$8,'Bid Tab (F&B Ops and CatMan) 10'!CL23,0)))))))))) -> 0 | G30: Michael Yves Valdez | H30: Guiller Fiestada | I30: Jennifer Enrile | J30: Jeric Conway Miranda | K30: Ricardo Aguas, Jr.
A31: =IF('Bid Tab (F&B Ops and CatMan) 10'!AO24=Reference!$A$8,'Bid Tab (F&B Ops and CatMan) 10'!AJ24,IF('Bid Tab (F&B Ops and CatMan) 10'!AU24=Reference!$A$8,'Bid Tab (F&B Ops and CatMan) 10'!AP24,IF('Bid Tab (F&B Ops and CatMan) 10'!BA24=Reference!$A$8,'Bid Tab (F&B Ops and CatMan) 10'!AV24,IF('Bid Tab (F&B Ops and CatMan) 10'!BG24=Reference!$A$8,'Bid Tab (F&B Ops and CatMan) 10'!BB24,IF('Bid Tab (F&B Ops and CatMan) 10'!BM24=Reference!$A$8,'Bid Tab (F&B Ops and CatMan) 10'!BH24,IF('Bid Tab (F&B Ops and CatMan) 10'!BS24=Reference!$A$8,'Bid Tab (F&B Ops and CatMan) 10'!BN24,IF('Bid Tab (F&B Ops and CatMan) 10'!BY24=Reference!$A$8,'Bid Tab (F&B Ops and CatMan) 10'!BT24,IF('Bid Tab (F&B Ops and CatMan) 10'!CE24=Reference!$A$8,'Bid Tab (F&B Ops and CatMan) 10'!BZ24,IF('Bid Tab (F&B Ops and CatMan) 10'!CK24=Reference!$A$8,'Bid Tab (F&B Ops and CatMan) 10'!CF24,IF('Bid Tab (F&B Ops and CatMan) 10'!CQ24=Reference!$A$8,'Bid Tab (F&B Ops and CatMan) 10'!CL24,0)))))))))) -> 0 | G31: Narrizza Esteves | H31: JM Villacorte | I31: Jennifer Enrile | J31: Jeric Conway Miranda | K31: Ricardo Aguas, Jr.
A32: =IF('Bid Tab (F&B Ops and CatMan) 10'!AO25=Reference!$A$8,'Bid Tab (F&B Ops and CatMan) 10'!AJ25,IF('Bid Tab (F&B Ops and CatMan) 10'!AU25=Reference!$A$8,'Bid Tab (F&B Ops and CatMan) 10'!AP25,IF('Bid Tab (F&B Ops and CatMan) 10'!BA25=Reference!$A$8,'Bid Tab (F&B Ops and CatMan) 10'!AV25,IF('Bid Tab (F&B Ops and CatMan) 10'!BG25=Reference!$A$8,'Bid Tab (F&B Ops and CatMan) 10'!BB25,IF('Bid Tab (F&B Ops and CatMan) 10'!BM25=Reference!$A$8,'Bid Tab (F&B Ops and CatMan) 10'!BH25,IF('Bid Tab (F&B Ops and CatMan) 10'!BS25=Reference!$A$8,'Bid Tab (F&B Ops and CatMan) 10'!BN25,IF('Bid Tab (F&B Ops and CatMan) 10'!BY25=Reference!$A$8,'Bid Tab (F&B Ops and CatMan) 10'!BT25,IF('Bid Tab (F&B Ops and CatMan) 10'!CE25=Reference!$A$8,'Bid Tab (F&B Ops and CatMan) 10'!BZ25,IF('Bid Tab (F&B Ops and CatMan) 10'!CK25=Reference!$A$8,'Bid Tab (F&B Ops and CatMan) 10'!CF25,IF('Bid Tab (F&B Ops and CatMan) 10'!CQ25=Reference!$A$8,'Bid Tab (F&B Ops and CatMan) 10'!CL25,0)))))))))) -> 0 | G32: Remilyn Lopez | H32: JM Villacorte | I32: Jennifer Enrile | J32: Jeric Conway Miranda | K32: Ricardo Aguas, Jr.
A33: =IF('Bid Tab (F&B Ops and CatMan) 10'!AO26=Reference!$A$8,'Bid Tab (F&B Ops and CatMan) 10'!AJ26,IF('Bid Tab (F&B Ops and CatMan) 10'!AU26=Reference!$A$8,'Bid Tab (F&B Ops and CatMan) 10'!AP26,IF('Bid Tab (F&B Ops and CatMan) 10'!BA26=Reference!$A$8,'Bid Tab (F&B Ops and CatMan) 10'!AV26,IF('Bid Tab (F&B Ops and CatMan) 10'!BG26=Reference!$A$8,'Bid Tab (F&B Ops and CatMan) 10'!BB26,IF('Bid Tab (F&B Ops and CatMan) 10'!BM26=Reference!$A$8,'Bid Tab (F&B Ops and CatMan) 10'!BH26,IF('Bid Tab (F&B Ops and CatMan) 10'!BS26=Reference!$A$8,'Bid Tab (F&B Ops and CatMan) 10'!BN26,IF('Bid Tab (F&B Ops and CatMan) 10'!BY26=Reference!$A$8,'Bid Tab (F&B Ops and CatMan) 10'!BT26,IF('Bid Tab (F&B Ops and CatMan) 10'!CE26=Reference!$A$8,'Bid Tab (F&B Ops and CatMan) 10'!BZ26,IF('Bid Tab (F&B Ops and CatMan) 10'!CK26=Reference!$A$8,'Bid Tab (F&B Ops and CatMan) 10'!CF26,IF('Bid Tab (F&B Ops and CatMan) 10'!CQ26=Reference!$A$8,'Bid Tab (F&B Ops and CatMan) 10'!CL26,0)))))))))) -> 0 | G33: Rhodeza Villaluna | H33: Sara Jane Pontero | I33: Jennifer Enrile | J33: Jeric Conway Miranda | K33: Ricardo Aguas, Jr.
A34: =IF('Bid Tab (F&B Ops and CatMan) 10'!AO27=Reference!$A$8,'Bid Tab (F&B Ops and CatMan) 10'!AJ27,IF('Bid Tab (F&B Ops and CatMan) 10'!AU27=Reference!$A$8,'Bid Tab (F&B Ops and CatMan) 10'!AP27,IF('Bid Tab (F&B Ops and CatMan) 10'!BA27=Reference!$A$8,'Bid Tab (F&B Ops and CatMan) 10'!AV27,IF('Bid Tab (F&B Ops and CatMan) 10'!BG27=Reference!$A$8,'Bid Tab (F&B Ops and CatMan) 10'!BB27,IF('Bid Tab (F&B Ops and CatMan) 10'!BM27=Reference!$A$8,'Bid Tab (F&B Ops and CatMan) 10'!BH27,IF('Bid Tab (F&B Ops and CatMan) 10'!BS27=Reference!$A$8,'Bid Tab (F&B Ops and CatMan) 10'!BN27,IF('Bid Tab (F&B Ops and CatMan) 10'!BY27=Reference!$A$8,'Bid Tab (F&B Ops and CatMan) 10'!BT27,IF('Bid Tab (F&B Ops and CatMan) 10'!CE27=Reference!$A$8,'Bid Tab (F&B Ops and CatMan) 10'!BZ27,IF('Bid Tab (F&B Ops and CatMan) 10'!CK27=Reference!$A$8,'Bid Tab (F&B Ops and CatMan) 10'!CF27,IF('Bid Tab (F&B Ops and CatMan) 10'!CQ27=Reference!$A$8,'Bid Tab (F&B Ops and CatMan) 10'!CL27,0)))))))))) -> 0 | G34: Rizzaro Dayrit | H34: JM Villacorte | I34: Jennifer Enrile | J34: Jeric Conway Miranda | K34: Ricardo Aguas, Jr.
A35: =IF('Bid Tab (F&B Ops and CatMan) 10'!AO28=Reference!$A$8,'Bid Tab (F&B Ops and CatMan) 10'!AJ28,IF('Bid Tab (F&B Ops and CatMan) 10'!AU28=Reference!$A$8,'Bid Tab (F&B Ops and CatMan) 10'!AP28,IF('Bid Tab (F&B Ops and CatMan) 10'!BA28=Reference!$A$8,'Bid Tab (F&B Ops and CatMan) 10'!AV28,IF('Bid Tab (F&B Ops and CatMan) 10'!BG28=Reference!$A$8,'Bid Tab (F&B Ops and CatMan) 10'!BB28,IF('Bid Tab (F&B Ops and CatMan) 10'!BM28=Reference!$A$8,'Bid Tab (F&B Ops and CatMan) 10'!BH28,IF('Bid Tab (F&B Ops and CatMan) 10'!BS28=Reference!$A$8,'Bid Tab (F&B Ops and CatMan) 10'!BN28,IF('Bid Tab (F&B Ops and CatMan) 10'!BY28=Reference!$A$8,'Bid Tab (F&B Ops and CatMan) 10'!BT28,IF('Bid Tab (F&B Ops and CatMan) 10'!CE28=Reference!$A$8,'Bid Tab (F&B Ops and CatMan) 10'!BZ28,IF('Bid Tab (F&B Ops and CatMan) 10'!CK28=Reference!$A$8,'Bid Tab (F&B Ops and CatMan) 10'!CF28,IF('Bid Tab (F&B Ops and CatMan) 10'!CQ28=Reference!$A$8,'Bid Tab (F&B Ops and CatMan) 10'!CL28,0)))))))))) -> 0 | G35: Rowie Marie Caudilla | H35: Jennifer Enrile | J35: Jeric Conway Miranda | K35: Ricardo Aguas, Jr.
A36: =IF('Bid Tab (F&B Ops and CatMan) 10'!AO29=Reference!$A$8,'Bid Tab (F&B Ops and CatMan) 10'!AJ29,IF('Bid Tab (F&B Ops and CatMan) 10'!AU29=Reference!$A$8,'Bid Tab (F&B Ops and CatMan) 10'!AP29,IF('Bid Tab (F&B Ops and CatMan) 10'!BA29=Reference!$A$8,'Bid Tab (F&B Ops and CatMan) 10'!AV29,IF('Bid Tab (F&B Ops and CatMan) 10'!BG29=Reference!$A$8,'Bid Tab (F&B Ops and CatMan) 10'!BB29,IF('Bid Tab (F&B Ops and CatMan) 10'!BM29=Reference!$A$8,'Bid Tab (F&B Ops and CatMan) 10'!BH29,IF('Bid Tab (F&B Ops and CatMan) 10'!BS29=Reference!$A$8,'Bid Tab (F&B Ops and CatMan) 10'!BN29,IF('Bid Tab (F&B Ops and CatMan) 10'!BY29=Reference!$A$8,'Bid Tab (F&B Ops and CatMan) 10'!BT29,IF('Bid Tab (F&B Ops and CatMan) 10'!CE29=Reference!$A$8,'Bid Tab (F&B Ops and CatMan) 10'!BZ29,IF('Bid Tab (F&B Ops and CatMan) 10'!CK29=Reference!$A$8,'Bid Tab (F&B Ops and CatMan) 10'!CF29,IF('Bid Tab (F&B Ops and CatMan) 10'!CQ29=Reference!$A$8,'Bid Tab (F&B Ops and CatMan) 10'!CL29,0)))))))))) -> 0 | G36: Sara Jane Pontero | H36: Jennifer Enrile | J36: Jeric Conway Miranda | K36: Ricardo Aguas, Jr.
A37: =IF('Bid Tab (F&B Ops and CatMan) 10'!AO30=Reference!$A$8,'Bid Tab (F&B Ops and CatMan) 10'!AJ30,IF('Bid Tab (F&B Ops and CatMan) 10'!AU30=Reference!$A$8,'Bid Tab (F&B Ops and CatMan) 10'!AP30,IF('Bid Tab (F&B Ops and CatMan) 10'!BA30=Reference!$A$8,'Bid Tab (F&B Ops and CatMan) 10'!AV30,IF('Bid Tab (F&B Ops and CatMan) 10'!BG30=Reference!$A$8,'Bid Tab (F&B Ops and CatMan) 10'!BB30,IF('Bid Tab (F&B Ops and CatMan) 10'!BM30=Reference!$A$8,'Bid Tab (F&B Ops and CatMan) 10'!BH30,IF('Bid Tab (F&B Ops and CatMan) 10'!BS30=Reference!$A$8,'Bid Tab (F&B Ops and CatMan) 10'!BN30,IF('Bid Tab (F&B Ops and CatMan) 10'!BY30=Reference!$A$8,'Bid Tab (F&B Ops and CatMan) 10'!BT30,IF('Bid Tab (F&B Ops and CatMan) 10'!CE30=Reference!$A$8,'Bid Tab (F&B Ops and CatMan) 10'!BZ30,IF('Bid Tab (F&B Ops and CatMan) 10'!CK30=Reference!$A$8,'Bid Tab (F&B Ops and CatMan) 10'!CF30,IF('Bid Tab (F&B Ops and CatMan) 10'!CQ30=Reference!$A$8,'Bid Tab (F&B Ops and CatMan) 10'!CL30,0)))))))))) -> 0 | G37: Brian Anthony Macalindong | J37: Shellame Palaganas | K37: Ricardo Aguas, Jr.
G38: Dan Errol Bavar | H38: Robert Tyron Samson | J38: Shellame Palaganas | K38: Ricardo Aguas, Jr.
G39: Danica Cruz | H39: Frederick Zulueta | J39: Shellame Palaganas | K39: Ricardo Aguas, Jr.
G40: Enryl Centeno | H40: Robert Tyron Samson | J40: Shellame Palaganas | K40: Ricardo Aguas, Jr.
G41: Frederick Zulueta | J41: Shellame Palaganas | K41: Ricardo Aguas, Jr.
G42: Jay Ramos | H42: Frederick Zulueta | J42: Shellame Palaganas | K42: Ricardo Aguas, Jr.
G43: Jazel Sibal | H43: Brian Anthony Macalindong | J43: Shellame Palaganas | K43: Ricardo Aguas, Jr.
G44: Jexxel Hernandez | H44: Brian Anthony Macalindong | J44: Shellame Palaganas | K44: Ricardo Aguas, Jr.
G45: John Vincent Dimaunahan | H45: Brian Anthony Macalindong | J45: Shellame Palaganas | K45: Ricardo Aguas, Jr.
G46: Jonar Manzano | H46: Robert Tyron Samson | J46: Shellame Palaganas | K46: Ricardo Aguas, Jr.
G47: Nilo Bendanillo | H47: Brian Anthony Macalindong | J47: Shellame Palaganas | K47: Ricardo Aguas, Jr.
G48: Rey Tobias | H48: Frederick Zulueta | J48: Shellame Palaganas | K48: Ricardo Aguas, Jr.
G49: Reynaldo Sta Rita | H49: Frederick Zulueta | J49: Shellame Palaganas | K49: Ricardo Aguas, Jr.
G50: Robert Tyron Samson | J50: Shellame Palaganas | K50: Ricardo Aguas, Jr.
G51: Shellame Palaganas | K51: Ricardo Aguas, Jr.
G52: Sherwin Jeffrey Lacson | H52: Dan Errol Bavar | I52: Robert Tyron Samson | J52: Shellame Palaganas | K52: Ricardo Aguas, Jr.
G53: Yzcel Ubando | H53: Brian Anthony Macalindong | J53: Shellame Palaganas | K53: Ricardo Aguas, Jr.
G54: Michael Guanzon | H54: Rowie Marie Caudilla | I54: Jennifer Enrile | J54: Jeric Conway Miranda | K54: Ricardo Aguas, Jr.
G55: Mark Lloydwin Bucag | H55: John Vincent Dimaunahan | I55: Brian Anthony Macalindong | J55: Shellame Palaganas | K55: Ricardo Aguas, Jr.
